Workbook

Sheet Disclaimer
B6: Disclaimer:
B8: Português:
B9: - A aba OPERATIONAL INFO contém informações operacionais divulgadas como, por exemplo, ARR, produção de crédito, entre outras
B10: - A aba GAAP-Consolidated-P&L possui o Demonstrativo de Resultado (GAAP)
B11: - A aba GAAP-Consolidated-BS possui o Balanço Patrimonial (GAAP) com a operação de Techfin Desconsolidada
B12: - A aba GAAP-Consolidated-CF possui o Fluxo de Caixa (GAAP) com a operação de Techfin Desconsolidada
B13: - A aba Non-GAAP-Consolidated-P&L possui o EBITDA Consolidado com o resultado da operação de Techfin à 50% em todos os períodos
B14: - A aba Non-GAAP-Techfin-P&L possui o Demonstrativo de Resultado Non-GAAP da Dimensão de Techin sem os efeitos do FIDC
B15: - A aba Non-GAAP-Techfin-BS Techfin wo FIDC possui o Balanço Patrimonial Non-GAAP da Dimensão de Techin sem os efeitos do FIDC
B16: - A aba Non-GAAP-Techfin-CF Techfin wo FIDC possui o Fluxo de Caixa Non-GAAP da Dimensão de Techin sem os efeitos do FIDC
B17: - As informações contidas na aba CONTRIB MGN PRO FORMA demonstram as margens de contribuição Pró-Forma de Business Performance e Techfin, considerando os resultados não auditados de janeiro a maio de 2020 da Supplier, de janeiro a dezembro de 2020 da Tail Target e de janeiro de 2020 a maio de 2021 da RD station.
B18: - As informações contidas na aba IS - 2015 to 2018 estão separadas entre Software e Hardware
... B32: - Information presented in the IS - 2018 to 2020 sheet has the consolidated Income Statements for the years 2018 to 2020

Sheet OPERATIONAL INFO
A1: PORTUGUÊS | B1: ENGLISH
A2: Informações Operacionais | B2: Operational Informations | C2: 1Q21 | D2: 2Q21 | E2: 3Q21 | F2: 4Q21 | G2: 1Q22 | H2: 2Q22 | I2: 3Q22 | J2: 4Q22 | K2: 1Q23 | L2: 2Q23 | M2: 3Q23 | N2: 4Q23 | O2: 1Q24 | P2: 2Q24 | Q2: 3Q24 | R2: 4Q24 | S2: 1Q25 | T2: 2Q25 | U2: 3Q25
A4: Consolidado | B4: Management
A5: ARR (R$ milhões) | B5: ARR (R$ million) | C5: =SUM(C6:C8) -> 2265.3934 | D5: =SUM(D6:D8) -> 2595.1044 | E5: =SUM(E6:E8) -> 2751.9757 | F5: =SUM(F6:F8) -> 3002.5216 | G5: =SUM(G6:G8) -> 3279.5606 | H5: =SUM(H6:H8) -> 3530.9156 | I5: =SUM(I6:I8) -> 3740.0856 | J5: =SUM(J6:J8) -> 3939.8936 | ... U5: =SUM(U6:U8) -> 6270.6186
A6: Baseline | B6: Baseline | C6: 2164.2664 | D6: 2265.3934 | E6: 2595.1044 | F6: 2751.9757 | G6: 3002.5216 | H6: 3297.6396 | I6: 3530.9156 | J6: 3740.0856 | K6: 3939.8936 | L6: 4121.4256 | M6: 4329.5306 | N6: 4496.7136 | O6: 4659.1476 | P6: 4875.6306 | Q6: 5118.2156 | R6: 5291.6646 | S6: 5480.0046 | T6: 5771.7866 | U6: 5985.1126
A7: Adição Líquida de ARR | B7: ARR Net Addition | C7: 87.212 | D7: 117.707 | E7: 156.87131 | F7: 250.54583 | G7: 262.583 | H7: 204.711 | I7: 182.769 | J7: 189.324 | K7: 181.532 | L7: 178.047 | M7: 167.183 | N7: 182.55 | O7: 182.283 | P7: 168.953 | Q7: 173.449 | R7: 188.34 | S7: 278.45 | T7: 213.326 | U7: 220.231
A8: Adição Inorgânica | B8: Inorganic Addition | C8: 13.915 | D8: 212.004 | E8: 0 | F8: 0 | G8: 14.456 | H8: 28.565 | I8: 26.401 | J8: 10.484 | K8: 0 | L8: 30.058 | M8: 0 | N8: -20.116 | O8: 34.2 | P8: 73.632 | Q8: 0 | R8: 0 | S8: 13.332 | T8: 0 | U8: 65.275
A10: Gestão | B10: Management
A11: ARR (R$ milhões) | B11: ARR (R$ million) | C11: =SUM(C12:C14) -> 2262.0264 | D11: =SUM(D12:D14) -> 2379.0674 | E11: =SUM(E12:E14) -> 2515.4387 | F11: =SUM(F12:F14) -> 2750.9316 | G11: =SUM(G12:G14) -> 3028.4536 | H11: =SUM(H12:H14) -> 3243.6256 | I11: =SUM(I12:I14) -> 3429.5126 | J11: =SUM(J12:J14) -> 3613.9356 | ... U11: =SUM(U12:U14) -> 5660.1836
A12: Baseline | B12: Baseline | C12: 2161.0974 | D12: 2262.0264 | E12: 2379.0674 | F12: 2515.4387 | G12: 2750.9316 | H12: 3028.4536 | I12: 3243.6256 | J12: 3429.5126 | K12: 3613.9356 | L12: 3769.1636 | M12: 3915.6896 | N12: 4052.8586 | O12: 4192.4156 | P12: 4385.9996 | Q12: 4606.8996 | R12: 4764.6496 | S12: 4936.4896 | T12: 5206.4376 | U12: 5397.8336
A13: Adição Líquida de ARR | B13: ARR Net Addition | C13: 87.014 | D13: 117.041 | E13: 136.37131 | F13: 235.49283 | G13: 263.066 | H13: 186.607 | I13: 164.501 | J13: 173.939 | K13: 155.228 | L13: 146.526 | M13: 137.169 | N13: 159.673 | O13: 159.384 | P13: 147.268 | Q13: 157.75 | R13: 171.84 | S13: 256.616 | T13: 191.396 | U13: 197.075
A14: Adição Inorgânica | B14: Inorganic Addition | C14: 13.915 | D14: 0 | E14: 0 | F14: 0 | G14: 14.456 | H14: 28.565 | I14: 21.386 | J14: 10.484 | K14: 0 | L14: 0 | M14: 0 | N14: -20.116 | O14: 34.2 | P14: 73.632 | Q14: 0 | R14: 0 | S14: 13.332 | T14: 0 | U14: 65.275
A15: Taxa de Retenção | B15: Retention Rate | C15: 0.9805 | D15: 0.988 | E15: 0.983 | F15: 0.9799 | G15: 0.988 | H15: 0.9849 | I15: 0.9857 | J15: 0.9903 | K15: 0.9797 | L15: 0.9829 | M15: 0.9817 | N15: 0.9754 | O15: 0.9869 | P15: 0.9821 | Q15: 0.9858 | R15: 0.9887 | S15: 0.9828 | T15: 0.9829 | U15: 0.98613
A17: RD Station | B17: RD Station
A18: ARR SaaS (R$ milhões) | B18: SaaS ARR (R$ million) | C18: =SUM(C19:C21) -> 3.367 | D18: =SUM(D19:D21) -> 216.037 | E18: =SUM(E19:E21) -> 236.537 | F18: =SUM(F19:F21) -> 251.59 | G18: =SUM(G19:G21) -> 269.186 | H18: =SUM(H19:H21) -> 287.29 | I18: =SUM(I19:I21) -> 310.573 | J18: =SUM(J19:J21) -> 325.958 | ... U18: =SUM(U19:U21) -> 610.435
A19: Baseline | B19: Baseline | C19: 3.169 | D19: 3.367 | E19: 216.037 | F19: 236.537 | G19: 251.59 | H19: 269.186 | I19: 287.29 | J19: 310.573 | K19: 325.958 | L19: 352.262 | M19: 413.841 | N19: 443.855 | O19: 466.732 | P19: 489.631 | Q19: 511.316 | R19: 527.015 | S19: 543.515 | T19: 565.349 | U19: 587.279
A20: Adição Líquida de ARR | B20: ARR Net Addition | C20: 0.198 | D20: 0.666 | E20: 20.5 | F20: 15.053 | G20: 17.596 | H20: 18.104 | I20: 18.268 | J20: 15.385 | K20: 26.304 | L20: 31.521 | M20: 30.014 | N20: 22.877 | O20: 22.899 | P20: 21.685 | Q20: 15.699 | R20: 16.5 | S20: 21.834 | T20: 21.93 | U20: 23.156
A21: Adição Inorgânica | B21: Inorganic Addition | C21: 0 | D21: 212.004 | E21: 0 | F21: 0 | G21: 0 | H21: 0 | I21: 5.015 | J21: 0 | K21: 0 | L21: 30.058 | M21: 0 | N21: 0 | O21: 0 | P21: 0 | Q21: 0 | R21: 0 | S21: 0 | T21: 0 | U21: 0
A22: Taxa de Retenção SaaS | B22: SaaS Retention Rate | C22: 0.9224 | D22: 0.9745 | E22: 0.979 | F22: 0.977 | G22: 0.9766 | H22: 0.9734 | I22: 0.9714 | J22: 0.9753 | K22: 0.9531 | L22: 0.951 | M22: 0.949 | N22: 0.9506 | O22: 0.9169 | P22: 0.9439 | Q22: 0.944 | R22: 0.9454 | S22: 0.9498 | T22: 0.9474 | U22: 0.9475
A24: Techfin | B24: Techfin
A25: Produção de Crédito (R$ milhões) | B25: Credit Production (R$ million) | C25: 2043.0158 | D25: 2438.294 | E25: 2665.8744 | F25: 2624.2087 | G25: 2562.5826 | H25: 2646.5157 | I25: 2908.7334 | J25: 2702.6311 | K25: 2524.7986 | L25: 2483.3088 | M25: 2885.6232 | N25: 2735.619 | O25: 2618.485 | P25: 2791.1 | Q25: 3047.242 | R25: 3414.679 | S25: 3208.912 | T25: 3237.892 | U25: 3393.912
A26: Prazo médio de Produção de Crédito (dias) | B26: Average Term of Credit Production (days) | C26: 57.18 | D26: 51.9 | E26: 55.25 | F26: 61.41 | G26: 58.41 | H26: 54.03 | I26: 62.49 | J26: 68.81 | K26: 60.83 | L26: 55.9 | M26: 74.14 | N26: 70.27 | O26: 65.02 | P26: 59.52 | Q26: 64.15 | R26: 69.55 | S26: 64.68 | T26: 60.34 | U26: 67.14
A27: Carteira de Crédito Supplier (R$ milhões) | B27: Supplier Funding Cost (R$ million) | C27: 1391.8783 | D27: 1491.0133 | E27: 1584.2727 | F27: 1548.0262 | G27: 1813.5466 | H27: 1763.1342 | I27: 1802.7891 | J27: 1834.3134 | K27: 1965.0837 | L27: 1805.883 | M27: 1978.049 | N27: 2086.9096 | O27: 2325.5598 | P27: 2112.9116 | Q27: 2142.539 | R27: 2152.5246 | S27: 2471.812 | T27: 2472.7102 | U27: 2380.1684
A28: Prazo médio calculado Carteira em dia (dias) | B28: Calculated Average Term of On Due Portfolio (days) | C28: =C30/(C25/90) -> 61.006005 | D28: =D30/(D25/90) -> 54.953952 | E28: =E30/(E25/90) -> 53.415255 | F28: =F30/(F25/90) -> 53.09756 | G28: =G30/(G25/90) -> 62.890183 | H28: =H30/(H25/90) -> 59.390873 | I28: =I30/(I25/90) -> 55.251822 | J28: =J30/(J25/90) -> 60.541684 | ... U28: =U30/(U25/90) -> 61.876009
A29: Direitos Credit. da Supplier por Venc. (Em R$ milhões) | B29: Supplier's Credit Rights by Maturity (In R$ million) | C29: =C38+C39 -> 1392.845 | D29: =D38+D39 -> 1499.527 | E29: =E38+E39 -> 1594.86 | F29: =F38+F39 -> 1566.134 | G29: =G38+G39 -> 1813.547 | H29: =H38+H39 -> 1763.136 | I29: =I38+I39 -> 1802.79 | J29: =J38+J39 -> 1834.3156 | ... U29: =U38+U39 -> 2380.1684
A30: A vencer | B30: On Due | C30: 1384.847 | D30: 1488.821 | E30: 1582.204 | F30: 1548.212 | G30: 1790.681 | H30: 1746.432 | I30: 1785.698 | J30: 1818.0204 | K30: 1950.4056 | L30: 1786.6374 | M30: 1964.7743 | N30: 2069.7873 | O30: 2308.9406 | P30: 2088.8085 | Q30: 2125.3346 | R30: 2120.8833 | S30: 2446.435 | T30: 2427.7873 | U30: 2333.3525
A31: Títulos Vencidos | B31: Notes overdue
A32: Até 30 dias | B32: Up to 30 days | C32: 8.151 | D32: 12.353 | E32: 14.881 | F32: 17.448 | G32: 21.205 | H32: 16.285 | I32: 16.108 | J32: 20.529591 | K32: 14.080934 | L32: 14.608075 | M32: 13.076076 | N32: 15.13229 | O32: 13.30087 | P32: 18.589769 | Q32: 14.33117 | R32: 33.34594 | S32: 22.331 | T32: 43.90649 | U32: 29.93243
A33: de 31 a 60 dias | B33: from 31 to 60 days | C33: 1.315 | D33: 1.929 | E33: 2.138 | F33: 3.933 | G33: 5.704 | H33: 4.097 | I33: 4.2189141 | J33: 5.2642987 | K33: 3.9818165 | L33: 4.5809696 | M33: 4.5020463 | N33: 5.52732 | O33: 4.95896 | P33: 6.4119039 | Q33: 5.05639 | R33: 2.75683 | S33: 7.653 | T33: 5.52404 | U33: 3.83022
A34: de 61 a 90 dias | B34: from 61 to 90 days | C34: 1.222 | D34: 1.459 | E34: 2.037 | F34: 2.874 | G34: 5.296 | H34: 3.485 | I34: 3.8500465 | J34: 6.4600933 | K34: 3.9330058 | L34: 6.2493691 | M34: 3.7782825 | N34: 4.00276 | O34: 4.44359 | P34: 4.2492448 | Q34: 3.3092 | R34: 2.89424 | S34: 3.54 | T34: 4.05755 | U34: 8.92841
A35: de 91 a 180 dias | B35: from 91 to 180 days | C35: 2.167 | D35: 2.682 | E35: 3.604 | F35: 5.27 | G35: 8.255 | H35: 11.503 | I35: 9.18 | J35: 9.6219498 | K35: 18.311 | L35: 15.326625 | M35: 8.4839869 | N35: 10.68817 | O35: 10.15961 | P35: 11.121737 | Q35: 10.35126 | R35: 8.00301 | S35: 7.512 | T35: 10.736 | U35: 26.89417
A36: de 181 a 360 dias | B36: from 181 to 360 days | C36: 7.483 | D36: 3.542 | E36: 4.547 | F36: 6.874 | G36: 7.824 | H36: 11.536 | I36: 16.686 | J36: 18.079806 | K36: 16.579 | L36: 20.262948 | M36: 24.404643 | N36: 21.03753 | O36: 22.87725 | P36: 18.313719 | Q36: 17.16877 | R36: 17.95082 | S36: 15.831 | T36: 12.95949 | U36: 13.23948
A37: mais de 360 dias | B37: over 360 days | C37: 49.504 | D37: 54.681 | E37: 55.755 | F37: 57.25 | G37: 59.101 | H37: 61.206 | I37: 64.958 | J37: 70.638322 | K37: 79.173 | L37: 85.380159 | M37: 93.0808 | N37: 103.63531 | O37: 110.39034 | P37: 122.38778 | Q37: 131.14813 | R37: 137.99645 | S37: 144.569 | T37: 149.10342 | U37: 153.60587
A38: Contas a receber bruto | B38: Gross Trade Receivables | C38: =SUM(C30,C32:C37) -> 1454.689 | D38: =SUM(D30,D32:D37) -> 1565.467 | E38: =SUM(E30,E32:E37) -> 1665.166 | F38: =SUM(F30,F32:F37) -> 1641.861 | G38: =SUM(G30,G32:G37) -> 1898.066 | H38: =SUM(H30,H32:H37) -> 1854.544 | I38: =SUM(I30,I32:I37) -> 1900.699 | J38: =SUM(J30,J32:J37) -> 1948.6145 | ... U38: =SUM(U30,U32:U37) -> 2569.7831
A39: (-) Provisão para perda esperada | B39: Provision for Expected Credit Losses | C39: -61.844 | D39: -65.94 | E39: -70.306 | F39: -75.727 | G39: -84.519 | H39: -91.408 | I39: -97.909 | J39: -114.29884 | K39: -121.374 | L39: -127.14955 | M39: -134.04241 | N39: -142.90106 | O39: -149.51146 | P39: -156.97106 | Q39: -164.16058 | R39: -171.30599 | S39: -176.059 | T39: -181.36415 | U39: -189.6147
A40: Caixa - Operação de Crédito (R$ milhões) | B40: Cash Position - Credit Operation (R$ million) | C40: 305.9428 | D40: 444.69132 | E40: 679.15073 | F40: 523.46124 | G40: 293.55753 | H40: 494.11898 | I40: 629.53824 | J40: 619.2657 | K40: 311.13406 | L40: 784.68239 | M40: 274.95486 | N40: 334.89447 | O40: 189.47522 | P40: 433.0831 | Q40: 386.33089 | R40: 91.23722 | S40: 206.10168 | T40: 195.90543 | U40: 336.45193
A41: Inadimplência acima de 90 dias | B41: Delinquency Rate above 90 days
A42: Techfin | B42: Techfin | C42: 0.0073152 | D42: 0.005 | E42: 0.0063 | F42: =SUM(F35:F36)/SUM(F30:F36) -> 0.0076637105 | G42: =SUM(G35:G36)/SUM(G30:G36) -> 0.0087435052 | H42: =SUM(H35:H36)/SUM(H30:H36) -> 0.012846993 | I42: =SUM(I35:I36)/SUM(I30:I36) -> 0.014090223 | J42: =SUM(J35:J36)/SUM(J30:J36) -> 0.014750856 | K42: =SUM(K35:K36)/SUM(K30:K36) -> 0.017381632 | L42: =SUM(L35:L36)/SUM(L30:L36) -> 0.019261914 | M42: =SUM(M35:M36)/SUM(M30:M36) -> 0.016289408 | ... U42: =SUM(U35:U36)/SUM(U30:U36) -> 0.016610391
A43: Média Brasil | B43: Brazil Average | C43: 0.024 | D43: 0.03 | E43: 0.025 | F43: 0.026 | G43: 0.026 | H43: 0.026 | I43: 0.028 | J43: 0.032 | K43: 0.036 | L43: 0.039 | M43: 0.04 | N43: 0.041 | O43: 0.044 | P43: 0.044 | Q43: 0.045 | R43: 0.045 | S43: 0.046 | T43: 0.051 | U43: 0.054

Sheet GAAP-Consolidated-P&L
A1: PORTUGUÊS | B1: ENGLISH
A2: Demonstração de Resultados GAAP Trimestre (em R$ mil) | B2: GAAP Income Statement Quarter (in R$ thousand) | C2: 1Q21 | D2: 2Q21 | E2: 3Q21 | F2: 4Q21 | G2: 1Q22 | H2: 2Q22 | I2: 3Q22 | J2: 4Q22 | K2: 1Q23 | L2: 2Q23 | M2: 3Q23 | N2: 4Q23 | O2: 1Q24 | P2: 2Q24 | Q2: 3Q24 | R2: 4Q24 | S2: 1Q25 | T2: 2Q25 | U2: 3Q25
A3: Resultado de Gestão | B3: Management Result
A4: Receita Líquida | B4: Net Revenue | C4: =C5+C6 -> 653821 | D4: =D5+D6 -> 672848 | E4: =E5+E6 -> 712293 | F4: =F5+F6 -> 754053 | G4: =G5+G6 -> 819459 | H4: =H5+H6 -> 830971 | I4: =I5+I6 -> 883523 | J4: =J5+J6 -> 908332 | ... U4: =U5+U6 -> 1393406
A5: Recorrente | B5: Recurring | C5: 529041 | D5: 554322 | E5: 583967 | F5: 623285 | G5: 668764 | H5: 705609 | I5: 748781 | J5: 780492 | K5: 800624 | L5: 832012 | M5: 873258 | N5: 899958 | O5: 936972 | P5: 1001235 | Q5: 1045609 | R5: 1090015 | S5: 1160357 | T5: 1198126 | U5: 1266752
A6: Não Recorrente | B6: Non Recurring | C6: =C7+C8 -> 124780 | D6: =D7+D8 -> 118526 | E6: =E7+E8 -> 128326 | F6: =F7+F8 -> 130768 | G6: =G7+G8 -> 150695 | H6: =H7+H8 -> 125362 | I6: =I7+I8 -> 134742 | J6: =J7+J8 -> 127840 | ... U6: =U7+U8 -> 126654
A7: Licenças | B7: License | C7: 58068 | D7: 45732 | E7: 50784 | F7: 53769 | G7: 79385 | H7: 44210 | I7: 51401 | J7: 49367 | K7: 80409 | L7: 48627 | M7: 52576 | N7: 58168 | O7: 76869 | P7: 46755 | Q7: 48932 | R7: 46307 | S7: 67655 | T7: 42415 | U7: 40646
A8: Serviços | B8: Services | C8: 66712 | D8: 72794 | E8: 77542 | F8: 76999 | G8: 71310 | H8: 81152 | I8: 83341 | J8: 78473 | K8: 76093 | L8: 89436 | M8: 94808 | N8: 87369 | O8: 82391 | P8: 88473 | Q8: 85010 | R8: 90389 | S8: 80191 | T8: 86016 | U8: 86008
A9: Custos | B9: Costs | C9: -175325 | D9: -186925 | E9: -195804 | F9: -210201 | G9: -220630 | H9: -229686 | I9: -245051 | J9: -251675 | K9: -251965 | L9: -254841 | M9: -281975 | N9: -292296 | O9: -301244 | P9: -323690 | Q9: -337260 | R9: -348424.33 | S9: -358097 | T9: -375913 | U9: -379155
A10: Lucro Bruto Ajustado | B10: Adjusted Gross Profit | C10: =C9+C4 -> 478496 | D10: =D9+D4 -> 485923 | E10: =E9+E4 -> 516489 | F10: =F9+F4 -> 543852 | G10: =G9+G4 -> 598829 | H10: =H9+H4 -> 601285 | I10: =I9+I4 -> 638472 | J10: =J9+J4 -> 656657 | ... U10: =U9+U4 -> 1014251
A11: Margem Bruta Ajustada | B11: Adjusted Gross Margin | C11: =C10/C4 -> 0.73184557 | D11: =D10/D4 -> 0.72218837 | E11: =E10/E4 -> 0.7251075 | F11: =F10/F4 -> 0.72123843 | G11: =G10/G4 -> 0.73076139 | H11: =H10/H4 -> 0.72359324 | I11: =I10/I4 -> 0.72264333 | J11: =J10/J4 -> 0.7229262 | ... U11: =U10/U4 -> 0.72789338
A12: Pesquisa e Desenvolvimento | B12: Research and Development | C12: -113064 | D12: -119466 | E12: -123470 | F12: -135390 | G12: -140915 | H12: -145620 | I12: -152136 | J12: -163174 | K12: -167399 | L12: -168205 | M12: -169404 | N12: -182290 | O12: -183854 | P12: -187569 | Q12: -195148 | R12: -201698 | S12: -207458 | T12: -222278 | U12: -234667
A13: Provisão para Perda Esperada | B13: Provision for Expected Credit Losses | C13: -4995 | D13: -4622 | E13: -6597 | F13: -2418 | G13: -6573 | H13: -4708 | I13: -7095 | J13: -3628 | K13: -5990 | L13: -8441 | M13: -7693 | N13: -6174 | O13: -10176 | P13: -12165 | Q13: -9114 | R13: -13385 | S13: -13649 | T13: -11299 | U13: -11825
A14: Despesas Comerciais e de Marketing | B14: Sales and Marketing Expenses | C14: -121690 | D14: -124685 | E14: -137011 | F14: -139253 | G14: -155199 | H14: -159047 | I14: -163866 | J14: -167254 | K14: -184294 | L14: -201382 | M14: -202688 | N14: -217888 | O14: -218647 | P14: -228213 | Q14: -230469 | R14: -239723 | S14: -258545 | T14: -273648 | U14: -267582
A15: Despesas Gerais e Administrativas | B15: General and Administrative Expenses | C15: -53998 | D15: -58031 | E15: -57967 | F15: -58674 | G15: -67608 | H15: -73008 | I15: -75490 | J15: -85344 | K15: -76507 | L15: -76941 | M15: -80928 | N15: -86166 | O15: -88176 | P15: -96065 | Q15: -93399 | R15: -99076 | S15: -97727 | T15: -98881 | U15: -110485
A16: Provisão para Contingências | B16: Provision for Contingencies | C16: -9086 | D16: -4803 | E16: -10615 | F16: -7330 | G16: -10936 | H16: -2650 | I16: -5497 | J16: -12870 | K16: -175 | L16: -7118 | M16: -3479 | N16: -9286 | O16: -244 | P16: -5799 | Q16: -4535 | R16: -9864 | S16: -13461 | T16: -2091 | U16: -8670
A17: Outras Receitas Operacionais Líquidas | B17: Other Net Revenues (Expenses) | C17: 1381 | D17: 582 | E17: 2862 | F17: 1641 | G17: -434 | H17: 983 | I17: 865 | J17: 3214 | K17: 1168 | L17: 1103 | M17: 1304 | N17: 3579 | O17: 2539 | P17: 4258 | Q17: 2791 | R17: 6553 | S17: 1655 | T17: 2156 | U17: 3460
A18: EBITDA Ajustado de Gestão | B18: Management Adjusted EBITDA | C18: =C10+SUM(C12:C13,C14:C17) -> 177044 | D18: =D10+SUM(D12:D13,D14:D17) -> 174898 | E18: =E10+SUM(E12:E13,E14:E17) -> 183691 | F18: =F10+SUM(F12:F13,F14:F17) -> 202428 | G18: =G10+SUM(G12:G13,G14:G17) -> 217164 | H18: =H10+SUM(H12:H13,H14:H17) -> 217235 | I18: =I10+SUM(I12:I13,I14:I17) -> 235253 | J18: =J10+SUM(J12:J13,J14:J17) -> 227601 | ... U18: =U10+SUM(U12:U13,U14:U17) -> 384482
A19: % EBITDA Ajustado de Gestão | B19: % Management Adjusted EBITDA | C19: =C18/C$4 -> 0.27078359 | D19: =D18/D$4 -> 0.25993687 | E19: =E18/E$4 -> 0.25788685 | F19: =F18/F$4 -> 0.26845328 | G19: =G18/G$4 -> 0.26500899 | H19: =H18/H$4 -> 0.26142308 | I19: =I18/I$4 -> 0.26626698 | J19: =J18/J$4 -> 0.25057028 | ... U19: =U18/U$4 -> 0.27592963
A20: Itens Extraordinários | B20: Extraordinary Items | C20: =SUM(C21:C29) -> -1972 | D20: =SUM(D21:D29) -> 3738 | E20: =SUM(E21:E29) -> -1447 | F20: =SUM(F21:F29) -> -8643 | G20: =SUM(G21:G29) -> -28178 | H20: =SUM(H21:H29) -> 13788 | I20: =SUM(I21:I29) -> -5278 | J20: =SUM(J21:J29) -> -10145 | ... U20: =SUM(U21:U29) -> -6188
A21: Custos com lay-offs | B21: Extraordinary Layoffs Costs | C21: 0 | D21: 0 | E21: 0 | F21: 0 | G21: 0 | H21: 0 | I21: 0 | J21: 0 | K21: 0 | L21: 0 | M21: 0 | N21: 0 | O21: 0 | P21: 0 | Q21: 0 | R21: 0 | S21: 0 | T21: 0 | U21: 0
A22: Provisões - Não Caixa | B22: Provision Adjustment - Non Cash | C22: 0 | D22: 0 | E22: 0 | F22: 0 | G22: 0 | H22: 0 | I22: 0 | J22: 0 | K22: 0 | L22: 0 | M22: 0 | N22: 0 | O22: 0 | P22: 0 | Q22: 0 | R22: 0 | S22: 0 | T22: 0 | U22: 0
A23: Indenização por Rescisão de Contrato | B23: Indemnity for Termination of Contract | C23: 0 | D23: 0 | E23: 0 | F23: 0 | G23: 0 | H23: 0 | I23: 0 | J23: 0 | K23: 0 | L23: 0 | M23: 0 | N23: 0 | O23: 0 | P23: 0 | Q23: 0 | R23: 0 | S23: 0 | T23: 0 | U23: 0
A24: Ajuste de M&A a Valor Justo | B24: M&A Adjustment at Fair Value | C24: 0 | D24: 834 | E24: 0 | F24: -18943 | G24: -24913 | H24: -1158 | I24: 0 | J24: -498 | K24: -1201 | L24: -5064 | M24: -8256 | N24: 1581 | O24: -14035 | P24: -1551 | Q24: 0 | R24: 7616 | S24: -13486 | T24: 2879 | U24: 0
A25: Perda (Ganho) na Baixa de Ativos | B25: Lost (Earn) in Investment Sale | C25: 0 | D25: 0 | E25: 1156 | F25: 0 | G25: 0 | H25: 0 | I25: 0 | J25: -4689 | K25: 0 | L25: 0 | M25: 0 | N25: 0 | O25: 5892 | P25: 0 | Q25: 8599 | R25: -7333 | S25: -2411 | T25: -1759 | U25: 0
A26: Gastos com Transações de M&A | B26: Expenses with M&A Transactions | C26: -1972 | D26: -5814 | E26: -2603 | F26: -178 | G26: -3265 | H26: -2657 | I26: -5278 | J26: -3963 | K26: -1270 | L26: -1364 | M26: -1492 | N26: -5711 | O26: -2969 | P26: -3935 | Q26: -3101 | R26: -2757 | S26: -1880 | T26: -1222 | U26: -6220
A27: Crédito Tributário | B27: Tax Credit | C27: 0 | D27: 8718 | E27: 0 | F27: 10478 | G27: 0 | H27: 17603 | I27: 0 | J27: -995 | K27: 0 | L27: -863 | M27: 233 | N27: 0 | O27: 0 | P27: 0 | Q27: 0 | R27: 0 | S27: 0 | T27: 0 | U27: 0
A28: Ajuste Extraord. Reestruturação Operacional | B28: Extraord. Adj. - Operatl. Restructuring | C28: 0 | D28: 0 | E28: 0 | F28: 0 | G28: 0 | H28: 0 | I28: 0 | J28: 0 | K28: -3094 | L28: -7347 | M28: -53 | N28: -2046 | O28: -4057 | P28: -60 | Q28: 451 | R28: -4113 | S28: -575 | T28: -3066 | U28: 32
A29: Reoneração da Folha de Pagamento | B29: Adj. - Payroll Tax Surcharge | C29: 0 | D29: 0 | E29: 0 | F29: 0 | G29: 0 | H29: 0 | I29: 0 | J29: 0 | K29: 0 | L29: 0 | M29: 0 | N29: 0 | O29: 0 | P29: 0 | Q29: 0 | R29: -13948.67 | S29: 0 | T29: 0 | U29: 0
A30: EBITDA Gestão | B30: Management EBITDA | C30: =C18+C20 -> 175072 | D30: =D18+D20 -> 178636 | E30: =E18+E20 -> 182244 | F30: =F18+F20 -> 193785 | G30: =G18+G20 -> 188986 | H30: =H18+H20 -> 231023 | I30: =I18+I20 -> 229975 | J30: =J18+J20 -> 217456 | ... U30: =U18+U20 -> 378294
A31: % EBITDA Gestão | B31: % Management EBITDA | C31: =C30/C$4 -> 0.26776748 | D31: =D30/D$4 -> 0.26549235 | E31: =E30/E$4 -> 0.25585539 | F31: =F30/F$4 -> 0.25699122 | G31: =G30/G$4 -> 0.23062289 | H31: =H30/H$4 -> 0.27801572 | I31: =I30/I$4 -> 0.26029317 | J31: =J30/J$4 -> 0.23940145 | ... U31: =U30/U$4 -> 0.27148871
A33: Resultado da RD Station | B33: RD Station Result
A34: Receita Líquida | B34: Net Revenue | C34: =C35+C38 -> 642 | D34: =D35+D38 -> 19299 | E34: =E35+E38 -> 58683 | F34: =F35+F38 -> 63722 | G34: =G35+G38 -> 66345 | H34: =H35+H38 -> 71582 | I34: =I35+I38 -> 78397 | J34: =J35+J38 -> 84231 | ... U34: =U35+U38 -> 161850
A35: Recorrente | B35: Recurring | C35: =C36+C37 -> 777 | D35: =D36+D37 -> 18887 | E35: =E36+E37 -> 57241 | F35: =F36+F37 -> 61991 | G35: =G36+G37 -> 65488 | H35: =H36+H37 -> 70459 | I35: =I36+I37 -> 77073 | J35: =J36+J37 -> 82942 | ... U35: =U36+U37 -> 155796
A36: SaaS | B36: SaaS | C36: 777 | D36: 18887 | E36: 57241 | F36: 61991 | G36: 65488 | H36: 70459 | I36: 76982 | J36: 82841 | K36: 85673 | L36: 93786 | M36: 107377 | N36: 116956 | O36: 121803 | P36: 126691 | Q36: 131238 | R36: 136283 | S36: 137795 | T36: 144781 | U36: 150884
A37: Transacional | B37: Transactional | C37: 0 | D37: 0 | E37: 0 | F37: 0 | G37: 0 | H37: 0 | I37: 91 | J37: 101 | K37: 1111 | L37: 1372 | M37: 1083 | N37: 307 | O37: 1724 | P37: 2578 | Q37: 3220 | R37: 3830 | S37: 4783 | T37: 6403 | U37: 4912
A38: Não Recorrente | B38: Non Recurring | C38: -135 | D38: 412 | E38: 1442 | F38: 1731 | G38: 857 | H38: 1123 | I38: 1324 | J38: 1289 | K38: 1279 | L38: 2925 | M38: 3729 | N38: 4074 | O38: 4026 | P38: 4376 | Q38: 5837 | R38: 5753 | S38: 6288 | T38: 4732 | U38: 6054
A39: Custos | B39: Costs | C39: -62 | D39: -4144 | E39: -14156 | F39: -16018 | G39: -16465 | H39: -16555 | I39: -17876 | J39: -19022 | K39: -20033 | L39: -22179 | M39: -25391 | N39: -27557 | O39: -29428 | P39: -32072 | Q39: -32851 | R39: -33584.67 | S39: -37652 | T39: -39134 | U39: -40254
A40: Lucro Bruto Ajustado | B40: Adjusted Gross Profit | C40: =C39+C34 -> 580 | D40: =D39+D34 -> 15155 | E40: =E39+E34 -> 44527 | F40: =F39+F34 -> 47704 | G40: =G39+G34 -> 49880 | H40: =H39+H34 -> 55027 | I40: =I39+I34 -> 60521 | J40: =J39+J34 -> 65209 | ... U40: =U39+U34 -> 121596
A41: Margem Bruta Ajustada | B41: Adjusted Gross Margin | C41: =C40/C34 -> 0.90342679 | D41: =D40/D34 -> 0.78527385 | E41: =E40/E34 -> 0.75877171 | F41: =F40/F34 -> 0.74862685 | G41: =G40/G34 -> 0.75182757 | H41: =H40/H34 -> 0.76872677 | I41: =I40/I34 -> 0.77198107 | J41: =J40/J34 -> 0.77416866 | ... U41: =U40/U34 -> 0.75128823
A42: Pesquisa e Desenvolvimento | B42: Research and Development | C42: 0 | D42: -3930 | E42: -14343 | F42: -14416 | G42: -16545 | H42: -18944 | I42: -19771 | J42: -21368 | K42: -22708 | L42: -24392 | M42: -26741 | N42: -27620 | O42: -28311 | P42: -29247 | Q42: -27883 | R42: -24552 | S42: -29558 | T42: -30512 | U42: -31948
A43: Provisão para Perda Esperada | B43: Provision for Expected Credit Losses | C43: -55 | D43: -186 | E43: -1771 | F43: 55 | G43: -756 | H43: -1151 | I43: -1483 | J43: -1518 | K43: -1637 | L43: -1697 | M43: -2535 | N43: -2124 | O43: -3061 | P43: -4102 | Q43: -3758 | R43: -2867 | S43: -927 | T43: -2739 | U43: -2505
A44: Despesas Comerciais e de Marketing | B44: Sales and Marketing Expenses | C44: -710 | D44: -6972 | E44: -18644 | F44: -21229 | G44: -21451 | H44: -21669 | I44: -23861 | J44: -27900 | K44: -28065 | L44: -32648 | M44: -35979 | N44: -45523 | O44: -41759 | P44: -44136 | Q44: -43285 | R44: -50331 | S44: -47811 | T44: -49528 | U44: -51804
A45: Despesas Administrativas e Outras | B45: G&A Expenses and Others | C45: 99 | D45: -2620 | E45: -7701 | F45: -11841 | G45: -9839 | H45: -9770 | I45: -10672 | J45: -11634 | K45: -11946 | L45: -13465 | M45: -14680 | N45: -16290 | O45: -15518 | P45: -16397 | Q45: -15082 | R45: -14646 | S45: -15126 | T45: -15782 | U45: -15020
A46: EBITDA Ajustado da RD Station | B46: RD Station Adjusted EBITDA | C46: =C40+SUM(C42,C43,C44,C45) -> -86 | D46: =D40+SUM(D42,D43,D44,D45) -> 1447 | E46: =E40+SUM(E42,E43,E44,E45) -> 2068 | F46: =F40+SUM(F42,F43,F44,F45) -> 273 | G46: =G40+SUM(G42,G43,G44,G45) -> 1289 | H46: =H40+SUM(H42,H43,H44,H45) -> 3493 | I46: =I40+SUM(I42,I43,I44,I45) -> 4734 | J46: =J40+SUM(J42,J43,J44,J45) -> 2789 | ... U46: =U40+SUM(U42,U43,U44,U45) -> 20319
A47: % EBITDA Ajustado da RD Station | B47: % RD Station Adjusted EBITDA | C47: =C46/C$34 -> -0.13395639 | D47: =D46/D$34 -> 0.074977978 | E47: =E46/E$34 -> 0.035240189 | F47: =F46/F$34 -> 0.0042842346 | G47: =G46/G$34 -> 0.019428744 | H47: =H46/H$34 -> 0.048797184 | I47: =I46/I$34 -> 0.060384964 | J47: =J46/J$34 -> 0.033111325 | ... U47: =U46/U$34 -> 0.12554217
A48: Itens Extraordinários | B48: Extraordinary Items | C48: =SUM(C49:C51) -> 0 | D48: =SUM(D49:D51) -> 0 | E48: =SUM(E49:E51) -> 0 | F48: =SUM(F49:F51) -> 0 | G48: =SUM(G49:G51) -> 0 | H48: =SUM(H49:H51) -> 0 | I48: =SUM(I49:I51) -> 0 | J48: =SUM(J49:J51) -> -2099 | ... U48: =SUM(U49:U51) -> -597
A49: Ajuste de M&A a Valor Justo | B49: M&A Adjustment at Fair Value | C49: 0 | D49: 0 | E49: 0 | F49: 0 | G49: 0 | H49: 0 | I49: 0 | J49: -2099 | K49: -20407 | L49: 0 | M49: 395 | N49: -39976 | O49: 0 | P49: -9825 | Q49: -728 | R49: -21553 | S49: 0 | T49: -6641 | U49: 0
A50: Ajuste Extraord. Reestruturação Operacional | B50: Extraord. Adj. - Operatl. Restructuring | C50: 0 | D50: 0 | E50: 0 | F50: 0 | G50: 0 | H50: 0 | I50: 0 | J50: 0 | K50: 0 | L50: 0 | M50: 0 | N50: 0 | O50: 0 | P50: -565 | Q50: 0 | R50: 0 | S50: 0 | T50: -2202 | U50: -597
A51: Reoneração da Folha de Pagamento | B51: Adjustment - Payroll Tax Surcharge | C51: 0 | D51: 0 | E51: 0 | F51: 0 | G51: 0 | H51: 0 | I51: 0 | J51: 0 | K51: 0 | L51: 0 | M51: 0 | N51: 0 | O51: 0 | P51: 0 | Q51: 0 | R51: -1530.33 | S51: 0 | T51: 0 | U51: 0
A52: EBITDA RD Station | B52: RD Station EBITDA | C52: =C46+C48 -> -86 | D52: =D46+D48 -> 1447 | E52: =E46+E48 -> 2068 | F52: =F46+F48 -> 273 | G52: =G46+G48 -> 1289 | H52: =H46+H48 -> 3493 | I52: =I46+I48 -> 4734 | J52: =J46+J48 -> 690 | ... U52: =U46+U48 -> 19722
A53: % EBITDA RD Station | B53: % RD Station EBITDA | C53: =C52/C$34 -> -0.13395639 | D53: =D52/D$34 -> 0.074977978 | E53: =E52/E$34 -> 0.035240189 | F53: =F52/F$34 -> 0.0042842346 | G53: =G52/G$34 -> 0.019428744 | H53: =H52/H$34 -> 0.048797184 | I53: =I52/I$34 -> 0.060384964 | J53: =J52/J$34 -> 0.0081917584 | ... U53: =U52/U$34 -> 0.12185357
A57: Gestão + RD Station | B57: Management + RD Station Result
A58: Receita Líquida | B58: Net Revenue | C58: 664642 | D58: 702431 | E58: 781381 | F58: 828857 | G58: 885804 | H58: 902553 | I58: 961920 | J58: 992563 | K58: 1045189 | L58: 1068158 | M58: 1132831 | N58: 1166832 | O58: 1223785 | P58: 1270108 | Q58: 1319846 | R58: 1372577 | S58: 1457069 | T58: 1482473 | U58: 1555256
A59: Lucro Bruto | B59: Gross Income | C59: 479076 | D59: 501078 | E59: 561016 | F59: 591556 | G59: 648709 | H59: 656312 | I59: 698993 | J59: 721866 | K59: 771906 | L59: 784834 | M59: 825465 | N59: 846979 | O59: 892274 | P59: 914346 | Q59: 949735 | R59: 986138 | S59: 1060863 | T59: 1065214 | U59: 1135633
A60: Margem Bruta | B60: Gross Margin | C60: =C59/C58 -> 0.72080308 | D60: =D59/D58 -> 0.71334836 | E60: =E59/E58 -> 0.71798009 | F60: =F59/F58 -> 0.71370092 | G60: =G59/G58 -> 0.73233921 | H60: =H59/H58 -> 0.72717281 | I60: =I59/I58 -> 0.72666438 | J60: =J59/J58 -> 0.72727474 | ... U60: =U59/U58 -> 0.7301904
A61: Pesquisa e Desenvolvimento | B61: Research and Development | C61: -113064 | D61: -123396 | E61: -137813 | F61: -149806 | G61: -157460 | H61: -164564 | I61: -171907 | J61: -184542 | K61: -190143 | L61: -192597 | M61: -196145 | N61: -209910 | O61: -212165 | P61: -216816 | Q61: -223031 | R61: -232161 | S61: -237033 | T61: -253951 | U61: -266775
A62: Provisão para Perda Esperada | B62: Provision for Expected Credit Losses | C62: -5050 | D62: -4808 | E62: -8368 | F62: -2363 | G62: -7329 | H62: -5859 | I62: -8578 | J62: -5146 | K62: -7627 | L62: -10138 | M62: -10228 | N62: -8298 | O62: -13237 | P62: -16267 | Q62: -12872 | R62: -16252 | S62: -14576 | T62: -14038 | U62: -14330
A63: Despesas Comerciais e de Marketing | B63: Sales and Marketing Expenses | C63: -122400 | D63: -131657 | E63: -155655 | F63: -160482 | G63: -176650 | H63: -180716 | I63: -187727 | J63: -195154 | K63: -213633 | L63: -235073 | M63: -238667 | N63: -263889 | O63: -261583 | P63: -272349 | Q63: -273754 | R63: -295292 | S63: -306460 | T63: -323960 | U63: -319577
A64: Despesas Gerais e Administrativas | B64: General and Administrative Expenses | C64: -55871 | D64: -68206 | E64: -68281 | F64: -70717 | G64: -80814 | H64: -85491 | I64: -91146 | J64: -100979 | K64: -89160 | L64: -91794 | M64: -97250 | N64: -108455 | O64: -108679 | P64: -116163 | Q64: -111215 | R64: -120358 | S64: -114835 | T64: -117087 | U64: -131935
A65: Provisão para Contingências | B65: Provision for Contingencies | C65: -9086 | D65: -4803 | E65: -10615 | F65: -7330 | G65: -10936 | H65: -2690 | I65: -5498 | J65: -12870 | K65: -175 | L65: -7118 | M65: -3479 | N65: -11829 | O65: -337 | P65: -6042 | Q65: -4536 | R65: -9903 | S65: -13470 | T65: -2128 | U65: -8716
A66: Depreciação e Amortização | B66: Depreciation and Amortization | C66: -44130 | D66: -44534 | E66: -55609 | F66: -54911 | G66: -57110 | H66: -58116 | I66: -59635 | J66: -61268 | K66: -62053 | L66: -75709 | M66: -71456 | N66: -73249 | O66: -73375 | P66: -84260 | Q66: -86773 | R66: -81498 | S66: -85427 | T66: -88969 | U66: -93714
A67: Outras Receitas Operacionais Líquidas | B67: Other Net Revenues (Expenses) | C67: 1381 | D67: 11875 | E67: 4028 | F67: -6800 | G67: -25245 | H67: 17524 | I67: 572 | J67: -5029 | K67: -21502 | L67: -4800 | M67: -6227 | N67: -33553 | O67: -5536 | P67: -7734 | Q67: 10747 | R67: -14812 | S67: -14128 | T67: -3237 | U67: 3716
A68: Resultado da Equivalência Patrimônial | B68: Equity Pickup | C68: 0 | D68: -564 | E68: 38 | F68: 0 | G68: 7 | H68: 0 | I68: 0 | J68: -449 | K68: 0 | L68: 0 | M68: 4402 | N68: -1207 | O68: -4261 | P68: -3561 | Q68: 2058 | R68: 4193 | S68: 2974 | T68: 154 | U68: 7401
A70: Lucro antes dos Juros e Impostos (LAJIR) | B70: EBIT | C70: =C59+SUM(C61:C68) -> 130856 | D70: =D59+SUM(D61:D68) -> 134985 | E70: =E59+SUM(E61:E68) -> 128741 | F70: =F59+SUM(F61:F68) -> 139147 | G70: =G59+SUM(G61:G68) -> 133172 | H70: =H59+SUM(H61:H68) -> 176400 | I70: =I59+SUM(I61:I68) -> 175074 | J70: =J59+SUM(J61:J68) -> 156429 | ... U70: =U59+SUM(U61:U68) -> 311703
A72: Resultado Financeiro | B72: Financial Result | C72: =C73+C74 -> -8351 | D72: =D73+D74 -> -13323 | E72: =E73+E74 -> -34046 | F72: =F73+F74 -> 1516 | G72: =G73+G74 -> -702 | H72: =H73+H74 -> 13481 | I72: =I73+I74 -> 2809 | J72: =J73+J74 -> 4932 | ... U72: =U73+U74 -> -1014
A73: Receitas Financeiras | B73: Financial Revenue | C73: 7805 | D73: 12157 | E73: 13297 | F73: 57984 | G73: 77850 | H73: 98694 | I73: 92824 | J73: 92644 | K73: 71435 | L73: 87329 | M73: 104463 | N73: 92271 | O73: 88933 | P73: 67867 | Q73: 67291 | R73: 54023 | S73: 65700 | T73: 73759 | U73: 95863
A74: Despesas Financeiras | B74: Financial Expense | C74: -16156 | D74: -25480 | E74: -47343 | F74: -56468 | G74: -78552 | H74: -85213 | I74: -90015 | J74: -87712 | K74: -92066 | L74: -91031 | M74: -96484 | N74: -93461 | O74: -93628 | P74: -77511 | Q74: -87112 | R74: -69279 | S74: -85052 | T74: -92890 | U74: -96877
A76: Lucro Antes da Tributação (LAIR) | B76: Earnings Before Taxes (EBT) | C76: =C70+C72 -> 122505 | D76: =D70+D72 -> 121662 | E76: =E70+E72 -> 94695 | F76: =F70+F72 -> 140663 | G76: =G70+G72 -> 132470 | H76: =H70+H72 -> 189881 | I76: =I70+I72 -> 177883 | J76: =J70+J72 -> 161361 | ... U76: =U70+U72 -> 310689
A78: Imposto de Renda e Contrib. Social | B78: Income Tax and Social Contribution | C78: =C79+C80 -> -38618 | D78: =D79+D80 -> -36579 | E78: =E79+E80 -> 1654 | F78: =F79+F80 -> -11263 | G78: =G79+G80 -> -36776 | H78: =H79+H80 -> -57087 | I78: =I79+I80 -> -35507 | J78: =J79+J80 -> -11834 | ... U78: =U79+U80 -> -59740
A79: Corrente | B79: Current | C79: -47264 | D79: -26858 | E79: -6902 | F79: -23981 | G79: -42158 | H79: -43068 | I79: -27986 | J79: -40355 | K79: -62675 | L79: -53470 | M79: -22886 | N79: -31727 | O79: -66445 | P79: -56750 | Q79: -28767 | R79: -39824 | S79: -64210 | T79: -32852 | U79: -51129
A80: Diferido | B80: Deferred | C80: 8646 | D80: -9721 | E80: 8556 | F80: 12718 | G80: 5382 | H80: -14019 | I80: -7521 | J80: 28521 | K80: -179 | L80: 335 | M80: 1704 | N80: 22627 | O80: -12044 | P80: -4902 | Q80: 93518 | R80: 23709 | S80: 6098 | T80: -15228 | U80: -8611
A82: Lucro líquido Gestão + RD Station | B82: Management + RD Station Net Income | C82: =C76+C78 -> 83887 | D82: =D76+D78 -> 85083 | E82: =E76+E78 -> 96349 | F82: =F76+F78 -> 129400 | G82: =G76+G78 -> 95694 | H82: =H76+H78 -> 132794 | I82: =I76+I78 -> 142376 | J82: =J76+J78 -> 149527 | ... U82: =U76+U78 -> 250949
A84: Techfin - Lucro (Prejuízo) da Operação Descontinuada | B84: Techfin - Net Income (Loss) from Discontinued Operation | C84: -3242 | D84: -6437 | E84: -7432 | F84: -3571 | G84: -10717 | H84: -3653 | I84: 13392 | J84: 3888 | K84: -5594 | L84: -7935 | M84: 241298 | N84: 0 | O84: -1085 | P84: 0 | Q84: 0 | R84: 0 | S84: 0 | T84: 0 | U84: 0
A85: RJ - Lucro (Prejuízo) da Operação Descontinuada | B85: RJ - Net Income (Loss) from Discontinued Operation | C85: 0 | D85: 0 | E85: 0 | F85: 0 | G85: 0 | H85: 0 | I85: 0 | J85: 0 | K85: 0 | L85: 0 | M85: 0 | N85: 0 | O85: 539 | P85: 847 | Q85: 555 | R85: 839 | S85: 151 | T85: 300 | U85: 593
A87: Lucro líquido Consolidado | B87: Consolidated Net Income | C87: =C82+C84+C85 -> 80645 | D87: =D82+D84+D85 -> 78646 | E87: =E82+E84+E85 -> 88917 | F87: =F82+F84+F85 -> 125829 | G87: =G82+G84+G85 -> 84977 | H87: =H82+H84+H85 -> 129141 | I87: =I82+I84+I85 -> 155768 | J87: =J82+J84+J85 -> 153415 | ... U87: =U82+U84+U85 -> 251542
A88: Lucro Líquido de Não Controladores | B88: Non-Controlling Net Income | C88: 0 | D88: 0 | E88: 0 | F88: -5546 | G88: -5522 | H88: -6748 | I88: -6930 | J88: -5965 | K88: -5426 | L88: -8492 | M88: -7043 | N88: -8654 | O88: -2722 | P88: -5833 | Q88: -4849 | R88: -4526 | S88: -5948 | T88: -6369 | U88: -8233
A89: Lucro Líquido GAAP | B89: GAAP Net Income | C89: =C87+C88 -> 80645 | D89: =D87+D88 -> 78646 | E89: =E87+E88 -> 88917 | F89: =F87+F88 -> 120283 | G89: =G87+G88 -> 79455 | H89: =H87+H88 -> 122393 | I89: =I87+I88 -> 148838 | J89: =J87+J88 -> 147450 | ... U89: =U87+U88 -> 243309
A90: Margem Líquida | B90: Net Margin | C90: =C89/(C$58) -> 0.121336 | D90: =D89/(D$58) -> 0.1119626 | E90: =E89/(E$58) -> 0.11379468 | F90: =F89/(F$58) -> 0.14511912 | G90: =G89/(G$58) -> 0.089698173 | H90: =H89/(H$58) -> 0.13560755 | I90: =I89/(I$58) -> 0.15473012 | J90: =J89/(J$58) -> 0.1485548 | ... U90: =U89/(U$58) -> 0.15644305
A92: Lucro (Prejuízo) - Techfin | B92: Net Income (Loss) - Techfin | C92: =-C84 -> 3242 | D92: =-D84 -> 6437 | E92: =-E84 -> 7432 | F92: =-F84 -> 3571 | G92: =-G84 -> 10717 | H92: =-H84 -> 3653 | I92: =-I84 -> -13392 | J92: =-J84 -> -3888 | ... U92: =-U84 -> 0
A93: Lucro (Prejuízo) - RJ | B93: Net Income (Loss) - RJ | C93: =-C85 -> 0 | D93: =-D85 -> 0 | E93: =-E85 -> 0 | F93: =-F85 -> 0 | G93: =-G85 -> 0 | H93: =-H85 -> 0 | I93: =-I85 -> 0 | J93: =-J85 -> 0 | ... U93: =-U85 -> -593
A94: Imposto de Renda e Contribuição Social | B94: Income Tax and Social Contribution | C94: =-C78 -> 38618 | D94: =-D78 -> 36579 | E94: =-E78 -> -1654 | F94: =-F78 -> 11263 | G94: =-G78 -> 36776 | H94: =-H78 -> 57087 | I94: =-I78 -> 35507 | J94: =-J78 -> 11834 | ... U94: =-U78 -> 59740
A95: Resultado Financeiro | B95: Financial Result | C95: =-C72 -> 8351 | D95: =-D72 -> 13323 | E95: =-E72 -> 34046 | F95: =-F72 -> -1516 | G95: =-G72 -> 702 | H95: =-H72 -> -13481 | I95: =-I72 -> -2809 | J95: =-J72 -> -4932 | ... U95: =-U72 -> 1014
A96: Depreciação e Amortização | B96: Depreciation and Amortization | C96: =-C66 -> 44130 | D96: =-D66 -> 44534 | E96: =-E66 -> 55609 | F96: =-F66 -> 54911 | G96: =-G66 -> 57110 | H96: =-H66 -> 58116 | I96: =-I66 -> 59635 | J96: =-J66 -> 61268 | ... U96: =-U66 -> 93714
A98: LAJIDA GAAP | B98: EBITDA GAAP | C98: =C87+SUM(C92:C96) -> 174986 | D98: =D87+SUM(D92:D96) -> 179519 | E98: =E87+SUM(E92:E96) -> 184350 | F98: =F87+SUM(F92:F96) -> 194058 | G98: =G87+SUM(G92:G96) -> 190282 | H98: =H87+SUM(H92:H96) -> 234516 | I98: =I87+SUM(I92:I96) -> 234709 | J98: =J87+SUM(J92:J96) -> 217697 | ... U98: =U87+SUM(U92:U96) -> 405417
A100: Resultado da Equivalência Patrimônial - Techfin | B100: Equity Pickup - Techfin | C100: 0 | D100: 0 | E100: 0 | F100: 0 | G100: 0 | H100: 0 | I100: 0 | J100: 0 | K100: 0 | L100: 0 | M100: =-M68 -> -4402 | N100: =-N68 -> 1207 | O100: =-O68 -> 4261 | P100: =-P68 -> 3561 | Q100: =-Q68 -> -2058 | R100: =-R68 -> -4193 | S100: =-S68 -> -2974 | T100: =-T68 -> -154 | U100: =-U68 -> -7401
A101: Resultado da Equivalência Patrimônial - Outros | B101: Equity Pickup | C101: =-C68 -> 0 | D101: =-D68 -> 564 | E101: =-E68 -> -38 | F101: =-F68 -> 0 | G101: =-G68 -> -7 | H101: =-H68 -> 0 | I101: =-I68 -> 0 | J101: =-J68 -> 449 | ... L101: =-L68 -> 0 | M101: 0 | N101: 0 | O101: 0 | P101: 0 | Q101: 0 | R101: 0 | S101: 0 | T101: 0 | U101: 0
A102: Itens Extraordinários - EBITDA | B102: Extraordinary Items - EBITDA | C102: =SUM(C103:C113) -> 1972 | D102: =SUM(D103:D112) -> -3738 | E102: =SUM(E103:E112) -> 1447 | F102: =SUM(F103:F112) -> 8643 | G102: =SUM(G103:G112) -> 28178 | H102: =SUM(H103:H112) -> -13788 | I102: =SUM(I103:I112) -> 5278 | J102: =SUM(J103:J112) -> 12244 | K102: =SUM(K103:K112) -> 25972 | ... N102: =SUM(N103:N112) -> 46152 | O102: =SUM(O103:O113) -> 15169 | P102: =SUM(P103:P113) -> 15936 | Q102: =SUM(Q103:Q113) -> -5221 | R102: =SUM(R103:R113) -> 43619 | S102: =SUM(S103:S113) -> 18352 | T102: =SUM(T103:T113) -> 12011 | U102: =SUM(U103:U113) -> 6785
A103: Custos com lay-offs | B103: Extraordinary Layoffs Costs | C103: =-C21 -> 0 | D103: =-D21 -> 0 | E103: =-E21 -> 0 | F103: =-F21 -> 0 | G103: =-G21 -> 0 | H103: =-H21 -> 0 | I103: =-I21 -> 0 | J103: =-J21 -> 0 | ... U103: =-U21 -> 0
A104: Provisões - Não Caixa | B104: Provision Adjustment - Non Cash | C104: =-C22 -> 0 | D104: =-D22 -> 0 | E104: =-E22 -> 0 | F104: =-F22 -> 0 | G104: =-G22 -> 0 | H104: =-H22 -> 0 | I104: =-I22 -> 0 | J104: =-J22 -> 0 | ... U104: =-U22 -> 0
A105: Indenização por Rescisão de Contrato | B105: Indemnity for Termination of Contract | C105: =-C23 -> 0 | D105: =-D23 -> 0 | E105: =-E23 -> 0 | F105: =-F23 -> 0 | G105: =-G23 -> 0 | H105: =-H23 -> 0 | I105: =-I23 -> 0 | J105: =-J23 -> 0 | ... U105: =-U23 -> 0
A106: Ajuste de M&A a Valor Justo | B106: M&A Adjustment at Fair Value | C106: =-C24-C49 -> 0 | D106: =-D24-D49 -> -834 | E106: =-E24-E49 -> 0 | F106: =-F24-F49 -> 18943 | G106: =-G24-G49 -> 24913 | H106: =-H24-H49 -> 1158 | I106: =-I24-I49 -> 0 | J106: =-J24-J49 -> 2597 | ... U106: =-U24-U49 -> 0
A107: Perda (Ganho) na Baixa de Ativos | B107: Lost (Earn) in Investment Sale | C107: =-C25 -> 0 | D107: =-D25 -> 0 | E107: =-E25 -> -1156 | F107: =-F25 -> 0 | G107: =-G25 -> 0 | H107: =-H25 -> 0 | I107: =-I25 -> 0 | J107: =-J25 -> 4689 | ... U107: =-U25 -> 0
A108: Gastos com Transações de M&A | B108: Expenses with M&A Transactions | C108: =-C26 -> 1972 | D108: =-D26 -> 5814 | E108: =-E26 -> 2603 | F108: =-F26 -> 178 | G108: =-G26 -> 3265 | H108: =-H26 -> 2657 | I108: =-I26 -> 5278 | J108: =-J26 -> 3963 | ... U108: =-U26 -> 6220
A109: Crédito Tributário | B109: Tax Credit | C109: =-C27 -> 0 | D109: =-D27 -> -8718 | E109: =-E27 -> 0 | F109: =-F27 -> -10478 | G109: =-G27 -> 0 | H109: =-H27 -> -17603 | I109: =-I27 -> 0 | J109: =-J27 -> 995 | ... U109: =-U27 -> 0
A111: Ajuste Extraord. Reestruturação Operacional | B111: Extraord. Adj. - Operatl. Restructuring | C111: =-C50-C28 -> 0 | D111: =-D50-D28 -> 0 | E111: =-E50-E28 -> 0 | F111: =-F50-F28 -> 0 | G111: =-G50-G28 -> 0 | H111: =-H50-H28 -> 0 | I111: =-I50-I28 -> 0 | J111: =-J50-J28 -> 0 | ... U111: =-U50-U28 -> 565
A112: Reoneração da Folha de Pagamento | B112: Adj. - Payroll Tax Surcharge | C112: =-C29-C51 -> 0 | D112: =-D29-D51 -> 0 | E112: =-E29-E51 -> 0 | F112: =-F29-F51 -> 0 | G112: =-G29-G51 -> 0 | H112: =-H29-H51 -> 0 | I112: =-I29-I51 -> 0 | J112: =-J29-J51 -> 0 | ... U112: =-U29-U51 -> 0
A114: EBITDA Ajustado | B114: Adjusted EBITDA | C114: =C98+C101+C102+C100 -> 176958 | D114: =D98+D101+D102+D100 -> 176345 | E114: =E98+E101+E102+E100 -> 185759 | F114: =F98+F101+F102+F100 -> 202701 | G114: =G98+G101+G102+G100 -> 218453 | H114: =H98+H101+H102+H100 -> 220728 | I114: =I98+I101+I102+I100 -> 239987 | J114: =J98+J101+J102+J100 -> 230390 | ... U114: =U98+U101+U102+U100 -> 404801
A116: =A89 -> Lucro Líquido GAAP | B116: =B89 -> GAAP Net Income | C116: =C89 -> 80645 | D116: =D89 -> 78646 | E116: =E89 -> 88917 | F116: =F89 -> 120283 | G116: =G89 -> 79455 | H116: =H89 -> 122393 | ... U116: =U89 -> 243309
A117: Resultado da Operação Descontinuada ajustado | B117: Net Result from Discontinued Operation | C117: ='Non-GAAP-Techfin-P&L'!C25/2-C84 -> 1621 | D117: ='Non-GAAP-Techfin-P&L'!D25/2-D84 -> 3218.5 | E117: ='Non-GAAP-Techfin-P&L'!E25/2-E84 -> 3716 | F117: ='Non-GAAP-Techfin-P&L'!F25/2-F84 -> 1785.5 | G117: ='Non-GAAP-Techfin-P&L'!G25/2-G84 -> 5358.5 | H117: ='Non-GAAP-Techfin-P&L'!H25/2-H84 -> 1826.5 | I117: ='Non-GAAP-Techfin-P&L'!I25/2-I84 -> -6696 | J117: ='Non-GAAP-Techfin-P&L'!J25/2-J84 -> -1944 | ... L117: ='Non-GAAP-Techfin-P&L'!L25/2-L84 -> 3967.5 | M117: ='Non-GAAP-Techfin-P&L'!M25/2-M84-M68 -> -239970.5 | N117: ='Non-GAAP-Techfin-P&L'!N25/2-N84-N68 -> 2.5 | O117: ='Non-GAAP-Techfin-P&L'!O25/2-O84-O68 -> 1084.5 | P117: ='Non-GAAP-Techfin-P&L'!P25/2-P84-P68 -> 0.5 | Q117: ='Non-GAAP-Techfin-P&L'!Q25/2-Q84-Q68 -> 0 | R117: ='Non-GAAP-Techfin-P&L'!R25/2-R84-R68 -> 0 | S117: ='Non-GAAP-Techfin-P&L'!S25/2-S84-S68 -> 0 | T117: ='Non-GAAP-Techfin-P&L'!T25/2-T84-T68 -> -0.5 | U117: ='Non-GAAP-Techfin-P&L'!U25/2-U84-U68 -> 0.5
...

Sheet GAAP-Consolidated-BS
A1: PORTUGUÊS | B1: ENGLISH
A2: Balanço Patrimonial (GAAP) (R$ mil) | B2: GAAP Balance Sheet (R$ thousand) | C2: 1Q18 | D2: 2Q18 | E2: 3Q18 | F2: 4Q18 | G2: 1Q19 | H2: 2Q19 | I2: 3Q19 | J2: 4Q19 | K2: 1Q20 | L2: 2Q20 | M2: 3Q20 | N2: 4Q20 | O2: 1Q21 | P2: 2Q21 | Q2: 3Q21 | R2: 4Q21 | S2: 1Q22 | T2: 2Q22 | U2: 3Q22 | V2: 4Q22 | W2: 1Q23 | X2: 2Q23 | Y2: 3Q23 | Z2: 4Q23 | AA2: 1Q24 | AB2: 2Q24 | AC2: 3Q24 | AD2: 4Q24 | AE2: 1Q25 | AF2: 2Q25 | AG2: 3Q25
A4: ATIVO | B4: ASSETS | C4: =C5+C16 -> 2465242 | D4: =D5+D16 -> 2470229 | E4: =E5+E16 -> 2492641 | F4: =F5+F16 -> 2391277 | G4: =G5+G16 -> 2585845 | H4: =H5+H16 -> 3637843 | I4: =I5+I16 -> 3598169 | J4: =J5+J16 -> 3535927 | ... AG4: =AG5+AG16 -> 9219852
A5: Circulante | B5: Current assets | C5: =SUM(C6:C14) -> 1038781 | D5: =SUM(D6:D14) -> 1062090 | E5: =SUM(E6:E14) -> 1084241 | F5: =SUM(F6:F14) -> 1020134 | G5: =SUM(G6:G14) -> 1026741 | H5: =SUM(H6:H14) -> 2092456 | I5: =SUM(I6:I14) -> 2044020 | J5: =SUM(J6:J14) -> 2004275 | ... AG5: =SUM(AG6:AG14) -> 3145240
A6: Caixa e Equivalentes de Caixa | B6: Cash and Cash Equivalents | C6: 380705 | D6: 394462 | E6: 449606 | F6: 452799 | G6: 423658 | H6: 1494584 | I6: 1487702 | J6: 1538156 | K6: 1365366 | L6: 1263927 | M6: 999800 | N6: 1011638 | O6: 886108 | P6: 645664 | Q6: 2073866 | R6: 2735764 | S6: 2704890 | T6: 2567054 | U6: 2541052 | V6: 2735765 | W6: 2536064 | X6: 2720311 | Y6: 3056726 | Z6: 3129162 | AA6: 2548116 | AB6: 2205225 | AC6: 2154825 | AD6: 1942162 | AE6: 1943040 | AF6: 2094240 | AG6: 2005729
A7: Contas a Receber de Clientes | B7: Trade Receivables | C7: 535212 | D7: 542206 | E7: 536052 | F7: 504056 | G7: 484546 | H7: 476132 | I7: 470151 | J7: 453118 | K7: 460210 | L7: 514723 | M7: 598932 | N7: 630361 | O7: 474786 | P7: 502133 | Q7: 522425 | R7: 500958 | S7: 546459 | T7: 586998 | U7: 595520 | V7: 538199 | W7: 563766 | X7: 595326 | Y7: 617008 | Z7: 600731 | AA7: 642398 | AB7: 643537 | AC7: 647773 | AD7: 625678 | AE7: 714209 | AF7: 734666 | AG7: 736081
A8: Provisão para Perdas Esperadas | B8: Provision for Expected Credit Losses | C8: -107286 | D8: -110472 | E8: -112497 | F8: -118518 | G8: -117040 | H8: -110476 | I8: -109202 | J8: -102123 | K8: -89424 | L8: -90547 | M8: -81506 | N8: -76643 | O8: -79467 | P8: -79615 | Q8: -83918 | R8: -83383 | S8: -69278 | T8: -74831 | U8: -60966 | V8: -62551 | W8: -57532 | X8: -65549 | Y8: -59968 | Z8: -62203 | AA8: -61741 | AB8: -59316 | AC8: -65848 | AD8: -62350 | AE8: -73106 | AF8: -68298 | AG8: -67467
A9: Aplicações Financeiras | B9: Financial Investments | C9: 0 | D9: 0 | E9: 0 | F9: 0 | G9: 0 | H9: 0 | I9: 0 | J9: 0 | K9: 0 | L9: 47348 | M9: 53862 | N9: 161327 | O9: 0 | P9: 0 | Q9: 0 | R9: 0 | S9: 4273 | T9: 4382 | U9: 0 | V9: 0 | W9: 0 | X9: 0 | Y9: 0 | Z9: 0 | AA9: 0 | AB9: 0 | AC9: 0 | AD9: 0 | AE9: 0 | AF9: 0 | AG9: 0
A10: Estoques | B10: Inventory | C10: 41217 | D10: 37647 | E10: 35584 | F10: 41531 | G10: 0 | H10: 0 | I10: 0 | J10: 0 | K10: 0 | L10: 0 | M10: 0 | N10: 0 | O10: 0 | P10: 0 | Q10: 0 | R10: 0 | S10: 0 | T10: 0 | U10: 0 | V10: 0 | W10: 0 | X10: 0 | Y10: 0 | Z10: 0 | AA10: 0 | AB10: 0 | AC10: 0 | AD10: 0 | AE10: 0 | AF10: 0 | AG10: 0
A11: Tributos Correntes a Recuperar | B11: Recoverable Taxes | C11: 86623 | D11: 81224 | E11: 62777 | F11: 38817 | G11: 33674 | H11: 27877 | I11: 12161 | J11: 29662 | K11: 39277 | L11: 18071 | M11: 22384 | N11: 38092 | O11: 29700 | P11: 42302 | Q11: 37209 | R11: 67553 | S11: 78306 | T11: 74013 | U11: 71953 | V11: 87932 | W11: 96001 | X11: 74849 | Y11: 39165 | Z11: 87838 | AA11: 91170 | AB11: 73785 | AC11: 80289 | AD11: 83519 | AE11: 100935 | AF11: 93917 | AG11: 77107
A12: Garantias de Investimentos | B12: Escrow Account | C12: 49882 | D12: 49398 | E12: 46934 | F12: 44909 | G12: 44711 | H12: 45203 | I12: 26188 | J12: 25278 | K12: 10204 | L12: 10260 | M12: 10307 | N12: 10012 | O12: 9718 | P12: 9067 | Q12: 9191 | R12: 9341 | S12: 9593 | T12: 9811 | U12: 11652 | V12: 10391 | W12: 12707 | X12: 12206 | Y12: 13150 | Z12: 13175 | AA12: 13754 | AB12: 19575 | AC12: 13675 | AD12: 13974 | AE12: 14339 | AF12: 19182 | AG12: 46057
A13: Outros Ativos | B13: Othe Assets | C13: 52428 | D13: 67625 | E13: 65785 | F13: 56540 | G13: 69280 | H13: 61930 | I13: 58006 | J13: 60184 | K13: 74344 | L13: 81585 | M13: 64164 | N13: 45903 | O13: 59021 | P13: 91113 | Q13: 99715 | R13: 107739 | S13: 109519 | T13: 149379 | U13: 152408 | V13: 96447 | W13: 117905 | X13: 175915 | Y13: 183842 | Z13: 137595 | AA13: 141752 | AB13: 188107 | AC13: 227792 | AD13: 160575 | AE13: 165450 | AF13: 238249 | AG13: 289915
A14: Ativos Mantidos Para Venda | B14: Assets For Sale | C14: 0 | D14: 0 | E14: 0 | F14: 0 | G14: 87912 | H14: 97206 | I14: 99014 | J14: 0 | K14: 0 | L14: 0 | M14: 0 | N14: 0 | O14: 2230408 | P14: 2475620 | Q14: 2799755 | R14: 2641217 | S14: 2605828 | T14: 2758444 | U14: 2960010 | V14: 2823978 | W14: 2589975 | X14: 2905717 | Y14: 0 | Z14: 0 | AA14: 0 | AB14: 0 | AC14: 0 | AD14: 0 | AE14: 56842 | AF14: 57401 | AG14: 57818
A16: Não circulante | B16: Non-current assets | C16: =C17+SUM(C27:C29) -> 1426461 | D16: =D17+SUM(D27:D29) -> 1408139 | E16: =E17+SUM(E27:E29) -> 1408400 | F16: =F17+SUM(F27:F29) -> 1371143 | G16: =G17+SUM(G27:G29) -> 1559104 | H16: =H17+SUM(H27:H29) -> 1545387 | I16: =I17+SUM(I27:I29) -> 1554149 | J16: =J17+SUM(J27:J29) -> 1531652 | ... AG16: =AG17+SUM(AG27:AG29) -> 6074612
A17: Realizável a longo prazo | B17: Long-term assets | C17: =SUM(C18:C25) -> 296261 | D17: =SUM(D18:D25) -> 291007 | E17: =SUM(E18:E25) -> 289340 | F17: =SUM(F18:F25) -> 312060 | G17: =SUM(G18:G25) -> 299297 | H17: =SUM(H18:H25) -> 309193 | I17: =SUM(I18:I25) -> 345272 | J17: =SUM(J18:J25) -> 328403 | ... AG17: =SUM(AG18:AG25) -> 858902
A18: Contas a Receber de Clientes | B18: Trade Receivables | C18: 31733 | D18: 24860 | E18: 21777 | F18: 19890 | G18: 21672 | H18: 33544 | I18: 36401 | J18: 31627 | K18: 27578 | L18: 39327 | M18: 57679 | N18: 64012 | O18: 55988 | P18: 60881 | Q18: 60254 | R18: 64943 | S18: 56428 | T18: 53515 | U18: 47066 | V18: 38419 | W18: 31655 | X18: 22560 | Y18: 19030 | Z18: 16496 | AA18: 16664 | AB18: 19747 | AC18: 16519 | AD18: 13796 | AE18: 14492 | AF18: 15138 | AG18: 17897
A19: IR e CSLL Diferidos | B19: Deferred Tax Assets | C19: 97839 | D19: 85222 | E19: 80735 | F19: 125124 | G19: 110182 | H19: 104499 | I19: 106412 | J19: 100380 | K19: 78803 | L19: 87059 | M19: 96481 | N19: 100535 | O19: 94718 | P19: 84883 | Q19: 94881 | R19: 107000 | S19: 112661 | T19: 101145 | U19: 96046 | V19: 119048 | W19: 116865 | X19: 117297 | Y19: 123031 | Z19: 147426 | AA19: 138580 | AB19: 136133 | AC19: 231218 | AD19: 253511 | AE19: 256100 | AF19: 245119 | AG19: 243444
A20: Depósitos Judiciais | B20: Judicial Deposits | C20: 60190 | D20: 63863 | E20: 61873 | F20: 65965 | G20: 70399 | H20: 69702 | I20: 73675 | J20: 65059 | K20: 51484 | L20: 50094 | M20: 48789 | N20: 43972 | O20: 44324 | P20: 43617 | Q20: 42157 | R20: 29236 | S20: 28814 | T20: 32129 | U20: 32622 | V20: 34244 | W20: 37644 | X20: 39283 | Y20: 39673 | Z20: 33832 | AA20: 32244 | AB20: 32758 | AC20: 31928 | AD20: 28373 | AE20: 32411 | AF20: 29206 | AG20: 28404
A21: Crédito com Empresas Ligadas | B21: Credit with Related Parties | C21: 0 | D21: 0 | E21: 0 | F21: 0 | G21: 0 | H21: 0 | I21: 0 | J21: 0 | K21: 0 | L21: 0 | M21: 0 | N21: 0 | O21: 0 | P21: 0 | Q21: 0 | R21: 0 | S21: 0 | T21: 0 | U21: 678 | V21: 905 | W21: 1134 | X21: 7214 | Y21: 2507 | Z21: 3787 | AA21: 4997 | AB21: 4876 | AC21: 5231 | AD21: 5050 | AE21: 5817 | AF21: 4746 | AG21: 4739
A22: Tributos a Recuperar | B22: Recoverable taxes | C22: 21752 | D22: 21677 | E22: 21160 | F22: 236 | G22: 207 | H22: 0 | I22: 0 | J22: 0 | K22: 0 | L22: 8139 | M22: 8024 | N22: 0 | O22: 0 | P22: 0 | Q22: 0 | R22: 0 | S22: 0 | T22: 17752 | U22: 18077 | V22: 14216 | W22: 8091 | X22: 4092 | Y22: 1191 | Z22: 0 | AA22: 0 | AB22: 0 | AC22: 0 | AD22: 0 | AE22: 0 | AF22: 0 | AG22: 0
A23: Garantias de Investimentos | B23: Escrow Account | C23: 0 | D23: 0 | E23: 6464 | F23: 5334 | G23: 4368 | H23: 3735 | I23: 2455 | J23: 1987 | K23: 1630 | L23: 1347 | M23: 1141 | N23: 1116 | O23: 0 | P23: 34388 | Q23: 34857 | R23: 35427 | S23: 36386 | T23: 31288 | U23: 43978 | V23: 73766 | W23: 77066 | X23: 81709 | Y23: 114129 | Z23: 116759 | AA23: 178231 | AB23: 179074 | AC23: 181564 | AD23: 188845 | AE23: 182538 | AF23: 183976 | AG23: 192747
A24: Ativos Financeiros | B24: Investiments at Fair Value | C24: 57913 | D24: 67192 | E24: 69772 | F24: 69171 | G24: 69562 | H24: 68411 | I24: 74341 | J24: 71955 | K24: 92805 | L24: 97756 | M24: 100696 | N24: 92770 | O24: 101706 | P24: 89297 | Q24: 97102 | R24: 99621 | S24: 84577 | T24: 96516 | U24: 107067 | V24: 111231 | W24: 108091 | X24: 105384 | Y24: 110891 | Z24: 127483 | AA24: 140657 | AB24: 148965 | AC24: 163523 | AD24: 179830 | AE24: 193669 | AF24: 196743 | AG24: 213101
A25: Outros Ativos | B25: Othe Assets | C25: 26834 | D25: 28193 | E25: 27559 | F25: 26340 | G25: 22907 | H25: 29302 | I25: 51988 | J25: 57395 | K25: 65203 | L25: 60161 | M25: 59154 | N25: 57928 | O25: 61481 | P25: 78855 | Q25: 97814 | R25: 86703 | S25: 81367 | T25: 73645 | U25: 70506 | V25: 71563 | W25: 71662 | X25: 61847 | Y25: 57318 | Z25: 68699 | AA25: 72900 | AB25: 79063 | AC25: 103003 | AD25: 116522 | AE25: 135362 | AF25: 166598 | AG25: 158570
A27: Investimentos | B27: Investments | C27: 2407 | D27: 2589 | E27: 2551 | F27: 3129 | G27: 3054 | H27: 3033 | I27: 3204 | J27: 3120 | K27: 3239 | L27: 3464 | M27: 3402 | N27: 3476 | O27: 3707 | P27: 2797 | Q27: 2982 | R27: 3075 | S27: 2695 | T27: 2943 | U27: 3036 | V27: 0 | W27: 0 | X27: 0 | Y27: 324573 | Z27: 323367 | AA27: 319106 | AB27: 315545 | AC27: 317603 | AD27: 321796 | AE27: 324770 | AF27: 324923 | AG27: 314411
A28: Imobilizado | B28: Property, Plant and Equipment | C28: 185986 | D28: 186075 | E28: 189393 | F28: 198826 | G28: 416837 | H28: 402844 | I28: 388057 | J28: 389432 | K28: 393959 | L28: 387229 | M28: 378120 | N28: 364447 | O28: 388788 | P28: 385111 | Q28: 387470 | R28: 398496 | S28: 407399 | T28: 405241 | U28: 415777 | V28: 416875 | W28: 422161 | X28: 423663 | Y28: 424418 | Z28: 413486 | AA28: 405689 | AB28: 400429 | AC28: 397524 | AD28: 399215 | AE28: 418894 | AF28: 423074 | AG28: 456734
A29: Intangível | B29: Intangible Assets | C29: 941807 | D29: 928468 | E29: 927116 | F29: 857128 | G29: 839916 | H29: 830317 | I29: 817616 | J29: 810697 | K29: 1031418 | L29: 1590955 | M29: 1567313 | N29: 1586177 | O29: 1074309 | P29: 3137086 | Q29: 3149528 | R29: 3141338 | S29: 3283360 | T29: 3329185 | U29: 3492907 | V29: 3505765 | W29: 3502339 | X29: 3641474 | Y29: 3688497 | Z29: 3671227 | AA29: 4339314 | AB29: 4315393 | AC29: 4273733 | AD29: 4261225 | AE29: 4199832 | AF29: 4203673 | AG29: 4444565
A31: PASSIVO | B31: LIABILITIES | C31: =C32+C46+C58 -> 2465242 | D31: =D32+D46+D58 -> 2470229 | E31: =E32+E46+E58 -> 2492641 | F31: =F32+F46+F58 -> 2391277 | G31: =G32+G46+G58 -> 2585845 | H31: =H32+H46+H58 -> 3637843 | I31: =I32+I46+I58 -> 3598169 | J31: =J32+J46+J58 -> 3535927 | ... AG31: =AG32+AG46+AG58 -> 9219852
A32: Circulante | B32: Current liabilities | C32: =SUM(C33:C44) -> 634244 | D32: =SUM(D33:D44) -> 619774 | E32: =SUM(E33:E44) -> 746985 | F32: =SUM(F33:F44) -> 709612 | G32: =SUM(G33:G44) -> 706705 | H32: =SUM(H33:H44) -> 666765 | I32: =SUM(I33:I44) -> 768434 | J32: =SUM(J33:J44) -> 705552 | ... AG32: =SUM(AG33:AG44) -> 1339676
A33: Obrigações Sociais e Trabalhistas | B33: Labor Liabilities | C33: 147531 | D33: 169429 | E33: 192050 | F33: 174874 | G33: 168334 | H33: 190874 | I33: 217227 | J33: 193472 | K33: 190583 | L33: 235415 | M33: 238636 | N33: 211603 | O33: 207906 | P33: 319693 | Q33: 287922 | R33: 273974 | S33: 278175 | T33: 353390 | U33: 349392 | V33: 317684 | W33: 321109 | X33: 406082 | Y33: 414207 | Z33: 375960 | AA33: 407683 | AB33: 478996 | AC33: 473272 | AD33: 438679 | AE33: 442831 | AF33: 547042 | AG33: 544748
A34: Obrigações fiscais | B34: Taxes and Contributions Liabilities | C34: 40465 | D34: 39562 | E34: 41700 | F34: 47466 | G34: 44757 | H34: 53036 | I34: 55511 | J34: 55203 | K34: 53701 | L34: 99969 | M34: 89580 | N34: 74558 | O34: 63785 | P34: 68338 | Q34: 69031 | R34: 73605 | S34: 71857 | T34: 90197 | U34: 87792 | V34: 95042 | W34: 94422 | X34: 97955 | Y34: 110232 | Z34: 107427 | AA34: 116237 | AB34: 119837 | AC34: 113945 | AD34: 122612 | AE34: 121373 | AF34: 131815 | AG34: 134462
A35: Empréstimos e Financiamentos | B35: Loans and Financing | C35: 180979 | D35: 181079 | E35: 181090 | F35: 152927 | G35: 110559 | H35: 67803 | I35: 23333 | J35: 6363 | K35: 3649 | L35: 11071 | M35: 0 | N35: 101525 | O35: 0 | P35: 0 | Q35: 0 | R35: 0 | S35: 0 | T35: 0 | U35: 343 | V35: 170 | W35: 50 | X35: 0 | Y35: 32084 | Z35: 32083 | AA35: 1708 | AB35: 0 | AC35: 0 | AD35: 0 | AE35: 0 | AF35: 0 | AG35: 0
A36: Financiamento por Arrendamento | B36: Lease Liabilities | C36: 18587 | D36: 17834 | E36: 15401 | F36: 13227 | G36: 68150 | H36: 62717 | I36: 49910 | J36: 49260 | K36: 47588 | L36: 47323 | M36: 46785 | N36: 45281 | O36: 53496 | P36: 51429 | Q36: 51197 | R36: 51536 | S36: 58131 | T36: 56672 | U36: 56549 | V36: 57285 | W36: 57636 | X36: 59469 | Y36: 58414 | Z36: 58618 | AA36: 59838 | AB36: 57525 | AC36: 58195 | AD36: 58133 | AE36: 60100 | AF36: 67315 | AG36: 70654
A37: Debêntures | B37: Debentures | C37: 356 | D37: 3717 | E37: 72035 | F37: 77319 | G37: 76238 | H37: 81964 | I37: 200288 | J37: 202973 | K37: 200257 | L37: 403787 | M37: 0 | N37: 0 | O37: 0 | P37: 2993 | Q37: 27365 | R37: 385988 | S37: 430872 | T37: 518245 | U37: 5151 | V37: 58701 | W37: 8728 | X37: 61331 | Y37: 7327 | Z37: 55208 | AA37: 10279 | AB37: 48594 | AC37: 18480 | AD37: 62845 | AE37: 33383 | AF37: 88182 | AG37: 40692
A38: Fornecedores | B38: Trade and Other Payables | C38: 91276 | D38: 95745 | E38: 101543 | F38: 113907 | G38: 70560 | H38: 61544 | I38: 55512 | J38: 63821 | K38: 66238 | L38: 75153 | M38: 91360 | N38: 99109 | O38: 70988 | P38: 102242 | Q38: 108081 | R38: 105376 | S38: 102829 | T38: 102010 | U38: 118006 | V38: 128647 | W38: 112005 | X38: 200244 | Y38: 133117 | Z38: 155266 | AA38: 171433 | AB38: 194614 | AC38: 170444 | AD38: 211971 | AE38: 232230 | AF38: 224300 | AG38: 209380
A39: Comissões a Pagar | B39: Commissions Payable | C39: 45020 | D39: 42231 | E39: 41376 | F39: 43166 | G39: 47429 | H39: 43217 | I39: 44136 | J39: 46035 | K39: 52649 | L39: 47255 | M39: 53831 | N39: 53795 | O39: 60963 | P39: 60568 | Q39: 58838 | R39: 58158 | S39: 67516 | T39: 62330 | U39: 62406 | V39: 65518 | W39: 73849 | X39: 67997 | Y39: 64990 | Z39: 62610 | AA39: 61228 | AB39: 52412 | AC39: 63630 | AD39: 69126 | AE39: 60934 | AF39: 64475 | AG39: 69762
A40: Obrigações por Aquisição de Investimentos | B40: Accounts Payable from Acquisition of Subsidiaries | C40: 87986 | D40: 65641 | E40: 63177 | F40: 59597 | G40: 59398 | H40: 52479 | I40: 33464 | J40: 32554 | K40: 30717 | L40: 33891 | M40: 44174 | N40: 44781 | O40: 29400 | P40: 160230 | Q40: 136737 | R40: 153839 | S40: 95853 | T40: 48706 | U40: 59865 | V40: 52700 | W40: 96737 | X40: 315309 | Y40: 377285 | Z40: 421803 | AA40: 496198 | AB40: 238083 | AC40: 244932 | AD40: 115659 | AE40: 46348 | AF40: 43462 | AG40: 73859
A41: Dividendos e JCP a Pagar | B41: Dividends Payable | C41: 15972 | D41: 613 | E41: 31285 | F41: 13902 | G41: 12293 | H41: 768 | I41: 32828 | J41: 44579 | K41: 39705 | L41: 870 | M41: 36075 | N41: 57687 | O41: 51250 | P41: 1040 | Q41: 46388 | R41: 80153 | S41: 70895 | T41: 1191 | U41: 1270 | V41: 130363 | W41: 3316 | X41: 1432 | Y41: 1628 | Z41: 1781 | AA41: 1781 | AB41: 1781 | AC41: 1055 | AD41: 1222 | AE41: 83248 | AF41: 89324 | AG41: 89576
A42: Outros Passivos | B42: Other Liabilities | C42: 6072 | D42: 3923 | E42: 7328 | F42: 13227 | G42: 6778 | H42: 8800 | I42: 10485 | J42: 11292 | K42: 14546 | L42: 11927 | M42: 9836 | N42: 11592 | O42: 9263 | P42: 66689 | Q42: 83067 | R42: 86981 | S42: 96838 | T42: 114450 | U42: 127262 | V42: 66657 | W42: 80644 | X42: 86703 | Y42: 97882 | Z42: 77973 | AA42: 100887 | AB42: 88291 | AC42: 110038 | AD42: 63950 | AE42: 68302 | AF42: 77558 | AG42: 96720
A43: Repasse para Parceiros | B43: Transfer to Partners | C43: 0 | D43: 0 | E43: 0 | F43: 0 | G43: 0 | H43: 0 | I43: 0 | J43: 0 | K43: 0 | L43: 160843 | M43: 288733 | N43: 328817 | O43: 0 | P43: 0 | Q43: 0 | R43: 0 | S43: 0 | T43: 0 | U43: 0 | V43: 0 | W43: 0 | X43: 0 | Y43: 0 | Z43: 0 | AA43: 0 | AB43: 0 | AC43: 0 | AD43: 0 | AE43: 0 | AF43: 0 | AG43: 0
A44: Passivos Mantidos para Venda | B44: Liabilities for Sale | C44: 0 | D44: 0 | E44: 0 | F44: 0 | G44: 42209 | H44: 43563 | I44: 45740 | J44: 0 | K44: 0 | L44: 0 | M44: 0 | N44: 0 | O44: 1646270 | P44: 1893378 | Q44: 2217587 | R44: 2054172 | S44: 2027434 | T44: 2180375 | U44: 2335779 | V44: 2363599 | W44: 2135385 | X44: 2459248 | Y44: 0 | Z44: 0 | AA44: 0 | AB44: 0 | AC44: 0 | AD44: 0 | AE44: 9645 | AF44: 9846 | AG44: 9823
A46: Não circulante | B46: Non-current liabilities | C46: =SUM(C47:C56) -> 546169 | D46: =SUM(D47:D56) -> 528198 | E46: =SUM(E47:E56) -> 414645 | F46: =SUM(F47:F56) -> 393445 | G46: =SUM(G47:G56) -> 572130 | H46: =SUM(H47:H56) -> 565358 | I46: =SUM(I47:I56) -> 362831 | J46: =SUM(J47:J56) -> 351966 | ... AG46: =SUM(AG47:AG56) -> 2473094
A47: Empréstimos e Financiamentos | B47: Loans and Financing | C47: 113352 | D47: 68127 | E47: 23079 | F47: 6356 | G47: 3694 | H47: 987 | I47: 0 | J47: 0 | K47: 0 | L47: 0 | M47: 0 | N47: 0 | O47: 0 | P47: 0 | Q47: 0 | R47: 0 | S47: 0 | T47: 0 | U47: 715 | V47: 405 | W47: 0 | X47: 0 | Y47: 0 | Z47: 0 | AA47: 2915 | AB47: 0 | AC47: 0 | AD47: 0 | AE47: 0 | AF47: 0 | AG47: 0
A48: Financiamento por Arrendamento | B48: Lease Liabilities | C48: 38677 | D48: 37751 | E48: 33281 | F48: 28961 | G48: 202150 | H48: 195660 | I48: 195314 | J48: 192080 | K48: 195765 | L48: 189739 | M48: 185431 | N48: 178244 | O48: 203333 | P48: 190735 | Q48: 184993 | R48: 176584 | S48: 183819 | T48: 177793 | U48: 167416 | V48: 154673 | W48: 139660 | X48: 135510 | Y48: 120379 | Z48: 106663 | AA48: 93200 | AB48: 77272 | AC48: 78177 | AD48: 68285 | AE48: 62333 | AF48: 62485 | AG48: 92375
A49: Debêntures | B49: Debentures | C49: 267305 | D49: 269165 | E49: 199825 | F49: 199869 | G49: 199913 | H49: 199956 | I49: 0 | J49: 0 | K49: 0 | L49: 0 | M49: 0 | N49: 0 | O49: 0 | P49: 1494684 | Q49: 1496834 | R49: 1123138 | S49: 1123572 | T49: 999013 | U49: 1487693 | V49: 1488308 | W49: 1489073 | X49: 1489864 | Y49: 1490692 | Z49: 1491495 | AA49: 1492260 | AB49: 1493025 | AC49: 1470990 | AD49: 1472286 | AE49: 1473502 | AF49: 1474718 | AG49: 1476014
A50: Obrigações com Empresas ligadas | B50: Obligation related to Related Parties | C50: 0 | D50: 0 | E50: 0 | F50: 0 | G50: 0 | H50: 0 | I50: 0 | J50: 0 | K50: 0 | L50: 0 | M50: 0 | N50: 0 | O50: 0 | P50: 0 | Q50: 0 | R50: 0 | S50: 0 | T50: 0 | U50: 0 | V50: 0 | W50: 0 | X50: 0 | Y50: 0 | Z50: 0 | AA50: 0 | AB50: 0 | AC50: 0 | AD50: 0 | AE50: 0 | AF50: 0 | AG50: 0
A51: Provisão para Contingências | B51: Provision for Contingencies | C51: 120642 | D51: 127000 | E51: 124184 | F51: 127792 | G51: 133786 | H51: 133864 | I51: 136247 | J51: 131521 | K51: 129455 | L51: 135792 | M51: 134252 | N51: 125818 | O51: 135207 | P51: 125276 | Q51: 127625 | R51: 106939 | S51: 113748 | T51: 109184 | U51: 108786 | V51: 107491 | W51: 106350 | X51: 112691 | Y51: 115007 | Z51: 111990 | AA51: 108709 | AB51: 112605 | AC51: 100911 | AD51: 106272 | AE51: 111253 | AF51: 100768 | AG51: 108111
A52: Obrigações por Aquisição de Investimentos | B52: Accounts Payable from Acquisition of Subsidiaries | C52: 0 | D52: 12269 | E52: 18841 | F52: 15464 | G52: 14592 | H52: 15972 | I52: 14824 | J52: 10758 | K52: 32699 | L52: 173230 | M52: 170838 | N52: 163419 | O52: 157653 | P52: 269699 | Q52: 303777 | R52: 311575 | S52: 365343 | T52: 376159 | U52: 472709 | V52: 511519 | W52: 486183 | X52: 299133 | Y52: 265462 | Z52: 272135 | AA52: 318700 | AB52: 252444 | AC52: 254973 | AD52: 228249 | AE52: 226189 | AF52: 218689 | AG52: 242723
A53: IR e CSLL Diferidos | B53: Deferred Income Taxes | C53: 0 | D53: 0 | E53: 0 | F53: 0 | G53: 0 | H53: 0 | I53: 0 | J53: 0 | K53: 0 | L53: 0 | M53: 3741 | N53: 289 | O53: 2004 | P53: 2349 | Q53: 3655 | R53: 0 | S53: 1317 | T53: 2545 | U53: 5364 | V53: 623 | W53: 805 | X53: 1742 | Y53: 5732 | Z53: 8647 | AA53: 11637 | AB53: 14235 | AC53: 15616 | AD53: 13740 | AE53: 15874 | AF53: 20154 | AG53: 27086
A54: Obrigações Fiscais | B54: Tax Obligations | C54: 0 | D54: 0 | E54: 0 | F54: 0 | G54: 0 | H54: 0 | I54: 0 | J54: 0 | K54: 0 | L54: 4728 | M54: 3998 | N54: 3977 | O54: 3672 | P54: 3385 | Q54: 3087 | R54: 2677 | S54: 2386 | T54: 2117 | U54: 2379 | V54: 1381 | W54: 849 | X54: 498 | Y54: 216 | Z54: 42 | AA54: 1023 | AB54: 558 | AC54: 39 | AD54: 38 | AE54: 0 | AF54: 0 | AG54: 0
A55: Passivo Financeiro | B55: Call Option of Non-controlling Interests | C55: 0 | D55: 0 | E55: 0 | F55: 0 | G55: 0 | H55: 0 | I55: 0 | J55: 0 | K55: 0 | L55: 0 | M55: 0 | N55: 0 | O55: 0 | P55: 0 | Q55: 0 | R55: 366194 | S55: 373524 | T55: 381001 | U55: 388627 | V55: 383004 | W55: 390444 | X55: 398029 | Y55: 404324 | Z55: 412655 | AA55: 421157 | AB55: 424554 | AC55: 435291 | AD55: 444771 | AE55: 454274 | AF55: 465558 | AG55: 472850
A56: Outros Passivos | B56: Other Liabilities | C56: 6193 | D56: 13886 | E56: 15435 | F56: 15003 | G56: 17995 | H56: 18919 | I56: 16446 | J56: 17607 | K56: 21490 | L56: 22494 | M56: 25456 | N56: 30462 | O56: 37417 | P56: 67258 | Q56: 31346 | R56: 48131 | S56: 52536 | T56: 46316 | U56: 48098 | V56: 47574 | W56: 50633 | X56: 42273 | Y56: 44640 | Z56: 63833 | AA56: 65298 | AB56: 59846 | AC56: 62257 | AD56: 66762 | AE56: 72277 | AF56: 61609 | AG56: 53935
A58: Patrimônio líquido | B58: Shareholders' equity | C58: =SUM(C59:C65) -> 1284829 | D58: =SUM(D59:D65) -> 1322257 | E58: =SUM(E59:E65) -> 1331011 | F58: =SUM(F59:F65) -> 1288220 | G58: =SUM(G59:G65) -> 1307010 | H58: =SUM(H59:H65) -> 2405720 | I58: =SUM(I59:I65) -> 2466904 | J58: =SUM(J59:J65) -> 2478409 | ... AG58: =SUM(AG59:AG65) -> 5407082
A59: Capital Social | B59: Share Capital | C59: 989841 | D59: 1041229 | E59: 1041229 | F59: 1041229 | G59: 1041229 | H59: 1382509 | I59: 1382509 | J59: 1382509 | K59: 1382509 | L59: 1382509 | M59: 1382509 | N59: 1382509 | O59: 1382509 | P59: 1519412 | Q59: 2962585 | R59: 2962585 | S59: 2962585 | T59: 2962585 | U59: 2962585 | V59: 2962585 | W59: 2962585 | X59: 2962585 | Y59: 2962585 | Z59: 2962585 | AA59: 2962585 | AB59: 2962585 | AC59: 2962585 | AD59: 2962585 | AE59: 2962585 | AF59: 2962585 | AG59: 2962585
A60: Ações em Tesouraria | B60: Treasury Shares | C60: -70834 | D60: -70655 | E60: -70026 | F60: -70026 | G60: -64866 | H60: -63515 | I60: -62728 | J60: -62531 | K60: -94508 | L60: -148606 | M60: -148570 | N60: -148537 | O60: -148478 | P60: -133303 | Q60: -133195 | R60: -133195 | S60: -133141 | T60: -217944 | U60: -217892 | V60: -217671 | W60: -326979 | X60: -283774 | Y60: -283584 | Z60: -283445 | AA60: -367918 | AB60: -545092 | AC60: -606638 | AD60: -350163 | AE60: -349659 | AF60: -305211 | AG60: -305092
A61: Reserva de Capital | B61: Capital Reserves | C61: 165649 | D61: 167059 | E61: 168405 | F61: 169907 | G61: 168153 | H61: 867814 | I61: 871639 | J61: 875979 | K61: 873243 | L61: 879145 | M61: 887095 | N61: 894824 | O61: 901880 | P61: 894758 | Q61: 867555 | R61: 864868 | S61: 878478 | T61: 856005 | U61: 875042 | V61: 723183 | W61: 738255 | X61: 693915 | Y61: 716037 | Z61: 738293 | AA61: 758764 | AB61: 709199 | AC61: 730765 | AD61: 281801 | AE61: 294495 | AF61: 252057 | AG61: 280772
A62: Reservas de Lucros | B62: Profit Reserve | C62: 196815 | D62: 176720 | E62: 180030 | F62: 125228 | G62: 141573 | H62: 198609 | I62: 249647 | J62: 234389 | K62: 295897 | L62: 353890 | M62: 393458 | N62: 381869 | O62: 462514 | P62: 404254 | Q62: 441981 | R62: 483214 | S62: 562669 | T62: 685062 | U62: 773325 | V62: 793569 | W62: 887690 | X62: 983095 | Y62: 1271958 | Z62: 1262719 | AA62: 1389368 | AB62: 1504240 | AC62: 1659335 | AD62: 1715436 | AE62: 1828057 | AF62: 1928775 | AG62: 2083796
A63: Ajustes Acumulados de Conversão | B63: Carrying Value Adjustments | C63: -2517 | D63: 7411 | E63: 10042 | F63: 20704 | G63: 20187 | H63: 19453 | I63: 25132 | J63: 22051 | K63: 45096 | L63: 50473 | M63: 51524 | N63: 42541 | O63: 53303 | P63: 38092 | Q63: 48832 | R63: 55457 | S63: 37440 | T63: 45985 | U63: 48575 | V63: 46950 | W63: 44506 | X63: 39933 | Y63: 45489 | Z63: 40422 | AA63: 44042 | AB63: 56640 | AC63: 56559 | AD63: 71693 | AE63: 64303 | AF63: 58961 | AG63: 55296
A64: Dividendo Adicional Proposto | B64: Proposed Dividends | C64: 5442 | D64: 0 | E64: 0 | F64: 0 | G64: 0 | H64: 0 | I64: 0 | J64: 24817 | K64: 24817 | L64: 0 | M64: 0 | N64: 50960 | O64: 50960 | P64: 0 | Q64: 0 | R64: 0 | S64: 0 | T64: 0 | U64: 0 | V64: 0 | W64: 0 | X64: 0 | Y64: 0 | Z64: 0 | AA64: 0 | AB64: 0 | AC64: 0 | AD64: 0 | AE64: 0 | AF64: 0 | AG64: 0
A65: Participação dos Acionistas Não Controladores | B65: Non-controlling Interest | C65: 433 | D65: 493 | E65: 1331 | F65: 1178 | G65: 734 | H65: 850 | I65: 705 | J65: 1195 | K65: 0 | L65: 0 | M65: 0 | N65: 0 | O65: 0 | P65: 0 | Q65: 0 | R65: 253079 | S65: 258601 | T65: 265222 | U65: 272152 | V65: 276233 | W65: 281659 | X65: 292034 | Y65: 299078 | Z65: 292097 | AA65: 294819 | AB65: 300652 | AC65: 305501 | AD65: 305769 | AE65: 311717 | AF65: 318086 | AG65: 329725

Sheet GAAP-Consolidated-CF
A1: PORTUGUÊS | B1: ENGLISH
A2: Fluxo de Caixa (GAAP) Trimestre (R$ mil) | B2: GAAP Cash Flow - Quarter (R$ thousand) | C2: 1Q21 | D2: 2Q21 | E2: 3Q21 | F2: 4Q21 | G2: 1Q22 | H2: 2Q22 | I2: 3Q22 | J2: 4Q22 | K2: 1Q23 | L2: 2Q23 | M2: 3Q23 | N2: 4Q23 | O2: 1Q24 | P2: 2Q24 | Q2: 3Q24 | R2: 4Q24 | S2: 1Q25 | T2: 2Q25 | U2: 3Q25
A3: Fluxo de caixa das atividades operacionais: | B3: Operating Cashflow
A4: Lucro antes Tributação Imp. Renda e Contrib. Social | B4: Net income before taxes | C4: 122504 | D4: 121660 | E4: 94696 | F4: 140665 | G4: 132469 | H4: 189882 | I4: 177883 | J4: 161361 | K4: 168275 | L4: 165177 | M4: 214521 | N4: 135313 | O4: 208406 | P4: 181505 | Q4: 230528 | R4: 204799 | S4: 258556 | T4: 242867 | U4: 310689
A6: Ajustes por: | B6: Adjustments:
A7: Depreciação e Amortização | B7: Depreciation and Amortization | C7: 44130 | D7: 44536 | E7: 55609 | F7: 54909 | G7: 57110 | H7: 58116 | I7: 59635 | J7: 61267 | K7: 62136 | L7: 75791 | M7: 71540 | N7: 73334 | O7: 73375 | P7: 84261 | Q7: 86775 | R7: 81508 | S7: 85427 | T7: 88969 | U7: 93714
A8: Pagamento Baseado em Ações | B8: Share-based Payments Expense | C8: 7115 | D8: 8053 | E8: 13967 | F8: 5478 | G8: 13739 | H8: 1563 | I8: 19217 | J8: 18611 | K8: 17346 | L8: 5441 | M8: 20454 | N8: 21083 | O8: 26045 | P8: -6533 | Q8: 21587 | R8: 4719 | S8: 12431 | T8: 14324 | U8: 28867
A9: Perda (Ganho) na Baixa de Ativos | B9: Losses on Disposal of Fixed Assets and Inv. | C9: -294 | D9: 310 | E9: 10383 | F9: -826 | G9: 210 | H9: -678 | I9: -1911 | J9: 880 | K9: 955 | L9: -266 | M9: -165 | N9: 880 | O9: -564 | P9: -6492 | Q9: -11127 | R9: 8487 | S9: 2295 | T9: 1677.6015 | U9: -1058
A10: Provisão para Perda Esperada | B10: Provision for Expected Credit Losses | C10: 5050 | D10: 4808 | E10: 8368 | F10: 2287 | G10: 7334 | H10: 5854 | I10: 8577 | J10: 5147 | K10: 7461 | L10: 10208 | M10: 10388 | N10: 8337 | O10: 13237 | P10: 16267 | Q10: 12871 | R10: 16252 | S10: 14576 | T10: 14038 | U10: 14330
A11: Equivalência Patrimonial | B11: Equity Pickup | C11: 0 | D11: 564 | E11: -38 | F11: 0 | G11: -7 | H11: 0 | I11: 0 | J11: 449 | K11: 0 | L11: 0 | M11: -4402 | N11: 1207 | O11: 4261 | P11: 3561 | Q11: -2058 | R11: -4193 | S11: -2974 | T11: -154 | U11: -7401
A12: Provisão (Reversão) para Contingências | B12: Provision for Contingencies, Net of Reversals | C12: 9086 | D12: 4804 | E12: 10614 | F12: 7330 | G12: 10936 | H12: 2690 | I12: 5498 | J12: 12870 | K12: 105 | L12: 7126 | M12: 3498 | N12: 12350 | O12: 429 | P12: 6041 | Q12: 4535 | R12: 9893 | S12: 13470 | T12: 2128 | U12: 13669
A13: Provisão (Reversão) de outras Obrig. e Outros | B13: Provision (Reversal) for Other Obligations | C13: 0 | D13: 0 | E13: -1401 | F13: 18943 | G13: 24913 | H13: -1950 | I13: 0 | J13: 5292 | K13: 21607 | L13: 5576 | M13: 8023 | N13: 35454 | O13: 14035 | P13: -15637 | Q13: -20143 | R13: 16533 | S13: 11169 | T13: 5289 | U13: 0
A14: Juros e Variação Cambiais e Monetárias Líquidas | B14: Net Interest, Monetary and Exchange Variations | C14: 11684 | D14: 15913 | E14: 53518 | F14: 57577 | G14: 61964 | H14: 69446 | I14: 79904 | J14: 73274 | K14: 79053 | L14: 74548 | M14: 68556 | N14: 78140 | O14: 76753 | P14: 59048 | Q14: 72388 | R14: 61847 | S14: 69317 | T14: 71111 | U14: 78254
A16: Variação em ativos e passivos operacionais: | B16: Changes in operating assets and liabilities:
A17: Contas a Receber de Clientes | B17: Trade Receivables | C17: -7268 | D17: -9288 | E17: -23729 | F17: 13956 | G17: -57022 | H17: -35728 | I17: -24103 | J17: 23408 | K17: -31283 | L17: -23362 | M17: -28629 | N17: 12709 | O17: -48249 | P17: -20963 | Q17: -9516 | R17: 7168 | S17: -97980 | T17: -39949 | U17: -18272
A18: Impostos a Recuperar | B18: Recoverable Taxes | C18: -765 | D18: -4634 | E18: 4959 | F18: -32888 | G18: -9605 | H18: -38503 | I18: -11639 | J18: -15689 | K18: 4883 | L18: -12064 | M18: 11219 | N18: -50265 | O18: -2696 | P18: -15995 | Q18: -16891 | R18: -15558 | S18: -23292 | T18: -25828 | U18: 1628
A19: Depósitos Judiciais | B19: Judicial Deposits | C19: -294 | D19: 1129 | E19: 1913 | F19: 10676 | G19: 724 | H19: -2784 | I19: 137 | J19: -1030 | K19: -2716 | L19: -1664 | M19: 226 | N19: -1308 | O19: 1384 | P19: -310 | Q19: -1076 | R19: 1655 | S19: -3637 | T19: -862 | U19: 170
A20: Outros Ativos | B20: Other Assets | C20: -21761 | D20: -21912 | E20: -18215 | F20: 20896 | G20: -5568 | H20: -38546 | I20: -11486 | J20: 28659 | K20: -34452 | L20: -54741 | M20: -694 | N20: 52219 | O20: -34053 | P20: -52836 | Q20: -23123 | R20: 26519 | S20: -24260 | T20: -108630 | U20: -43155
A21: Obrigações Sociais e Trabalhistas | B21: Labor Liabilities | C21: 5908 | D21: 42405 | E21: -31771 | F21: -15455 | G21: 3062 | H21: 92679 | I21: 7725 | J21: -29914 | K21: 3425 | L21: 100758 | M21: 27236 | N21: -34469 | O21: 7346 | P21: 102310 | Q21: 3762 | R21: -25972 | S21: 14907 | T21: 117314 | U21: 11116
A22: Fornecedores | B22: Trade and Other Payables | C22: -23023 | D22: -9128 | E22: 892 | F22: 2242 | G22: -3038 | H22: -1355 | I22: 15516 | J22: 10651 | K22: -16706 | L22: 22236 | M22: -6158 | N22: 20334 | O22: 13738 | P22: 23395 | Q22: -24223 | R22: 38155 | S22: 20763 | T22: -7930 | U22: -17763
A23: Comissões a Pagar | B23: Commissions Payable | C23: 8836 | D23: -3047 | E23: -1730 | F23: -680 | G23: 9359 | H23: -5186 | I23: 76 | J23: 3112 | K23: 8331 | L23: -5852 | M23: -3007 | N23: -2380 | O23: -3961 | P23: -8816 | Q23: 11218 | R23: 5496 | S23: -8291 | T23: 3541 | U23: 5287
A24: Impostos a Pagar | B24: Taxes and Contributions Payable | C24: -8460 | D24: -3130 | E24: 17141 | F24: 4814 | G24: 4840 | H24: -6151 | I24: 2289 | J24: -8447 | K24: -12907 | L24: -6356 | M24: -20989 | N24: 12981 | O24: -7832 | P24: 865 | Q24: 3274 | R24: 435 | S24: 9010 | T24: 16434 | U24: -14385
A25: Repasse para Parceiros | B25: Business Partners Payable | C25: 0 | D25: 0 | E25: 0 | F25: 0 | G25: 0 | H25: 0 | I25: 0 | J25: 0 | K25: 0 | L25: 0 | M25: 0 | N25: 0 | O25: 0 | P25: 0 | Q25: 0 | R25: 0 | S25: 0 | T25: 0 | U25: 0
A26: Outras Contas a Pagar | B26: Other Accounts Payable | C26: 5359 | D26: -25473 | E26: -31428 | F26: -8577 | G26: 5686 | H26: 1137 | I26: 6352 | J26: -24625 | K26: 12853 | L26: -9606 | M26: 8300 | N26: -30513 | O26: -7043 | P26: 266 | Q26: -8832 | R26: -7340 | S26: -900 | T26: -13208 | U26: 812
A27: Geração Operacional de Caixa | B27: Operating Cash Generation | C27: =SUM(C4,C7:C14,C17:C26) -> 157807 | D27: =SUM(D4,D7:D14,D17:D26) -> 167570 | E27: =SUM(E4,E7:E14,E17:E26) -> 163748 | F27: =SUM(F4,F7:F14,F17:F26) -> 281347 | G27: =SUM(G4,G7:G14,G17:G26) -> 257106 | H27: =SUM(H4,H7:H14,H17:H26) -> 290486 | I27: =SUM(I4,I7:I14,I17:I26) -> 333670 | J27: =SUM(J4,J7:J14,J17:J26) -> 325276 | ... U27: =SUM(U4,U7:U14,U17:U26) -> 456502
A29: Juros Pagos | B29: Interest paid | C29: -3638 | D29: -3123 | E29: -3192 | F29: -54073 | G29: -3038 | H29: -93502 | I29: -76737 | J29: -3113 | K29: -108686 | L29: -2246 | M29: -111614 | N29: -2375 | O29: -97810 | P29: -2434 | Q29: -76152 | R29: -1532 | S29: -80231 | T29: -2245 | U29: -112868
A30: IR e CSLL Pagos | B30: Tax Paid | C30: -45226 | D30: -23339 | E30: -29493 | F30: -33889 | G30: -50073 | H30: -9637 | I30: -32128 | J30: -22750 | K30: -51550 | L30: -28483 | M30: -63355 | N30: -46223 | O30: -53870 | P30: -41880 | Q30: -33442 | R30: -26960 | S30: -73808 | T30: -27197 | U30: -33572
A31: Caixa Líquido das Atividades Operacionais | B31: Net Cash from Operating Activities | C31: =SUM(C27,C29:C30) -> 108943 | D31: =SUM(D27,D29:D30) -> 141108 | E31: =SUM(E27,E29:E30) -> 131063 | F31: =SUM(F27,F29:F30) -> 193385 | G31: =SUM(G27,G29:G30) -> 203995 | H31: =SUM(H27,H29:H30) -> 187347 | I31: =SUM(I27,I29:I30) -> 224805 | J31: =SUM(J27,J29:J30) -> 299413 | ... U31: =SUM(U27,U29:U30) -> 310062
A33: Fluxo de caixa proveniente de atividades em investimentos | B33: Investing activities cash flow
A34: Dividendos Recebidos | B34: Dividends Received | C34: 0 | D34: 0 | E34: 1373 | F34: 746 | G34: 0 | H34: 0 | I34: - | J34: - | K34: 0 | L34: 0 | M34: 9073 | N34: 0 | O34: 0 | P34: 0 | Q34: 0 | R34: 0 | S34: 0 | T34: 0 | U34: 15598
A35: Aumento de Ativo Imobilizado | B35: Acquisitions of Prop. Plant and Equip. | C35: -9673 | D35: -13290 | E35: -34988 | F35: -35548 | G35: -14557 | H35: -18229 | I35: -35968 | J35: -32184 | K35: -37927 | L35: -22751 | M35: -37263 | N35: -25319 | O35: -23469 | P35: -37315 | Q35: -19760 | R35: -38704 | S35: -51840 | T35: -41874 | U35: -29901
A36: Aumento de Intangível | B36: Acquisition of Intangible Assets | C36: -10436 | D36: -13162 | E36: -39914 | F36: -17790 | G36: -9709 | H36: -23486 | I36: -21989 | J36: -25001 | K36: -28830 | L36: -21260 | M36: -83535 | N36: -20315 | O36: -36152 | P36: -41926 | Q36: -20138 | R36: -24238 | S36: -22318 | T36: -29688 | U36: -24285
A37: Mútuo com Franquias | B37: Franchises Loan | C37: -2996 | D37: -18166 | E37: -9876 | F37: -16626 | G37: 4471 | H37: 4747 | I37: 12101 | J37: 2938 | K37: 6195 | L37: 5518 | M37: -2484 | N37: 3921 | O37: 3585 | P37: 3821 | Q37: -18763 | R37: 10768 | S37: 2916 | T37: 3299 | U37: 2141
A38: Aquisição de Participação Societária | B38: Acquisition of Subsidiaries, Net of Cash | C38: 0 | D38: -1705030 | E38: -1 | F38: 0 | G38: -67589 | H38: -29947 | I38: -82218 | J38: -996 | K38: 0 | L38: -38748 | M38: -44451 | N38: -5668 | O38: -570907 | P38: -12666 | Q38: 0 | R38: -38871 | S38: 0 | T38: 0 | U38: -194227
A39: Pag. de Obrig. por Aquisição de Invest. | B39: Payments from Acquisitions of Subsidiaries | C39: -24065 | D39: -1389 | E39: -7788 | F39: -820 | G39: -119449 | H39: -50531 | I39: -13641 | J39: -25641 | K39: -11732 | L39: -25752 | M39: -5305 | N39: -707 | O39: -25641 | P39: -289349 | Q39: 0 | R39: -159681 | S39: -87484 | T39: -26683 | U39: -7521
A40: Venda (Aquisição) de Investimentos | B40: Proceeds from Sale of Subsid., Net of Cash | C40: 5041 | D40: 346 | E40: 41 | F40: 41 | G40: 6398 | H40: 40 | I40: 38 | J40: 43 | K40: 0 | L40: 54 | M40: 0 | N40: 0 | O40: 21144 | P40: 0 | Q40: 22030 | R40: -1365 | S40: 0 | T40: 0 | U40: 0
A41: Valor da Venda de Ativo Imobilizado | B41: Proceeds from Sale of Prop. Plant and Equip. | C41: 503 | D41: 882 | E41: 1752 | F41: 1099 | G41: 197 | H41: 1016 | I41: 444 | J41: 1412 | K41: 496 | L41: 718 | M41: 532 | N41: 1762 | O41: 7021 | P41: 1284 | Q41: 1531 | R41: 1676 | S41: 1442 | T41: 1107.3985 | U41: 2188
A42: Resgate (Investimento) Financeiros e Fundo CVC | B42: Financial and CVC Fund Rescue (Investment) | C42: 0 | D42: 0 | E42: 0 | F42: 0 | G42: -4192 | H42: -3491 | I42: -4083 | J42: -8315 | K42: 0 | L42: -4532 | M42: 385 | N42: -20689 | O42: -26010 | P42: 0 | Q42: -15399 | R42: -5616 | S42: -21389 | T42: -2438 | U42: -23173
A43: Caixa Recebido (Investido) - Techfin | B43: Net cash Received (Invested) - Techfin | C43: -193462 | D43: -5162 | E43: -7573 | F43: -9209 | G43: -7201 | H43: -5926 | I43: -18252 | J43: -2403 | K43: -5012 | L43: 235 | M43: 410000 | N43: 0 | O43: 0 | P43: 0 | Q43: 0 | R43: 0 | S43: 0 | T43: 0 | U43: 0
A44: Caixa Recebido (Investido) - RJ | B44: Net cash Received (Invested) - RJ | C44: 0 | D44: 0 | E44: 0 | F44: 0 | G44: 0 | H44: 0 | I44: 0 | J44: 0 | K44: 0 | L44: 0 | M44: 0 | N44: 0 | O44: 1300 | P44: 644 | Q44: 798 | R44: 437 | S44: -1619 | T44: -125 | U44: 154
A45: Fluxo de caixa proveniente de atividades em investimentos | B45: Investing activities cash flow | C45: =SUM(C34:C44) -> -235088 | D45: =SUM(D34:D44) -> -1754971 | E45: =SUM(E34:E44) -> -96974 | F45: =SUM(F34:F44) -> -78107 | G45: =SUM(G34:G44) -> -211631 | H45: =SUM(H34:H44) -> -125807 | I45: =SUM(I34:I44) -> -163568 | J45: =SUM(J34:J44) -> -90147 | ... U45: =SUM(U34:U44) -> -259026
A47: Fluxo de caixa proveniente de atividades de financiamento | B47: Financing activities cash flow
A48: Pag. de Principal de Emp. e Financ. | B48: Payment of Princ. of Loans and Financing | C48: -828 | D48: 0 | E48: -3329 | F48: 0 | G48: -5187 | H48: -1553 | I48: - | J48: -444 | K48: -440 | L48: -10517 | M48: 0 | N48: 0 | O48: -35708 | P48: -4664 | Q48: 0 | R48: 0 | S48: 0 | T48: 0 | U48: -13116
A49: Pag. de Principal de Debêntures | B49: Payment of Principal of Debentures | C49: 0 | D49: 0 | E49: 0 | F49: 0 | G49: 0 | H49: 0 | I49: -1500000 | J49: 0 | K49: 0 | L49: 0 | M49: 0 | N49: 0 | O49: 0 | P49: -5000 | Q49: -1500000 | R49: 0 | S49: 0 | T49: 0 | U49: -21237
A50: Pag. de Parcelas de Arrend. Mercantil | B50: Payment of Principal of Lease Liabilities | C50: -8215 | D50: -14781 | E50: -9615 | F50: -13162 | G50: -8718 | H50: -19152 | I50: -13743 | J50: -13882 | K50: -13912 | L50: -14859 | M50: -15171 | N50: -15112 | O50: -15049 | P50: -15016 | Q50: -16743 | R50: -13971 | S50: -15378 | T50: -22164 | U50: -17158
A51: Captação de Debên e Empr. e Fin. | B51: Proceeds from debentures, loans and finan. | C51: 0 | D51: 1489369 | E51: 0 | F51: 0 | G51: 0 | H51: 0 | I51: 1488256 | J51: 0 | K51: 0 | L51: 0 | M51: 32083 | N51: 0 | O51: 0 | P51: 0 | Q51: 1474982 | R51: 0 | S51: 0 | T51: 0 | U51: 0
A52: Aumento de Capital Líquido de Gastos | B52: Capital Increase, Net of Expenses | C52: 0 | D52: 0 | E52: 1443173 | F52: 0 | G52: 0 | H52: 0 | I52: - | J52: 0 | K52: 0 | L52: 0 | M52: 0 | N52: 0 | O52: 0 | P52: 0 | Q52: 0 | R52: 0 | S52: 0 | T52: 0 | U52: 0
A53: Investimento de não controladores | B53: Investments from Non-controlling Interest | C53: 0 | D53: 0 | E53: 0 | F53: 600073 | G53: 0 | H53: 0 | I53: - | J53: 0 | K53: 0 | L53: 4164 | M53: 0 | N53: 0 | O53: 0 | P53: 0 | Q53: 0 | R53: 0 | S53: 0 | T53: 0 | U53: 0
A54: Gastos com emissão de ações | B54: Share Issue Expenses | C54: 0 | D54: 0 | E54: -36115 | F54: -4264 | G54: -75 | H54: 0 | I54: - | J54: 0 | K54: 0 | L54: 0 | M54: 0 | N54: 0 | O54: 0 | P54: 0 | Q54: 0 | R54: 0 | S54: 0 | T54: 0 | U54: 0
A55: Crédito com Empresas Ligadas | B55: Receivables from Related Companies | C55: 0 | D55: 0 | E55: 0 | F55: 0 | G55: 0 | H55: 0 | I55: -678 | J55: -227 | K55: -230 | L55: -6079 | M55: 6277 | N55: 32 | O55: 0 | P55: 0 | Q55: 0 | R55: 0 | S55: 0 | T55: 0 | U55: 0
A56: Dividendos e JCP Pago | B56: Dividends and Interest on Equity Paid | C56: -6437 | D56: -101170 | E56: 0 | F56: -36027 | G56: -9258 | H56: -69704 | I56: -61074 | J56: 0 | K56: -127047 | L56: -4165 | M56: -138674 | N56: -142277 | O56: 0 | P56: 0 | Q56: -136626 | R56: -128726 | S56: 0 | T56: -81924 | U56: -88036
A57: Ações em Tesouraria, Líquidas | B57: Net Treasury Shares | C57: 0 | D57: 0 | E57: 0 | F57: 0 | G57: 0 | H57: -108967 | I57: - | J57: 0 | K57: -109392 | L57: 0 | M57: 0 | N57: 0 | O57: -64091 | P57: -248327 | Q57: -42667 | R57: -216283 | S57: 0 | T57: 0 | U57: 0
A58: Fluxo de caixa proveniente de atividades de financiamento | B58: Net cash used in financing activities | C58: =SUM(C48:C57) -> -15480 | D58: =SUM(D48:D57) -> 1373418 | E58: =SUM(E48:E57) -> 1394114 | F58: =SUM(F48:F57) -> 546620 | G58: =SUM(G48:G57) -> -23238 | H58: =SUM(H48:H57) -> -199376 | I58: =SUM(I48:I57) -> -87239 | J58: =SUM(J48:J57) -> -14553 | ... U58: =SUM(U48:U57) -> -139547
A60: Aumentodas disponibilidades | B60: Increase (decrease) in cash and cash equivalents | C60: =SUM(C31,C45,C58) -> -141625 | D60: =SUM(D31,D45,D58) -> -240445 | E60: =SUM(E31,E45,E58) -> 1428203 | F60: =SUM(F31,F45,F58) -> 661898 | G60: =SUM(G31,G45,G58) -> -30874 | H60: =SUM(H31,H45,H58) -> -137836 | I60: =SUM(I31,I45,I58) -> -26002 | J60: =SUM(J31,J45,J58) -> 194713 | ... U60: =SUM(U31,U45,U58) -> -88511
A62: Caixa e equivalente de caixa no início do período | B62: Cash and cash equivalents at the beginning of the period | C62: 1027733 | D62: =ROUND(C63,0) -> 886108 | E62: =ROUND(D63,0) -> 645663 | F62: =ROUND(E63,0) -> 2073866 | G62: =ROUND(F63,0) -> 2735764 | H62: =ROUND(G63,0) -> 2704890 | I62: =ROUND(H63,0) -> 2567054 | J62: =ROUND(I63,0) -> 2541052 | K62: =ROUND(J63,0) -> 2735765 | ... U62: =ROUND(T63,0) -> 2094240
A63: Caixa e equivalente de caixa no fim do período | B63: Cash and cash equivalents at the end of the period | C63: =C62+C60 -> 886108 | D63: =D62+D60 -> 645663 | E63: =E62+E60 -> 2073866 | F63: =F62+F60 -> 2735764 | G63: =G62+G60 -> 2704890 | H63: =H62+H60 -> 2567054 | I63: =I62+I60 -> 2541052 | J63: =J62+J60 -> 2735765 | ... U63: =U62+U60 -> 2005729
A65: Receita Aplicação Financeira Líq. Impostos | B65: Revenue from financial investment, net of Taxes | C65: 0 | D65: 0 | E65: 0 | F65: 0 | G65: 75280 | H65: 80852 | I65: 90545 | J65: 88598 | K65: 63023 | L65: 79920 | M65: 93287 | N65: 84499 | O65: 78470 | P65: 58553 | Q65: 59669 | R65: 56330 | S65: 59234 | T65: 65439 | U65: 73293
A66: Ajuste IR e CSLL Pagos s/ Alienação JV Techfin | B66: Income Tax paid Adjust. w/ JV Techfin Alienation | G66: 0 | H66: 0 | I66: 0 | J66: 0 | K66: 0 | L66: 0 | M66: 30229 | N66: 0 | O66: 0 | P66: 0 | Q66: 0 | R66: 0 | S66: 0 | T66: 0 | U66: 0
A67: Fluxo de Caixa Livre da Empresa | B67: Free Cash Flow to Firm | C67: =C27+C30+C35+C36+C41+C50-C65+C66 -> 84760 | D67: =D27+D30+D35+D36+D41+D50-D65+D66 -> 103880 | E67: =E27+E30+E35+E36+E41+E50-E65+E66 -> 51490 | F67: =F27+F30+F35+F36+F41+F50-F65+F66 -> 182057 | G67: =G27+G30+G35+G36+G41+G50-G65+G66 -> 98966 | H67: =H27+H30+H35+H36+H41+H50-H65+H66 -> 140146 | I67: =I27+I30+I35+I36+I41+I50-I65+I66 -> 139741 | J67: =J27+J30+J35+J36+J41+J50-J65+J66 -> 144273 | ... U67: =U27+U30+U35+U36+U41+U50-U65+U66 -> 280481

Sheet Non-GAAP-Techfin-P&L
A1: PORTUGUÊS | B1: ENGLISH
A2: Demonstração de Resultados Trimestre (em R$ mil) | B2: Consolidated Income Statement Quarter (in R$ thousand) | C2: 1Q21 | D2: 2Q21 | E2: 3Q21 | F2: 4Q21 | G2: 1Q22 | H2: 2Q22 | I2: 3Q22 | J2: 4Q22 | K2: 1Q23 | L2: 2Q23 | M2: 3Q23 | N2: 4Q23 | O2: 1Q24 | P2: 2Q24 | Q2: 3Q24 | R2: 4Q24 | S2: 1Q25 | T2: 2Q25 | U2: 3Q25
A3: Receita de Techfin | B3: Techfin Net Revenue | C3: 55614 | D3: 60944 | E3: 73157 | F3: 91836 | G3: 82632 | H3: 93895 | I3: 117432 | J3: 117926 | K3: 99752 | L3: 88872 | M3: 136104 | N3: 118818 | O3: 99468 | P3: 102219 | Q3: 115023 | R3: 129834 | S3: 121025 | T3: 119141 | U3: 152513
A4: Custo de Funding | B4: Funding Cost | C4: -13356 | D4: -17285 | E4: -25150 | F4: -27291 | G4: -35517 | H4: -42020 | I4: -44753 | J4: -42462 | K4: -45283 | L4: -41386 | M4: -38270 | N4: -45751 | O4: -36474 | P4: -32377 | Q4: -36621 | R4: -33566 | S4: -41560 | T4: -46676 | U4: -50711
A5: Receita de Techfin Líquida de Funding | B5: Techfin Revenue - Net of funding | C5: =C3+C4 -> 42258 | D5: =D3+D4 -> 43659 | E5: =E3+E4 -> 48007 | F5: =F3+F4 -> 64545 | G5: =G3+G4 -> 47115 | H5: =H3+H4 -> 51875 | I5: =I3+I4 -> 72679 | J5: =J3+J4 -> 75464 | ... U5: =U3+U4 -> 101802
A6: Custos Operacionais | B6: Operational Costs | C6: -4869 | D6: -5385 | E6: -5949 | F6: -7336 | G6: -5895 | H6: -5680 | I6: -6944 | J6: -6772 | K6: -6444 | L6: -7572 | M6: -10444 | N6: -10547 | O6: -9208 | P6: -11324 | Q6: -10743 | R6: -13325 | S6: -8882 | T6: -7329 | U6: -7375
A7: Pesquisa e Desenvolvimento | B7: Research and Development | C7: -4499 | D7: -5823 | E7: -5865 | F7: -7972 | G7: -6722 | H7: -6180 | I7: -10038 | J7: -8384 | K7: -9384 | L7: -9032 | M7: -13202 | N7: -17710 | O7: -13526 | P7: -8251 | Q7: -8620 | R7: -9318 | S7: -7568 | T7: -8997 | U7: -9658
A8: Provisão para Perda Esperada | B8: Provision for Expected Credit Losses | C8: -1818 | D8: -4092 | E8: -4337 | F8: -5399 | G8: -10227 | H8: -7271 | I8: -7018 | J8: -16007 | K8: -8290 | L8: -6758 | M8: -9683 | N8: -8541 | O8: -7203 | P8: -8580 | Q8: -7562 | R8: -7262 | S8: -7103 | T8: -8511 | U8: -9930
A9: Demais Despesas Operacionais | B9: Other Operating Expenses | C9: -18033 | D9: -19946 | E9: -23276 | F9: -26084 | G9: -19421 | H9: -24104 | I9: -30231 | J9: -25799 | K9: -26409 | L9: -27202 | M9: -40299 | N9: -33981 | O9: -33598 | P9: -41359 | Q9: -42913 | R9: -42057.932 | S9: -43362 | T9: -45254 | U9: -49323
A10: Resultado da Equivalência Patrimônial | B10: Equity Pickup | C10: 0 | D10: 0 | E10: 0 | F10: 0 | G10: 0 | H10: 0 | I10: 0 | J10: 0 | K10: 0 | L10: 0 | M10: 0 | N10: 0 | O10: 0 | P10: 0 | Q10: 0 | R10: 0 | S10: 0 | T10: 0 | U10: 0
A11: EBITDA Ajustado Techfin | B11: Techfin Adjusted EBITDA | C11: =SUM(C5,C6,C7,C8,C9,C10) -> 13039 | D11: =SUM(D5,D6,D7,D8,D9,D10) -> 8413 | E11: =SUM(E5,E6,E7,E8,E9,E10) -> 8580 | F11: =SUM(F5,F6,F7,F8,F9,F10) -> 17754 | G11: =SUM(G5,G6,G7,G8,G9,G10) -> 4850 | H11: =SUM(H5,H6,H7,H8,H9,H10) -> 8640 | I11: =SUM(I5,I6,I7,I8,I9,I10) -> 18448 | J11: =SUM(J5,J6,J7,J8,J9,J10) -> 18502 | ... U11: =SUM(U5,U6,U7,U8,U9,U10) -> 25516
A12: % EBITDA Ajustado Techfin | B12: % Techfin Adjusted EBITDA | C12: =C11/C5 -> 0.30855696 | D12: =D11/D5 -> 0.19269795 | E12: =E11/E5 -> 0.17872394 | F12: =F11/F5 -> 0.27506391 | G12: =G11/G5 -> 0.10293962 | H12: =H11/H5 -> 0.16655422 | I12: =I11/I5 -> 0.25382848 | J12: =J11/J5 -> 0.24517651 | ... U12: =U11/U5 -> 0.25064341
A13: Depreciação e Amortização | B13: Depreciation and Amortization | C13: -15173 | D13: -15236 | E13: -15696 | F13: -15831 | G13: -14680 | H13: -11276 | I13: -10110 | J13: -10519 | K13: -10593 | L13: -10195 | M13: -10095 | N13: -10067 | O13: -9452 | P13: -9227 | Q13: -9222 | R13: -10197 | S13: -3190 | T13: -3193 | U13: -3191
A14: Resultado Financeiro | B14: Financial Result | C14: -286 | D14: -266 | E14: -570 | F14: -544 | G14: -94 | H14: -156 | I14: 423 | J14: 145 | K14: 134 | L14: 702 | M14: 3758 | N14: 4767 | O14: 4225 | P14: 3588 | Q14: 3408 | R14: 2437 | S14: 1870 | T14: 2952 | U14: 3076
A15: Imposto de Renda e Contrib. Social Ajustado | B15: Adjusted Income Tax and Social Contribution | C15: -822 | D15: 652 | E15: 254 | F15: -4950 | G15: -793 | H15: -861 | I15: 4631 | J15: -4240 | K15: 923 | L15: 4636 | M15: -6410 | N15: 603 | O15: -1008.64 | P15: -1810 | Q15: 1366 | R15: -6239.7431 | S15: -5282 | T15: -1826 | U15: -10598
A16: Amort. de Intang. de Aquisições Líq. de IR | B16: Net Effect of Amortization | C16: 9598.38 | D16: 9598.38 | E16: 9598.38 | F16: 9598.38 | G16: 8099.52 | H16: 6239.64 | I16: 5227.2 | J16: 5227.2 | K16: 5227.2 | L16: 5227.2 | M16: 5227.2 | N16: 5227.2 | O16: 5227.2 | P16: 5227.2 | Q16: 5227.2 | R16: 5227.2 | S16: 1247.4 | T16: 1247.4 | U16: 1247.4
A17: Lucro (Prejuízo) Ajustado da Techfin | B17: Adjusted Net Income (Loss) from Techfin | C17: =C11+C13+C14+C15+C16 -> 6356.38 | D17: =D11+D13+D14+D15+D16 -> 3161.38 | E17: =E11+E13+E14+E15+E16 -> 2166.38 | F17: =F11+F13+F14+F15+F16 -> 6027.38 | G17: =G11+G13+G14+G15+G16 -> -2617.48 | H17: =H11+H13+H14+H15+H16 -> 2586.64 | I17: =I11+I13+I14+I15+I16 -> 18619.2 | J17: =J11+J13+J14+J15+J16 -> 9115.2 | ... U17: =U11+U13+U14+U15+U16 -> 16050.4
A18: % Lucro (Prejuízo) da Techfin | B18: % Net Income (Loss) from Techfin | C18: =C17/C$5 -> 0.15041838 | D18: =D17/D$5 -> 0.072410729 | E18: =E17/E$5 -> 0.045126336 | F18: =F17/F$5 -> 0.093382601 | G18: =G17/G$5 -> -0.055555131 | H18: =H17/H$5 -> 0.04986294 | I18: =I17/I$5 -> 0.25618404 | J18: =J17/J$5 -> 0.12078872 | ... U18: =U17/U$5 -> 0.15766291
A19: Itens Extraordinários | B19: Extraordinary Items | C19: =SUM(C20:C22) -> 0 | D19: =SUM(D20:D22) -> 0 | E19: =SUM(E20:E22) -> 0 | F19: =SUM(F20:F22) -> 0 | G19: =SUM(G20:G22) -> 0 | H19: =SUM(H20:H22) -> 0 | I19: =SUM(I20:I22) -> 0 | J19: =SUM(J20:J22) -> 0 | ... U19: =SUM(U20:U22) -> 0
A20: Perda (Ganho) na Baixa de Ativos | B20: Lost (Earn) in Investment Sale | C20: 0 | D20: 0 | E20: 0 | F20: 0 | G20: 0 | H20: 0 | I20: 0 | J20: 0 | K20: 0 | L20: 0 | M20: 0 | N20: 0 | O20: 0 | P20: 0 | Q20: 0 | R20: -2518.068 | S20: 0 | T20: 0 | U20: 0
A21: Ajuste Extraord. Reestruturação Operacional | B21: Extraord. Adj. - Operatl. Restructuring | C21: 0 | D21: 0 | E21: 0 | F21: 0 | G21: 0 | H21: 0 | I21: 0 | J21: 0 | K21: 0 | L21: 0 | M21: 0 | N21: 0 | O21: -2646 | P21: 0 | Q21: 0 | R21: 0 | S21: 0 | T21: 0 | U21: 0
A22: Reoneração da Folha de Pagamento | B22: Adj. - Payroll Tax Surcharge | C22: 0 | D22: 0 | E22: 0 | F22: 0 | G22: 0 | H22: 0 | I22: 0 | J22: 0 | K22: 0 | L22: 0 | M22: 0 | N22: 0 | O22: 0 | P22: 0 | Q22: 0 | R22: -390 | S22: 0 | T22: 0 | U22: 0
A23: IR e CSLL (Itens Extraordinários) | B23: Taxes on Extraordinary Items | C23: =C19*-34% -> 0 | D23: =D19*-34% -> 0 | E23: =E19*-34% -> 0 | F23: =F19*-34% -> 0 | G23: =G19*-34% -> 0 | H23: =H19*-34% -> 0 | I23: =I19*-34% -> 0 | J23: =J19*-34% -> 0 | ... U23: =U19*-34% -> 0
A24: Amort. de Intang. de Aquisições Líq. de IR | B24: Net Effect of Amortization | C24: =-C16 -> -9598.38 | D24: =-D16 -> -9598.38 | E24: =-E16 -> -9598.38 | F24: =-F16 -> -9598.38 | G24: =-G16 -> -8099.52 | H24: =-H16 -> -6239.64 | I24: =-I16 -> -5227.2 | J24: =-J16 -> -5227.2 | ... U24: =-U16 -> -1247.4
A25: Lucro (Prejuízo) da Dimensão Techfin | B25: Net Income (Loss) from Techfin Dimension | C25: =C17+C19+C23+C24 -> -3242 | D25: =D17+D19+D23+D24 -> -6437 | E25: =E17+E19+E23+E24 -> -7432 | F25: =F17+F19+F23+F24 -> -3571 | G25: =G17+G19+G23+G24 -> -10717 | H25: =H17+H19+H23+H24 -> -3653 | I25: =I17+I19+I23+I24 -> 13392 | J25: =J17+J19+J23+J24 -> 3888 | ... U25: =U17+U19+U23+U24 -> 14803
A26: % Lucro (Prejuízo) da Dimensão Techfin | B26: % Net Income (Loss) from Techfin Dimension | C26: =C25/C$5 -> -0.076719201 | D26: =D25/D$5 -> -0.1474381 | E26: =E25/E$5 -> -0.15481076 | F26: =F25/F$5 -> -0.055325742 | G26: =G25/G$5 -> -0.22746471 | H26: =H25/H$5 -> -0.070419277 | I26: =I25/I$5 -> 0.1842623 | J26: =J25/J$5 -> 0.051521255 | ... U26: =U25/U$5 -> 0.14540972

Sheet Non-GAAP-Techfin-BS
A1: PORTUGUÊS | B1: ENGLISH
A2: Balanço Patrimonial Techfin (R$ mil) | B2: Techfin Balance Sheet (R$ thousand) | C2: 1Q21 | D2: 2Q21 | E2: 3Q21 | F2: 4Q21 | G2: 1Q22 | H2: 2Q22 | I2: 3Q22 | J2: 4Q22 | K2: 1Q23 | L2: 2Q23 | M2: 3Q23 | N2: 4Q23 | O2: 1Q24 | P2: 2Q24 | Q2: 3Q24 | R2: 4Q24 | S2: 1Q25 | T2: 2Q25 | U2: 3Q25
A4: ATIVO | B4: ASSETS | C4: =C5+C11 -> 1725800 | D4: =D5+D11 -> 1979945 | E4: =E5+E11 -> 2313723 | F4: =F5+F11 -> 2165370 | G4: =G5+G11 -> 2143229 | H4: =H5+H11 -> 2305532 | I4: =I5+I11 -> 2960010 | J4: =J5+J11 -> 2823978 | ... U4: =U5+U11 -> 3038262.9
A5: Circulante | B5: Current assets | C5: =SUM(C6:C9) -> 1711664 | D5: =SUM(D6:D9) -> 1965717 | E5: =SUM(E6:E9) -> 2296048 | F5: =SUM(F6:F9) -> 2149593 | G5: =SUM(G6:G9) -> 2128725 | H5: =SUM(H6:H9) -> 2290675 | I5: =SUM(I6:I9) -> 2473230 | J5: =SUM(J6:J9) -> 2519863 | ... U5: =SUM(U6:U9) -> 2839241.6
A6: Caixa e Equivalentes de Caixa | B6: Cash and Cash Equivalents | C6: 213914 | D6: 156596 | E6: 252019 | F6: 135308 | G6: 148782 | H6: 152282 | I6: 253708 | J6: 164755 | K6: 128303 | L6: 142889 | M6: 307549.35 | N6: 199150.99 | O6: 194270.62 | P6: 185971 | Q6: 200241 | R6: 258987 | S6: 109166 | T6: 168147.37 | U6: 134986.81
A7: Aplicações Financeiras | B7: Financial Investments | C7: 92028 | D7: 288095 | E7: 427131 | F7: 388154 | G7: 144775 | H7: 341837 | I7: 389407 | J7: 461895 | K7: 186850 | L7: 641501 | M7: 139208.38 | N7: 279009.79 | O7: 141252.85 | P7: 376268 | Q7: 298959 | R7: 154178 | S7: 177736.42 | T7: 127166.26 | U7: 267635.73
A8: Contas a Receber de Clientes Líquida | B8: Net Trade Receivables | C8: 1392847 | D8: 1499527 | E8: 1594860 | F8: 1566133 | G8: 1818252 | H8: 1769100 | I8: 1799505 | J8: 1836965 | K8: 1965965 | L8: 1803682 | M8: 1975362.1 | N8: 2080818.5 | O8: 2320094.5 | P8: 2108420.2 | Q8: 2138438.3 | R8: 2148456 | S8: 2471357.5 | T8: 2472710.2 | U8: 2380168.4
A9: Outros Ativos | B9: Other Assets | C9: 12875 | D9: 21499 | E9: 22038 | F9: 59998 | G9: 16916 | H9: 27456 | I9: 30610 | J9: 56248 | K9: 17062 | L9: 29270 | M9: 28017.368 | N9: 81378.18 | O9: 29551.35 | P9: 50576.32 | Q9: 49186.63 | R9: 127844 | S9: 63210.94 | T9: 59642.72 | U9: 56450.62
A11: Não circulante | B11: Non-current assets | C11: =SUM(C12:C14) -> 14136 | D11: =SUM(D12:D14) -> 14228 | E11: =SUM(E12:E14) -> 17675 | F11: =SUM(F12:F14) -> 15777 | G11: =SUM(G12:G14) -> 14504 | H11: =SUM(H12:H14) -> 14857 | I11: =SUM(I12:I14) -> 486780 | J11: =SUM(J12:J14) -> 304115 | ... U11: =SUM(U12:U14) -> 199021.29
A12: Outros Ativos | B12: Other Assets | C12: 7333 | D12: 7773 | E12: 11432 | F12: 8714 | G12: 7810 | H12: 8555 | I12: 51204 | J12: 47787 | K12: 48750 | L12: 55129 | M12: 60743.648 | N12: 46440.68 | O12: 50149.73 | P12: 50638.32 | Q12: 46232.28 | R12: 41609 | S12: 36279.37 | T12: 34480.84 | U12: 25795.13
A13: Imobilizado | B13: Property, Plant and Equipment | C13: 6146 | D13: 5745 | E13: 5552 | F13: 6374 | G13: 5957 | H13: 5558 | I13: 6699 | J13: 6406 | K13: 5877 | L13: 5416 | M13: 6899.5089 | N13: 7151.65 | O13: 6425.49 | P13: 5936.15 | Q13: 4679.06 | R13: 6955 | S13: 6312.36 | T13: 5599.12 | U13: 4950.86
A14: Intangível | B14: Intangible Assets | C14: 657 | D14: 710 | E14: 691 | F14: 689 | G14: 737 | H14: 744 | I14: 428877 | J14: 249922 | K14: 237168 | L14: 227830 | M14: 218775.97 | N14: 206853.81 | O14: 199544.45 | P14: 192053.07 | Q14: 183870.15 | R14: 175066 | S14: 172863.59 | T14: 170712.91 | U14: 168275.3
A16: PASSIVO | B16: LIABILITIES | C16: =C17+C24+C30 -> 1725800 | D16: =D17+D24+D30 -> 1979945 | E16: =E17+E24+E30 -> 2313723 | F16: =F17+F24+F30 -> 2165370 | G16: =G17+G24+G30 -> 2143229 | H16: =H17+H24+H30 -> 2305532 | I16: =I17+I24+I30 -> 2960010 | J16: =J17+J24+J30 -> 2823978 | ... U16: =U17+U24+U30 -> 3038263
A17: Circulante | B17: Current liabilities | C17: =SUM(C18:C22) -> 1644881 | D17: =SUM(D18:D22) -> 1891432 | E17: =SUM(E18:E22) -> 2215593 | F17: =SUM(F18:F22) -> 2051273 | G17: =SUM(G18:G22) -> 2029850 | H17: =SUM(H18:H22) -> 2186080 | I17: =SUM(I18:I22) -> 2331080 | J17: =SUM(J18:J22) -> 2361752 | ... U17: =SUM(U18:U22) -> 2395728.2
A18: Empréstimos e Arrendamentos | B18: Loans and Leases | C18: 102644 | D18: 103902 | E18: 102314 | F18: 104770 | G18: 1045 | H18: 1059 | I18: 1101 | J18: 1159 | K18: 1176 | L18: 252852 | M18: 620183.9 | N18: 1584.32 | O18: 101667.03 | P18: 9113.47 | Q18: 251449.71 | R18: 372744 | S18: 233344.85 | T18: 302582.53 | U18: 75915
A19: Debêntures | B19: Debentures | C19: 0 | D19: 0 | E19: 0 | F19: 0 | G19: 0 | H19: 0 | I19: 0 | J19: 0 | K19: 0 | L19: 0 | M19: 0 | N19: 0 | O19: 0 | P19: 0 | Q19: 0 | R19: 0 | S19: 0 | T19: 0 | U19: 0
A20: Repasse para parceiros | B20: Transfer to partners | C20: 381622 | D20: 432463 | E20: 526403 | F20: 520118 | G20: 608739 | H20: 621220 | I20: 689147 | J20: 678215 | K20: 713764 | L20: 703919 | M20: 506656.5 | N20: 779118.41 | O20: 721754.94 | P20: 988113.65 | Q20: 764019.5 | R20: 715141 | S20: 876801.61 | T20: 698867.02 | U20: 847194.14
A21: Cotas seniores e mezaninos | B21: Senior and Mezzanine Quota | C21: 1135225 | D21: 1322986 | E21: 1538368 | F21: 1372726 | G21: 1386758 | H21: 1512621 | I21: 1593971 | J21: 1638887 | K21: 1387918 | L21: 1449766 | M21: 903990.82 | N21: 1410463 | O21: 1412277.5 | P21: 1275303.9 | Q21: 1200564 | R21: 1111066 | S21: 1203660.7 | T21: 1293922.7 | U21: 1210399.8
A22: Outros Passivos | B22: Other Liabilities | C22: 25390 | D22: 32081 | E22: 48508 | F22: 53659 | G22: 33308 | H22: 51180 | I22: 46861 | J22: 43491 | K22: 27164 | L22: 41653 | M22: 47862.948 | N22: 52371.74 | O22: 57379.99 | P22: 56822.44 | Q22: 60981.15 | R22: 60568 | S22: 61046.22 | T22: 82206 | U22: 262219.23
A24: Não circulante | B24: Non-current liabilities | C24: =SUM(C25:C28) -> 2753 | D24: =SUM(D25:D28) -> 2646 | E24: =SUM(E25:E28) -> 2739 | F24: =SUM(F25:F28) -> 4230 | G24: =SUM(G25:G28) -> 4428 | H24: =SUM(H25:H28) -> 4222 | I24: =SUM(I25:I28) -> 4699 | J24: =SUM(J25:J28) -> 4870 | ... U24: =SUM(U25:U28) -> 13712.05
A25: Empréstimos e Arrendamentos | B25: Loans and Leases | C25: 2142 | D25: 1914 | E25: 1828 | F25: 2724 | G25: 2458 | H25: 2188 | I25: 1975 | J25: 1749 | K25: 1449 | L25: 1144 | M25: 2096.7637 | N25: 1790.17 | O25: 1455.46 | P25: 1115.45 | Q25: 866.88 | R25: 2364 | S25: 1723.95 | T25: 1262.02 | U25: 793.96
A26: Debêntures | B26: Debentures | C26: 0 | D26: 0 | E26: 0 | F26: 0 | G26: 0 | H26: 0 | I26: 0 | J26: 0 | K26: 0 | L26: 0 | M26: 0 | N26: 0 | O26: 0 | P26: 0 | Q26: 0 | R26: 0 | S26: 0 | T26: 0 | U26: 0
A27: Provisão para Contingências | B27: Provision for Contingencies | C27: 611 | D27: 637 | E27: 675 | F27: 708 | G27: 1039 | H27: 1038 | I27: 1097 | J27: 1166 | K27: 1617 | L27: 1642 | M27: 2500.293 | N27: 2477.58 | O27: 2381.53 | P27: 2645.47 | Q27: 1700.24 | R27: 936 | S27: 1025.68 | T27: 763.88 | U27: 708.84
A28: Outros Passivos | B28: Other Liabilities | C28: 0 | D28: 95 | E28: 236 | F28: 798 | G28: 931 | H28: 996 | I28: 1627 | J28: 1955 | K28: 2297 | L28: 8272 | M28: 4118.7622 | N28: 6265.12 | O28: 6160.43 | P28: 5659.15 | Q28: 6819.59 | R28: 6684 | S28: 10093.93 | T28: 9320.48 | U28: 12209.25
A30: Patrimônio líquido | B30: Shareholders' equity | C30: 78166 | D30: 85867 | E30: 95391 | F30: 109867 | G30: 108951 | H30: 115230 | I30: 624231 | J30: 457356 | K30: 454590 | L30: 446469 | M30: 649146.31 | N30: 646733.2 | O30: 638212.14 | P30: 631089.77 | Q30: 635205 | R30: 643592 | S30: 649228.96 | T30: 649535.26 | U30: 628822.72

Sheet Non-GAAP-Techfin-CF
A1: PORTUGUÊS | B1: ENGLISH
A2: Fluxo de Caixa Techfin (R$ mil) | B2: Techfin Cash Flow (R$ thousand) | C2: 1Q21 | D2: 2Q21 | E2: 3Q21 | F2: 4Q21 | G2: 1Q22 | H2: 2Q22 | I2: 3Q22 | J2: 4Q22 | K2: 1Q23 | L2: 2Q23 | M2: 3Q23 | N2: 4Q23 | O2: 1Q24 | P2: 2Q24 | Q2: 3Q24 | R2: 4Q24 | S2: 1Q25 | T2: 2Q25 | U2: 3Q25
A3: Fluxo de caixa das atividades operacionais: | B3: Operating Cashflow
A4: Lucro antes Tributação Imp. Renda e Contrib. Social | B4: Net income before taxes | C4: 1379 | D4: -7686 | E4: -7089 | F4: -2420 | G4: -9924 | H4: -2795 | I4: 8761 | J4: 8131 | K4: -6517 | L4: -12571 | M4: 17870 | N4: -3015 | O4: -8413 | P4: -5310 | Q4: 2747 | R4: 13639 | S4: 11232 | T4: 2132 | U4: -10089
A6: Ajustes por: | B6: Adjustments:
A7: Depreciação e Amortização | B7: Depreciation and Amortization | C7: 15831 | D7: 15696 | E7: 15236 | F7: 15173 | G7: 14680 | H7: 11276 | I7: 10110 | J7: 10519 | K7: 10593 | L7: 10195 | M7: 10096 | N7: 10067 | O7: 9452 | P7: 10049 | Q7: 8844 | R7: 9794 | S7: 3189 | T7: 3219.84 | U7: 3209.48
A8: Pagamento Baseado em Ações | B8: Share-based Payments Expense | C8: 0 | D8: 0 | E8: 0 | F8: 0 | G8: 0 | H8: 0 | I8: 3203 | J8: 694 | K8: 695 | L8: 280 | M8: 1858 | N8: 1280 | O8: 0 | P8: 1089 | Q8: 360 | R8: -185 | S8: 766 | T8: -1071 | U8: -7
A9: Perda (Ganho) na Baixa de Ativos | B9: Losses on Disposal of Fixed Assets and Inv. | C9: 0 | D9: -121 | E9: 0 | F9: 0 | G9: 0 | H9: 1 | I9: 63 | J9: 952 | K9: 0 | L9: -177 | M9: 251 | N9: 2724 | O9: 0 | P9: 50 | Q9: -32 | R9: 1669 | S9: 0 | T9: 0 | U9: 287
A10: Provisão para Perda Esperada | B10: Provision for Expected Credit Losses | C10: 5475 | D10: 4337 | E10: 4092 | F10: 1818 | G10: 10227 | H10: 7278 | I10: 7011 | J10: 16007 | K10: 8290 | L10: 6758 | M10: 9684 | N10: 8541 | O10: 6693 | P10: 9090 | Q10: 7562 | R10: 7262 | S10: 7103 | T10: 8511 | U10: 9930
A11: Equivalência Patrimonial | B11: Equity Pickup | C11: 0 | D11: 0 | E11: 0 | F11: 0 | G11: 0 | H11: 0 | I11: 0 | J11: 0 | K11: 0 | L11: 0 | M11: 0 | N11: 0 | O11: 0 | P11: 0 | Q11: 0 | R11: 0 | S11: 0 | T11: 0 | U11: 35493.01
A12: Provisão (Reversão) para Contingências | B12: Provision for Contingencies, Net of Reversals | C12: 16 | D12: 29 | E12: -10 | F12: 42 | G12: 471 | H12: -155 | I12: 119 | J12: 137 | K12: 420 | L12: -12 | M12: 909 | N12: 378 | O12: 3865 | P12: -3698 | Q12: -945 | R12: -764 | S12: 90 | T12: -296.75 | U12: -84.54
A13: Provisão (Reversão) de outras Obrig. e Outros | B13: Provision (Reversal) for Other Obligations | C13: 0 | D13: 834 | E13: -834 | F13: 0 | G13: 0 | H13: 0 | I13: 0 | J13: 0 | K13: 0 | L13: 0 | M13: 0 | N13: 0 | O13: 0 | P13: 0 | Q13: 0 | R13: 0 | S13: 0 | T13: 0 | U13: 0
A14: Remuneração dos cotistas seniores e mezaninos do FIDC | B14: Remuneration of FIDC senior and mezanine quotas | C14: 28193 | D14: 22928 | E14: 15492 | F14: 11781 | G14: 34025 | H14: 41400 | I14: 48255 | J14: 44527 | K14: 46759 | L14: 40736 | M14: 29522 | N14: 29517 | O14: 43863 | P14: 41473 | Q14: 38256 | R14: 35059 | S14: 38359 | T14: 43693.57 | U14: 48013.58
A15: Juros e Variação Cambiais e Monetárias Líquidas | B15: Net Interest, Monetary and Exchange Variations | C15: 2437 | D15: 975 | E15: 2416 | F15: 829 | G15: 2866 | H15: 72 | I15: 49 | J15: 36 | K15: 67 | L15: 22 | M15: 6208 | N15: 5098 | O15: -13465 | P15: 919 | Q15: -3049 | R15: -2407 | S15: -3644 | T15: -1166.57 | U15: -14301.94
A17: Variação em ativos e passivos operacionais: | B17: Changes in operating assets and liabilities:
A18: Contas a Receber de Clientes | B18: Trade Receivables | C18: 23249 | D18: -99670 | E18: -110771 | F18: -282513 | G18: -262345 | H18: 41873 | I18: -34675 | J18: -54009 | K18: -137290 | L18: 155525 | M18: -181364 | N18: -113998 | O18: -245968 | P18: 202582 | Q18: -37580 | R18: -17279 | S18: -330005 | T18: -9863 | U18: 82612
A19: Impostos a Recuperar | B19: Recoverable Taxes | C19: -7475 | D19: -3367 | E19: -4782 | F19: 1852 | G19: 16095 | H19: -4021 | I19: -11457 | J19: 8405 | K19: -2545 | L19: -3738 | M19: -3369 | N19: -11641 | O19: 0 | P19: -1869 | Q19: 321 | R19: 927 | S19: -4330 | T19: -848 | U19: -816
A20: Depósitos Judiciais | B20: Judicial Deposits | C20: 1 | D20: -1 | E20: -7 | F20: -3 | G20: -22 | H20: 0 | I20: 0 | J20: 0 | K20: -37 | L20: -24 | M20: -37 | N20: 13 | O20: 0 | P20: 2 | Q20: 279 | R20: -2 | S20: 22 | T20: -3 | U20: -6
A21: Outros Ativos | B21: Other Assets | C21: -29979 | D21: 3540 | E21: -4864 | F21: 29253 | G21: 26417 | H21: -6228 | I21: 4415 | J21: -35474 | K21: 40566 | L21: -9206 | M21: -2449 | N21: -41402 | O21: 48984 | P21: -16559 | Q21: 1182 | R21: -79585 | S21: 69021 | T21: 4416 | U21: 4008
A22: Obrigações Sociais e Trabalhistas | B22: Labor Liabilities | C22: 3034 | D22: 2295 | E22: -5090 | F22: 5471 | G22: -8162 | H22: 2536 | I22: -765 | J22: 1352 | K22: -7101 | L22: 5342 | M22: 11899 | N22: 31 | O22: 0 | P22: -3796 | Q22: 5424 | R22: 2966 | S22: -12148 | T22: 6684 | U22: 6663
A23: Fornecedores | B23: Trade and Other Payables | C23: 1178 | D23: 545 | E23: -723 | F23: 909 | G23: -1669 | H23: 3123 | I23: -1436 | J23: -469 | K23: -3832 | L23: 810 | M23: 5344 | N23: 6307 | O23: 0 | P23: 154 | Q23: -1879 | R23: -2165 | S23: 1673 | T23: 1026 | U23: 291
A24: Comissões a Pagar | B24: Commissions Payable | C24: -2740 | D24: 2969 | E24: 473 | F24: -893 | G24: 329 | H24: 888 | I24: -1562 | J24: 369 | K24: 275 | L24: 957 | M24: 469 | N24: -786 | O24: 0 | P24: 1156 | Q24: 1173 | R24: -685 | S24: -907 | T24: -560 | U24: 492
A25: Impostos a Pagar | B25: Taxes and Contributions Payable | C25: -1933 | D25: -461 | E25: -5126 | F25: -257 | G25: -20249 | H25: 4356 | I25: 12070 | J25: -8730 | K25: 984 | L25: 586 | M25: 3944 | N25: 3873 | O25: 2359 | P25: -2419 | Q25: 914 | R25: 1738 | S25: 440 | T25: 624.64 | U25: 1016
A26: Repasse para Parceiros | B26: Business Partners Payable | C26: -6285 | D26: 93940 | E26: 50841 | F26: 52805 | G26: 88621 | H26: 12481 | I26: 67927 | J26: -10932 | K26: 35549 | L26: -9845 | M26: -197263 | N26: 272462 | O26: -58837 | P26: 267833 | Q26: -224095 | R26: -48878 | S26: 161661 | T26: -177935 | U26: 148327
A27: Outras Contas a Pagar | B27: Other Accounts Payable | C27: -2268 | D27: 2682 | E27: 9449 | F27: -8653 | G27: -1443 | H27: 3727 | I27: -8783 | J27: 3784 | K27: -5445 | L27: 7218 | M27: -5974 | N27: -2205 | O27: 0 | P27: 142 | Q27: 4666 | R27: -869 | S27: 13635 | T27: 12935 | U27: 2609.06
A28: Geração Operacional de Caixa | B28: Operating Cash Generation | C28: =SUM(C4,C7:C15,C18:C27) -> 30113 | D28: =SUM(D4,D7:D15,D18:D27) -> 39464 | E28: =SUM(E4,E7:E15,E18:E27) -> -41297 | F28: =SUM(F4,F7:F15,F18:F27) -> -174806 | G28: =SUM(G4,G7:G15,G18:G27) -> -110083 | H28: =SUM(H4,H7:H15,H18:H27) -> 115812 | I28: =SUM(I4,I7:I15,I18:I27) -> 103305 | J28: =SUM(J4,J7:J15,J18:J27) -> -14701 | ... U28: =SUM(U4,U7:U15,U18:U27) -> 317646.65
A30: Juros Pagos | B30: Interest paid | C30: -45 | D30: -3356 | E30: -13 | F30: -37 | G30: -6550 | H30: -15 | I30: -15 | J30: 11 | K30: -41 | L30: -36 | M30: -64 | N30: -11255 | O30: -52 | P30: -366 | Q30: -508 | R30: -3626 | S30: -56 | T30: -47.95 | U30: -39.57
A31: IR e CSLL Pagos | B31: Tax Paid | C31: 0 | D31: 0 | E31: 3101 | F31: -3101 | G31: 0 | H31: -5164 | I31: -2480 | J31: -1454 | K31: 0 | L31: 0 | M31: -45 | N31: -62 | O31: -371 | P31: 39 | Q31: -125 | R31: -350 | S31: -1243 | T31: -9.64 | U31: 0
A32: Caixa Líquido das Atividades Operacionais | B32: Net Cash from Operating Activities | C32: =SUM(C28,C30:C31) -> 30068 | D32: =SUM(D28,D30:D31) -> 36108 | E32: =SUM(E28,E30:E31) -> -38209 | F32: =SUM(F28,F30:F31) -> -177944 | G32: =SUM(G28,G30:G31) -> -116633 | H32: =SUM(H28,H30:H31) -> 110633 | I32: =SUM(I28,I30:I31) -> 100810 | J32: =SUM(J28,J30:J31) -> -16144 | ... U32: =SUM(U28,U30:U31) -> 317607.08
A34: Fluxo de caixa proveniente de atividades em investimentos | B34: Investing activities cash flow
A35: Aumento de Ativo Imobilizado | B35: Acquisitions of Prop. Plant and Equip. | C35: -88 | D35: -97 | E35: -64 | F35: -944 | G35: -91 | H35: -109 | I35: -1033 | J35: -292 | K35: -97 | L35: -268 | M35: -582 | N35: -1030 | O35: -273 | P35: -149 | Q35: -37 | R35: -92 | S35: -155 | T35: -117.79 | U35: -238.21
A36: Aumento de Intangível | B36: Acquisition of Intangible Assets | C36: -52 | D36: -36 | E36: -109 | F36: 1 | G36: -102 | H36: -62 | I36: -791 | J36: -2241 | K36: -21 | L36: -158 | M36: -472 | N36: -110 | O36: -1143 | P36: -1969 | Q36: -79 | R36: 0 | S36: -189 | T36: -239.06 | U36: -171.94
A37: Mútuo com Franquias | B37: Franchises Loan | C37: 0 | D37: 0 | E37: 0 | F37: 0 | G37: 0 | H37: 0 | I37: 0 | J37: 0 | K37: 0 | L37: 0 | M37: 0 | N37: 0 | O37: 0 | P37: 0 | Q37: 0 | R37: 0 | S37: 0 | T37: 0 | U37: 0
A38: Aquisição de Participação Societária | B38: Acquisition of Subsidiaries, Net of Cash | C38: 0 | D38: 0 | E38: 0 | F38: 0 | G38: 0 | H38: 0 | I38: 0 | J38: 0 | K38: 0 | L38: 0 | M38: 0 | N38: 0 | O38: 0 | P38: 0 | Q38: 0 | R38: 0 | S38: 0 | T38: 0 | U38: 0
A39: Pag. de Obrig. por Aquisição de Invest. | B39: Payments from Acquisitions of Subsidiaries | C39: 0 | D39: 0 | E39: 0 | F39: 0 | G39: 0 | H39: 0 | I39: 0 | J39: 0 | K39: 0 | L39: 0 | M39: 0 | N39: 0 | O39: 0 | P39: 0 | Q39: 0 | R39: 0 | S39: 0 | T39: 0 | U39: 0
A40: Venda (Aquisição) de Investimentos | B40: Proceeds from Sale of Subsid., Net of Cash | C40: 0 | D40: 0 | E40: 0 | F40: 0 | G40: 0 | H40: 0 | I40: 0 | J40: 0 | K40: 0 | L40: 0 | M40: 0 | N40: 0 | O40: 0 | P40: 0 | Q40: 0 | R40: 0 | S40: 0 | T40: 0 | U40: 0
A41: Valor da Venda de Ativo Imobilizado | B41: Proceeds from Sale of Prop. Plant and Equip. | C41: 0 | D41: 121 | E41: 0 | F41: 0 | G41: 0 | H41: 0 | I41: 8 | J41: 169 | K41: 0 | L41: 207 | M41: 0 | N41: 77 | O41: 0 | P41: 0 | Q41: 360 | R41: -360 | S41: 0 | T41: 0 | U41: 0
A42: Resgate (Investimento) Financeiro | B42: Financial Rescue (Investment) | C42: 45593 | D42: -133270 | E42: -194326 | F42: 88237 | G42: 251483 | H42: -191620 | I42: -36378 | J42: -59574 | K42: 285040 | L42: -445842 | M42: 508015 | N42: -129154 | O42: 150899 | P42: -235178 | Q42: 83229 | R42: 151160 | S42: -19579 | T42: 52301.36 | U42: -128611.36
A43: Caixa da Dim. Techfin | B43: Net cash in Techfin Dim. | C43: 0 | D43: 0 | E43: 0 | F43: 0 | G43: 0 | H43: 0 | I43: 0 | J43: 0 | K43: 0 | L43: 0 | M43: 77 | N43: 0 | O43: 0 | P43: 0 | Q43: 0 | R43: 0 | S43: 0 | T43: 0 | U43: 0
A44: Fluxo de caixa proveniente de atividades em investimentos | B44: Investing activities cash flow | C44: =SUM(C35:C43) -> 45453 | D44: =SUM(D35:D43) -> -133282 | E44: =SUM(E35:E43) -> -194499 | F44: =SUM(F35:F43) -> 87294 | G44: =SUM(G35:G43) -> 251290 | H44: =SUM(H35:H43) -> -191791 | I44: =SUM(I35:I43) -> -38194 | J44: =SUM(J35:J43) -> -61938 | ... U44: =SUM(U35:U43) -> -129021.51
A46: Fluxo de caixa proveniente de atividades de financiamento | B46: Financing activities cash flow
A47: Pag. de Principal de Emp. e Financ. | B47: Payment of Princ. of Loans and Financing | C47: 0 | D47: 0 | E47: 0 | F47: 0 | G47: -100000 | H47: 0 | I47: 0 | J47: 0 | K47: 0 | L47: 0 | M47: 0 | N47: -600000 | O47: 0 | P47: -100390 | Q47: -3321 | R47: -235709 | S47: -353737 | T47: -205879 | U47: -427262
A48: Pag. de Principal de Debêntures | B48: Payment of Principal of Debentures | C48: 0 | D48: 0 | E48: 0 | F48: 0 | G48: 0 | H48: 0 | I48: 0 | J48: 0 | K48: 0 | L48: 0 | M48: 0 | N48: 0 | O48: 0 | P48: 0 | Q48: 0 | R48: 0 | S48: 0 | T48: 0 | U48: 0
A49: Pag. de Parcelas de Arrend. Mercantil | B49: Payment of Principal of Lease Liabilities | C49: -245 | D49: -291 | E49: -300 | F49: -297 | G49: -288 | H49: -288 | I49: -289 | J49: -305 | K49: -283 | L49: -288 | M49: -399 | N49: -415 | O49: -424 | P49: -529 | Q49: -401 | R49: -1755 | S49: -595 | T49: -594.62 | U49: -538.38
A50: Captação de Debên e Empr. e Fin. | B50: Proceeds from debentures, loans and finan. | C50: 0 | D50: 0 | E50: 0 | F50: 0 | G50: 0 | H50: 0 | I50: 0 | J50: 0 | K50: 0 | L50: 250000 | M50: 350000 | N50: 0 | O50: 100000 | P50: 7800 | Q50: 244000 | R50: 353800 | S50: 215340 | T50: 275500 | U50: 353190
A51: Resgate (Aplic.) de Cotas Seniores e Mezanino | B51: Red. (Aplic.) of Senior and Mezanine Quotas | C51: -200450 | D51: 186688 | E51: 170528 | F51: 111399 | G51: -28096 | H51: 79020 | I51: 21903 | J51: -12525 | K51: -307723 | L51: 12303 | M51: -581019 | N51: 466307 | O51: -42049 | P51: -178446 | Q51: -112996 | R51: -124557 | S51: 54236 | T51: 46568.9 | U51: -131536.9
A52: Aumento de Capital Líquido de Gastos | B52: Capital Increase, Net of Expenses | C52: 3431 | D52: 5162 | E52: 7573 | F52: 9209 | G52: 7201 | H52: 5926 | I52: 18252 | J52: 2403 | K52: 5012 | L52: -235 | M52: 199923 | N52: 0 | O52: 0 | P52: 0 | Q52: 0 | R52: 0 | S52: 0 | T52: 0 | U52: 0
A53: Caixa Investido na Dim. Techfin | B53: Net cash Invested in Techfin Dim. | C53: 0 | D53: 0 | E53: 0 | F53: 0 | G53: 0 | H53: 0 | I53: 0 | J53: 0 | K53: 0 | L53: 0 | M53: 0 | N53: 0 | O53: 0 | P53: 0 | Q53: 0 | R53: 0 | S53: 0 | T53: 0 | U53: 0
A54: Crédito com Empresas Ligadas | B54: Receivables from Related Companies | C54: 0 | D54: 0 | E54: 0 | F54: 0 | G54: 0 | H54: 0 | I54: 444 | J54: -444 | K54: 230 | L54: 6047 | M54: -6277 | N54: 0 | O54: 0 | P54: 0 | Q54: 0 | R54: 0 | S54: 0 | T54: 0 | U54: 0
A55: Dividendos e JCP Pago | B55: Dividends and Interest on Equity Paid | C55: -746 | D55: -1373 | E55: 0 | F55: 0 | G55: 0 | H55: 0 | I55: -1500 | J55: 0 | K55: 0 | L55: 0 | M55: -12095 | N55: 0 | O55: 0 | P55: 0 | Q55: 0 | R55: 0 | S55: 0 | T55: 0 | U55: -15598
A56: Ações em Tesouraria, Líquidas | B56: Net Treasury Shares | C56: 0 | D56: 0 | E56: 0 | F56: 0 | G56: 0 | H56: 0 | I56: 0 | J56: 0 | K56: 0 | L56: 0 | M56: 0 | N56: 0 | O56: 0 | P56: 0 | Q56: 0 | R56: 0 | S56: 0 | T56: 0 | U56: 0
A57: Fluxo de caixa proveniente de atividades de financiamento | B57: Net cash used in financing activities | C57: =SUM(C47:C56) -> -198010 | D57: =SUM(D47:D56) -> 190186 | E57: =SUM(E47:E56) -> 177801 | F57: =SUM(F47:F56) -> 120311 | G57: =SUM(G47:G56) -> -121183 | H57: =SUM(H47:H56) -> 84658 | I57: =SUM(I47:I56) -> 38810 | J57: =SUM(J47:J56) -> -10871 | ... U57: =SUM(U47:U56) -> -221745.28
A59: Aumento das disponibilidades | B59: Increase (decrease) in cash and cash equivalents | C59: =SUM(C32,C44,C57) -> -122489 | D59: =SUM(D32,D44,D57) -> 93012 | E59: =SUM(E32,E44,E57) -> -54907 | F59: =SUM(F32,F44,F57) -> 29661 | G59: =SUM(G32,G44,G57) -> 13474 | H59: =SUM(H32,H44,H57) -> 3500 | I59: =SUM(I32,I44,I57) -> 101426 | J59: =SUM(J32,J44,J57) -> -88953 | ... U59: =SUM(U32,U44,U57) -> -33159.71
A61: Caixa e equivalente de caixa no início do período | B61: Cash and cash equivalents at the beginning of the period | C61: 190031 | D61: =ROUND(C62,0) -> 67542 | E61: =ROUND(D62,0) -> 160554 | F61: =ROUND(E62,0) -> 105647 | G61: =ROUND(F62,0) -> 135308 | H61: =ROUND(G62,0) -> 148782 | I61: =ROUND(H62,0) -> 152282 | J61: =ROUND(I62,0) -> 253708 | K61: =ROUND(J62,0) -> 164755 | ... U61: =ROUND(T62,0) -> 168147
A62: Caixa e equivalente de caixa no fim do período | B62: Cash and cash equivalents at the end of the period | C62: =C61+C59 -> 67542 | D62: =D61+D59 -> 160554 | E62: =E61+E59 -> 105647 | F62: =F61+F59 -> 135308 | G62: =G61+G59 -> 148782 | H62: =H61+H59 -> 152282 | I62: =I61+I59 -> 253708 | J62: =J61+J59 -> 164755 | ... U62: =U61+U59 -> 134987.29
A64: Receita Aplicação Financeira Líq. Impostos | B64: Revenue from financial investment, net of Taxes | C64: 0 | D64: 0 | E64: 0 | F64: 0 | G64: 185 | H64: 117 | I64: 250 | J64: 327 | K64: 69 | L64: 900 | M64: 4953 | N64: 5676 | O64: 5070 | P64: 3756 | Q64: 3827 | R64: 2775 | S64: 3504 | T64: 3870 | U64: 1094
A65: Fluxo de Caixa Livre da Empresa | B65: Free Cash Flow to Firm | G65: =G28+G31+G35+G36+G41+G49-G64 -> -110749 | H65: =H28+H31+H35+H36+H41+H49-H64 -> 110072 | I65: =I28+I31+I35+I36+I41+I49-I64 -> 98470 | J65: =J28+J31+J35+J36+J41+J49-J64 -> -19151 | K65: =K28+K31+K35+K36+K41+K49-K64 -> -19039 | L65: =L28+L31+L35+L36+L41+L49-L64 -> 191449 | M65: =M28+M31+M35+M36+M41+M49-M64 -> -298853 | N65: =N28+N31+N35+N36+N41+N49-N64 -> 160028 | ... U65: =U28+U31+U35+U36+U41+U49-U64 -> 315604.12
