Workbook

Sheet dados_original
A1: nome_arquivo | B1: nome_projeto | C1: data_comite | D1: tipo_comite | E1: cenario | F1: unidades | G1: avaliacao_unit | H1: fracao_terreno_pct | I1: valor_rs_m2 | J1: custo_construcao_rs | K1: custo_construcao_pct_vgv | L1: prazo_obra_meses | M1: custo_total_unit | N1: custo_adc_selling | O1: preco_nominal_unit | P1: preco_raso_unit | Q1: li_pct | R1: li_regua_pct | S1: margem_bruta_economica_pct | T1: margem_rasa_economica_pct | U1: exposicao_rs_mil | V1: exposicao_pct_vgv | W1: renda | X1: pct_ret1 | Y1: pct_tcd | Z1: raso_sobre_custo
A2: 2025.01.20 - Acqua Danubio -Lançamento.pdf | B2: Acqua Danúbio | C2: 20/01/2025 | D2: Book de Lançamento | E2: Aprovacao | F2: 388 | G2: 203835 | H2: 0.033 | I2: 398 | J2: 40555 | K2: 0.487 | L2: 18 | M2: 104524 | O2: 214464 | P2: 190902 | Q2: 0.203 | R2: 0.2 | S2: 0.401 | T2: 0.245 | U2: 16047 | V2: 0.12 | W2: 2521 | X2: 0.5 | Y2: =(O2-P2)/O2 -> 0.10986459 | Z2: =P2/M2 -> 1.8263939
A3: 2025.01.20 - Acqua Danubio -Lançamento.pdf | B3: Acqua Danúbio | C3: 20/01/2025 | D3: Book de Lançamento | E3: Real | F3: 597 | G3: 204302 | H3: 0.033 | I3: 398 | J3: 60520 | K3: 0.467 | L3: 18 | M3: 101373 | O3: 217040 | P3: 193235 | Q3: 0.201 | R3: 0.2 | S3: 0.42 | T3: 0.341 | U3: 16950 | V3: 0.127 | W3: 2555 | X3: 0.412 | Y3: =(O3-P3)/O3 -> 0.10968024 | Z3: =P3/M3 -> 1.9061782
A4: 2025.11.07 - Acqua Viena - Investimento - Respostas REV01.pdf | B4: Acqua Viena | C4: 07/11/2025 | D4: Book de Investimento | E4: Aprovacao | F4: 600 | G4: 234 | H4: 0.07 | I4: 848 | J4: 61094 | K4: 0.46 | L4: 17 | M4: 101823.4 | O4: 220700 | P4: 201227 | Q4: 0.2 | R4: 0.2 | S4: 0.4 | T4: 0.332 | U4: 13557 | V4: 0.09 | W4: 3373 | X4: 0.298 | Y4: =(O4-P4)/O4 -> 0.088232895 | Z4: =P4/M4 -> 1.9762353
A5: 2025.09.25 - Panorama Santo André - lançamento_Respostas.pdf | B5: Adriático (Panorama Santo André) | C5: 25/09/2025 | D5: Comitê de escritura e lançamento | E5: Aprovacao | F5: 642 | G5: 269717 | H5: 0.08 | I5: 1618 | J5: 72330 | K5: 0.415 | L5: 23 | M5: 112664 | O5: 271451 | P5: 248101 | Q5: 0.207 | R5: 0.2 | S5: 0.403 | T5: 0.339 | U5: 17174 | V5: 0.1 | W5: 4886 | X5: 0 | Y5: =(O5-P5)/O5 -> 0.086019208 | Z5: =P5/M5 -> 2.202132
A6: 2025.09.25 - Panorama Santo André - lançamento_Respostas.pdf | B6: Adriático (Panorama Santo André) | C6: 25/09/2025 | D6: Comitê de escritura e lançamento | E6: Real | F6: 642 | G6: 269717 | H6: 0.08 | I6: 1664 | J6: 72330 | K6: 0.409 | L6: 23 | M6: 112664 | O6: 275377 | P6: 252026 | Q6: 0.213 | R6: 0.2 | S6: 0.407 | T6: 0.343 | U6: 13648 | V6: 0.078 | W6: 4886 | X6: 0 | Y6: =(O6-P6)/O6 -> 0.084796479 | Z6: =P6/M6 -> 2.2369701
A7: 2025.02.14 - Altiplano Sunset - Investimento.pdf | B7: Altiplano Sunset | C7: 10/02/2025 | D7: Book de Investimento | E7: Aprovacao | F7: 712 | G7: 239775 | H7: 0.093 | I7: 1035 | J7: 69445 | K7: 0.435 | L7: 17 | M7: 97536 | O7: 224103 | P7: 201035 | Q7: 0.2 | R7: 0.2 | S7: 0.385 | T7: 0.306 | U7: 11267 | V7: 0.064 | W7: 3204 | X7: 0.381 | Y7: =(O7-P7)/O7 -> 0.10293481 | Z7: =P7/M7 -> 2.0611364
A8: 2025.08.04 - Alto da Colina - Escritura REV01_Resposta.pdf | B8: Alto da Colina | C8: 04/08/2025 | D8: Book de Escritura | E8: Aprovacao | F8: 696 | G8: 232598 | H8: 0.06 | I8: 792 | J8: 73392 | K8: 0.468 | L8: 22 | M8: 105448 | O8: 225486 | P8: 202688 | Q8: 0.2 | R8: 0.2 | S8: 0.382 | T8: 0.304 | U8: 18827 | V8: 0.119 | W8: 3205 | X8: 0.403 | Y8: =(O8-P8)/O8 -> 0.10110606 | Z8: =P8/M8 -> 1.9221607
A9: 2025.09.25 - Alto da Colina - Lançamento.pdf | B9: Alto da Colina | C9: 25/09/2025 | D9: Book de Lançamento | E9: Real | F9: 696 | G9: 232598 | H9: 0.06 | I9: 793 | J9: 72544 | K9: 0.463 | L9: 22 | M9: 104230 | O9: 224978 | P9: 202871 | Q9: 0.201 | R9: 0.2 | S9: 0.384 | T9: 0.308 | U9: 19280 | V9: 0.124 | W9: 3243 | X9: 0.333 | Y9: =(O9-P9)/O9 -> 0.098262941 | Z9: =P9/M9 -> 1.9463782
A10: 2025.09.05 -Alvorada Aricanduva - Escritura + Lanç_Respostas.pdf | B10: Alvorada Aricanduva (Sobral) | C10: 05/09/2025 | D10: Comitê de escritura e lançamento | E10: Aprovacao | F10: 577 | G10: 248000 | H10: 0.086 | I10: 3608 | J10: 60613 | K10: 0.446 | L10: 23 | M10: 105049 | O10: 235485 | P10: 220993 | Q10: 0.2 | R10: 0.2 | S10: 0.365 | T10: 0.318 | U10: 9982 | V10: 0.074 | W10: 3648 | X10: 0.25 | Y10: =(O10-P10)/O10 -> 0.061541075 | Z10: =P10/M10 -> 2.1037135
A11: 2025.09.05 -Alvorada Aricanduva - Escritura + Lanç_Respostas.pdf | B11: Alvorada Aricanduva (Sobral) | C11: 05/09/2025 | D11: Comitê de escritura e lançamento | E11: Real | F11: 577 | G11: 248000 | H11: 0.086 | I11: 3608 | J11: 60613 | K11: 0.448 | L11: 23 | M11: 105049 | O11: 234664 | P11: 217861 | Q11: 0.195 | R11: 0.2 | S11: 0.369 | T11: 0.314 | U11: 13375 | V11: 0.1 | W11: 3658 | X11: 0.25 | Y11: =(O11-P11)/O11 -> 0.071604507 | Z11: =P11/M11 -> 2.0738988
A12: 2025.06.17 - Americanópolis - Essencial.pdf | B12: Americanópolis | C12: 17/06/2025 | D12: Comitê Essencial | E12: Aprovacao | F12: 707 | G12: 277595 | H12: 0.127 | I12: 5273 | J12: 70183 | K12: 0.388 | L12: 22 | M12: 99269 | O12: 255663 | P12: 247267 | Q12: 0.2 | R12: 0.2 | S12: 0.377 | T12: 0.353 | U12: 22565 | V12: 0.114 | W12: 4495 | X12: 0.13 | Y12: =(O12-P12)/O12 -> 0.032840106 | Z12: =P12/M12 -> 2.4908783
A13: 2025.06.30 - Araçá Prime - Investimento - atualização.pdf | B13: Araçá Prime | C13: 30/06/2025 | D13: Book de Investimento | E13: Aprovacao | F13: 428 | G13: 290000 | H13: 0.105 | I13: 2846 | J13: 46758 | K13: 0.409 | L13: 18 | M13: 109247 | O13: 266782 | P13: 246703 | Q13: 0.185 | R13: 0.2 | S13: 0.396 | T13: 0.341 | U13: 22248 | V13: 0.187 | W13: 5211 | X13: 0 | Y13: =(O13-P13)/O13 -> 0.075263698 | Z13: =P13/M13 -> 2.258213
... A61: 2025.12.19 - Elevato Ramos - Lançamento REV03_Respostas.pdf | B61: Elevato Ramos – RZN2 | C61: 19/12/2025 | D61: Book de Lançamento - Respostas | E61: Aprovacao | F61: 494 | G61: 243006 | H61: 0.088 | I61: 2398 | J61: 49509 | K61: 0.42 | L61: 19 | M61: 100220 | O61: 238783 | P61: 217628 | Q61: 0.197 | R61: 0.2 | S61: 0.399 | T61: 0.334 | U61: 15273 | V61: 0.131 | W61: 4135 | X61: 0 | Y61: =(O61-P61)/O61 -> 0.088595084 | Z61: =P61/M61 -> 2.1715027
A62: 2026.03.20 - Elevato Ramos - Lançamento EE.1_Respostas.pdf | B62: Elevato Ramos – RZN2 | C62: 20/03/2026 | D62: Book de Lançamento | E62: Aprovacao | F62: 494 | G62: 243006 | H62: 0.087 | I62: 2451 | J62: 50111 | K62: 0.413 | L62: 19 | M62: 101439 | N62: 0.001 | O62: 245505 | P62: 216533 | Q62: 0.221 | R62: 0.22 | S62: 0.42 | T62: 0.33 | U62: 14440 | V62: 0.119 | W62: 4135 | X62: 0.182 | Y62: =(O62-P62)/O62 -> 0.11800982 | Z62: =P62/M62 -> 2.1346129
A63: 2026.03.20 - Elevato Ramos - Lançamento EE.1_Respostas.pdf | B63: Elevato Ramos – RZN2 | C63: 20/03/2026 | D63: Book de Lançamento | E63: Real | F63: 494 | G63: 243006 | H63: 0.087 | I63: 2472 | J63: 50111 | K63: 0.409 | L63: 19 | M63: 101439 | N63: 0.001 | O63: 248120 | P63: 219293 | Q63: 0.224 | R63: 0.22 | S63: 0.42 | T63: 0.331 | U63: 11933 | V63: 0.097 | W63: 4135 | X63: 0.182 | Y63: =(O63-P63)/O63 -> 0.11618169 | Z63: =P63/M63 -> 2.1618214
A64: 2026.03.20 - Elevato Ramos - Lançamento EE.1_Respostas.pdf | B64: Elevato Ramos – RZN2 | C64: 20/03/2026 | D64: Book de Lançamento | E64: Aprovacao | F64: 494 | G64: 243006 | H64: 0.087 | I64: 2472 | J64: 50111 | K64: 0.413 | L64: 19 | M64: 101439 | O64: 245505 | P64: 216533 | Q64: 0.221 | R64: 0.22 | S64: 0.42 | T64: 0.33 | U64: 14440 | V64: 0.119 | W64: 4135 | X64: 0.182 | Y64: =(O64-P64)/O64 -> 0.11800982 | Z64: =P64/M64 -> 2.1346129
A65: 2025.11.03 - Elevato Trinitá - Investimento 2F - REV00 Final.pdf | B65: Elevato Trinità | C65: 03/11/2025 | D65: Comite Ampliado de Investimento | E65: Aprovacao | F65: 634 | G65: 288139 | H65: 0.158 | I65: 5027 | J65: 63007 | K65: 0.367 | L65: 17 | M65: 99380 | O65: 270979 | P65: 250150 | Q65: 0.2 | R65: 0.2 | S65: 0.395 | T65: 0.339 | U65: 9106 | V65: 0.048 | W65: 5299 | X65: 0 | Y65: =(O65-P65)/O65 -> 0.076865735 | Z65: =P65/M65 -> 2.5171061
A66: 2025.10.20 - Elevato Uno - Rev. c. Reneg. REV05 final.pdf | B66: Elevato Uno | C66: 20/10/2025 | D66: Comite de Reversão com Reneg. | E66: Aprovacao | F66: 370 | G66: 286589 | H66: 0.128 | I66: 6266 | J66: 37334 | K66: 0.36 | L66: 18 | M66: 100902 | O66: 280420 | P66: 258705 | Q66: 0.211 | R66: 0.2 | S66: 0.404 | T66: 0.348 | U66: 13492 | V66: 0.128 | W66: 5436 | X66: 0 | Y66: =(O66-P66)/O66 -> 0.077437415 | Z66: =P66/M66 -> 2.5639234
A67: 2025.05.19 - Encanto Piatã F2 - Lançamento REV02_Respostas.pdf | B67: Encanto Piatã - F2 | C67: 19/05/2025 | D67: Book de Lançamento | E67: Aprovacao | F67: 1043 | G67: 263317 | H67: 0.067 | I67: 1139 | J67: 91594 | K67: 0.347 | L67: 21 | M67: 87818 | O67: 253150 | P67: 229232 | Q67: 0.304 | R67: 0.2 | S67: 0.515 | T67: 0.459 | U67: 18808 | V67: 0.07 | W67: 4693 | X67: 0 | Y67: =(O67-P67)/O67 -> 0.094481533 | Z67: =P67/M67 -> 2.6103077
A68: 2025.05.19 - Encanto Piatã F2 - Lançamento REV02_Respostas.pdf | B68: Encanto Piatã - F2 | C68: 19/05/2025 | D68: Book de Lançamento | E68: Real | F68: 1043 | G68: 263317 | H68: 0.066 | I68: 1139 | J68: 91594 | K68: 0.343 | L68: 21 | M68: 87818 | O68: 255972 | P68: 231996 | Q68: 0.305 | R68: 0.2 | S68: 0.517 | T68: 0.46 | U68: 16646 | V68: 0.061 | W68: 4194 | X68: 0 | Y68: =(O68-P68)/O68 -> 0.093666495 | Z68: =P68/M68 -> 2.6417819
A69: 2026.03.02 - Encanto Piatã F3 - Lançamento REV01.pdf | B69: Encanto Piatã – F3 | C69: 02/03/2026 | D69: Book de Lançamento | E69: Aprovacao | F69: 379 | G69: 266898 | H69: 0.063 | I69: 425 | J69: 36597 | K69: 0.346 | L69: 18 | M69: 96561 | O69: 279141 | P69: 245636 | Q69: 0.329 | R69: 0.306 | S69: 0.526 | T69: 0.451 | U69: 11316 | V69: 0.107 | W69: 4291 | X69: 0 | Y69: =(O69-P69)/O69 -> 0.12002895 | Z69: =P69/M69 -> 2.5438428
A70: 2026.03.02 - Encanto Piatã F3 - Lançamento REV01.pdf | B70: Encanto Piatã – F3 | C70: 02/03/2026 | D70: Book de Lançamento | E70: Real | F70: 379 | G70: 266898 | H70: 0.064 | I70: 425 | J70: 36597 | K70: 0.353 | L70: 18 | M70: 96561 | O70: 273488 | P70: 240662 | Q70: 0.337 | R70: 0.22 | S70: 0.521 | T70: 0.446 | U70: 8234 | V70: 0.079 | W70: 4291 | X70: 0 | Y70: =(O70-P70)/O70 -> 0.1200272 | Z70: =P70/M70 -> 2.4923313
A71: 2025.04.01 - Essence Butantã - Reversão - R01.pdf | B71: Essence Butantã (Eiras Garcia) | C71: 02/04/2025 | D71: Book de Reversão Sem Reneg | E71: Aprovacao | F71: 409 | G71: 297115 | H71: 0.084 | I71: 4380 | J71: 43662 | K71: 0.422 | L71: 22 | M71: 106753 | O71: 253073 | P71: 236834 | Q71: 0.2 | R71: 0.2 | S71: 0.399 | T71: 0.352 | U71: 13823 | V71: 0.124 | W71: 4224 | X71: 0 | Y71: =(O71-P71)/O71 -> 0.064167256 | Z71: =P71/M71 -> 2.2185231
A72: 28.11.2025 - Essence Caucaia - Investimento - Respostas.pdf | B72: Essence Caucaia I, II e III (Terreno 710) | C72: 28/11/2025 | D72: Book de Investimento | E72: Aprovacao | F72: 1500 | G72: 207147 | H72: 0.085 | I72: 420 | J72: 137990 | K72: 0.462 | L72: 14 | M72: 91993 | O72: 199237 | P72: 181500 | Q72: 0.213 | R72: 0.2 | S72: 0.385 | T72: 0.319 | U72: 17242 | V72: 0.052 | W72: 2733 | X72: 0.756 | Y72: =(O72-P72)/O72 -> 0.089024629 | Z72: =P72/M72 -> 1.9729762
A73: 25.06.2025 - Essence Maracanaú I - Investimento_respostas comitê_R02.pdf | B73: Essence Maracanaú I (Terreno 626) | C73: 30/06/2025 | D73: Book de Investimento | E73: Aprovacao | F73: 432 | G73: 221581 | H73: 0.09 | I73: 431 | J73: 43803 | K73: 0.469 | L73: 11 | M73: 101395 | O73: 216050 | P73: 194800 | Q73: 0.202 | R73: 0.2 | S73: 0.372 | T73: 0.306 | U73: 9597 | V73: 0.094 | W73: 2604 | X73: 0.541 | Y73: =(O73-P73)/O73 -> 0.098356862 | Z73: =P73/M73 -> 1.9211993
A74: 25.06.2025 - Essence Maracanaú II - Investimento_respostas comitê_R02.pdf | B74: Essence Maracanaú II (Terreno 626) | C74: 30/06/2025 | D74: Book de Investimento | E74: Aprovacao | F74: 432 | G74: 221581 | H74: 0.09 | I74: 431 | J74: 43803 | K74: 0.469 | L74: 11 | M74: 101395 | O74: 216050 | P74: 194800 | Q74: 0.202 | R74: 0.2 | S74: 0.372 | T74: 0.306 | U74: 9597 | V74: 0.094 | W74: 2604 | X74: 0.541 | Y74: =(O74-P74)/O74 -> 0.098356862 | Z74: =P74/M74 -> 1.9211993
A75: 2025.08.25 - Estação Bordignon - Escritura 3 - final.pdf | B75: Estação Bordignon | C75: 25/08/2025 | D75: Book de Escritura | E75: Aprovacao | F75: 360 | G75: 235261 | H75: 0.111 | I75: 893 | J75: 33069 | K75: 0.399 | L75: 12 | M75: 91857 | O75: 230353 | P75: 210193 | Q75: 0.232 | R75: 0.2 | S75: 0.417 | T75: 0.36 | U75: 13056 | V75: 0.157 | W75: 3540 | X75: 0.188 | Y75: =(O75-P75)/O75 -> 0.087517853 | Z75: =P75/M75 -> 2.2882633
... A168: 2025.04.25 - Ventura III - Lançamento_Respostas.pdf | B168: Parque Ventura III | C168: 25/04/2025 | D168: Book de Lançamento | E168: Real | F168: 946 | G168: 213717 | H168: 0.024 | I168: 384 | J168: 95023 | K168: 0.483 | L168: 19 | M168: 100447 | O168: 207813 | P168: 185421 | Q168: 0.21 | R168: 0.2 | S168: 0.422 | T168: 0.345 | U168: 19369 | V168: 0.092 | W168: 2742 | X168: 0.519 | Y168: =(O168-P168)/O168 -> 0.10775072 | Z168: =P168/M168 -> 1.8459586
A169: 2025.12.09 - Protendit - Essencial_v1 2.pdf | B169: Pedro de Castilho (PROTENDIT) | C169: 08/12/2025 | E169: Aprovacao | F169: 952 | G169: 230000 | H169: 0.099 | I169: 2086 | J169: 93190 | K169: 0.447 | L169: 25 | M169: 97888 | O169: 219216 | P169: 197616 | Q169: 0.201 | R169: 0.2 | S169: 0.36 | T169: 0.28 | U169: 15303 | V169: 0.067 | W169: 2573 | X169: 0.75 | Y169: =(O169-P169)/O169 -> 0.098532954 | Z169: =P169/M169 -> 2.018797
A170: 2025.12.01 - Pirajussara - Essencial de Investimento.pdf | B170: Pirajussara | C170: 02/12/2025 | E170: Aprovacao | F170: 1103 | G170: 299691 | H170: 0.17 | I170: 4474 | J170: 111238 | K170: 0.364 | L170: 22 | M170: 100851 | O170: 276768 | P170: 260917 | Q170: 0.2 | R170: 0.2 | S170: 0.378 | T170: 0.335 | U170: 13544 | V170: 0.038 | W170: 5311 | X170: 0.009 | Y170: =(O170-P170)/O170 -> 0.057271794 | Z170: =P170/M170 -> 2.5871533
A171: 2025.12.12 - Pituba Prime - Investimento REV03_Resposta.pdf | B171: Pituba Prime | C171: 12/12/2025 | D171: Book de Investimento | E171: Aprovacao | F171: 428 | G171: 297220 | H171: 0.105 | I171: 2902 | J171: 48140 | K171: 0.388 | L171: 20 | M171: 112476 | O171: 289733 | P171: 266959 | Q171: 0.224 | R171: 0.2 | S171: 0.419 | T171: 0.363 | U171: 10380 | V171: 0.081 | W171: 5876 | X171: 0 | Y171: =(O171-P171)/O171 -> 0.078603404 | Z171: =P171/M171 -> 2.3734752
A172: 26.05.2025 - Plenum Camaçari - Investimento REV02.pdf | B172: Plenum Camaçari | C172: 26/05/2025 | D172: Book de Investimento | E172: Aprovacao | F172: 714 | G172: 212269 | H172: 0.036 | I172: 413 | J172: 74873 | K172: 0.486 | L172: 17 | M172: 104864 | O172: 215611 | P172: 197671 | Q172: 0.201 | R172: 0.2 | S172: 0.392 | T172: 0.331 | U172: 19963 | V172: 0.12 | W172: 2889 | X172: 0.511 | Y172: =(O172-P172)/O172 -> 0.083205402 | Z172: =P172/M172 -> 1.8850225
A173: 2025.11.17 - Portal de Salvador - Reversão cReneg. 2.pdf | B173: Portal de Salvador | C173: 17/11/2025 | D173: Book de Reversão c/ Reneg. | E173: Aprovacao | F173: 1378 | G173: 239731 | H173: 0.086 | I173: 641 | J173: 134632 | K173: 0.402 | L173: 20 | M173: 97701 | O173: 242979 | P173: 223367 | Q173: 0.2 | R173: 0.2 | S173: 0.435 | T173: 0.38 | U173: 17996 | V173: 0.049 | W173: 3454 | X173: 0.144 | Y173: =(O173-P173)/O173 -> 0.080714794 | Z173: =P173/M173 -> 2.2862304
A174: 2026.02.20 - Porto Lima - Escritura rv2.1_Respostas.pdf | B174: Porto Lima & Porto Seleta | C174: 20/02/2026 | D174: Book de Escritura | E174: Aprovacao | F174: 907 | G174: 202491 | H174: 0.044 | I174: 371 | J174: 85372 | K174: 0.443 | L174: 12 | M174: 94126 | O174: 212375 | P174: 187804 | Q174: 0.253 | R174: 0.22 | S174: 0.433 | T174: 0.35 | U174: 19167 | V174: 0.096 | W174: 2581 | X174: 0.721 | Y174: =(O174-P174)/O174 -> 0.11569629 | Z174: =P174/M174 -> 1.9952404
A175: 16.03.26 - Porto Lima - Lançamento EE.1.pdf | B175: Porto Lima & Porto Seleta | C175: 16/03/2026 | D175: Book de Lançamento | E175: Aprovacao | F175: 907 | G175: 206720 | H175: 0.044 | I175: 371 | J175: 88708 | K175: 0.464 | L175: 12 | M175: 97804 | N175: -0.004 | O175: 210643 | P175: 185785 | Q175: 0.23 | R175: 0.22 | S175: 0.412 | T175: 0.324 | U175: 19649 | V175: 0.1 | W175: 2535 | X175: 0.721 | Y175: =(O175-P175)/O175 -> 0.11801009 | Z175: =P175/M175 -> 1.8995644
A176: 16.03.26 - Porto Lima - Lançamento EE.1.pdf | B176: Porto Lima & Porto Seleta | C176: 16/03/2026 | D176: Book de Lançamento | E176: Real | F176: 907 | G176: 206720 | H176: 0.045 | I176: 371 | J176: 88876 | K176: 0.476 | L176: 12 | M176: 97989 | N176: -0.004 | O176: 206061 | P176: 181743 | Q176: 0.205 | R176: 0.22 | S176: 0.39 | T176: 0.296 | U176: 16217 | V176: 0.084 | W176: 2535 | X176: 0.721 | Y176: =(O176-P176)/O176 -> 0.1180136 | Z176: =P176/M176 -> 1.8547286
A177: 2025.04.28 - Porto Lima - Reversao c Reneg final.pdf | B177: Porto Lima I – F1 | C177: 28/04/2025 | D177: Book de Reversão com Renegociação | E177: Aprovacao | F177: 276 | G177: 202743 | H177: 0.048 | I177: 374 | J177: 26472 | K177: 0.487 | L177: 11 | M177: 95913 | O177: 197025 | P177: 175906 | Q177: 0.191 | R177: 0.2 | S177: 0.358 | T177: 0.3 | U177: 11707 | V177: 0.204 | W177: 2550 | X177: 0.716 | Y177: =(O177-P177)/O177 -> 0.10718944 | Z177: =P177/M177 -> 1.8340162
A178: 2025.11.24 - Porto Valência F2 - Lançamento_Respostas (1) 1.pdf | B178: Porto Valência F2 | C178: 28/11/2025 - Respostas | D178: Book de Lançamento | E178: Aprovacao | F178: 140 | G178: 203600 | H178: 0.034 | I178: 100 | J178: 12632 | K178: 0.424 | L178: 8 | M178: 90225 | O178: 212877 | P178: 191657 | Q178: 0.213 | R178: 0.301 | S178: 0.46 | T178: 0.396 | U178: 5135 | V178: 0.182 | W178: 2907 | X178: 0.2 | Y178: =(O178-P178)/O178 -> 0.099681976 | Z178: =P178/M178 -> 2.1242117
A179: 2025.11.24 - Porto Valência F2 - Lançamento_Respostas (1) 1.pdf | B179: Porto Valência F2 | C179: 28/11/2025 - Respostas | D179: Book de Lançamento | E179: Real | F179: 140 | G179: 203600 | H179: 0.036 | I179: 100 | J179: 12632 | K179: 0.451 | L179: 8 | M179: 90225 | O179: 200183 | P179: 180863 | Q179: 0.184 | R179: 0.2 | S179: 0.396 | T179: 0.352 | U179: 5135 | V179: 0.182 | W179: 2907 | X179: 0.6 | Y179: =(O179-P179)/O179 -> 0.096511692 | Z179: =P179/M179 -> 2.0045774
A180: 28.11.2025 - Porto Valência F2 - Lançamento - Respostas.pdf | B180: Porto Valência F2 | C180: 28/11/2025 - Respostas | D180: Book de Lançamento | E180: Aprovacao | F180: 140 | G180: 203600 | H180: 0.034 | I180: 100 | J180: 12632 | K180: 0.424 | L180: 8 | M180: 90225 | O180: 212877 | P180: 191657 | Q180: 0.213 | R180: 0.301 | S180: 0.46 | T180: 0.396 | U180: 5135 | V180: 0.182 | W180: 2907 | X180: 0.2 | Y180: =(O180-P180)/O180 -> 0.099681976 | Z180: =P180/M180 -> 2.1242117
A181: 28.11.2025 - Porto Valência F2 - Lançamento - Respostas.pdf | B181: Porto Valência F2 | C181: 28/11/2025 - Respostas | D181: Book de Lançamento | E181: Real | F181: 140 | G181: 203600 | H181: 0.036 | I181: 100 | J181: 12632 | K181: 0.451 | L181: 8 | M181: 90225 | O181: 200183 | P181: 180863 | Q181: 0.184 | R181: 0.2 | S181: 0.419 | T181: 0.352 | U181: 5135 | V181: 0.182 | W181: 2907 | X181: 0.6 | Y181: =(O181-P181)/O181 -> 0.096511692 | Z181: =P181/M181 -> 2.0045774
A182: 11.08.25 - PRESIDENTE - Investimento REV01.pdf | B182: Presidente | C182: 11/08/2025 | D182: Book de Investimento | E182: Aprovacao | F182: 1856 | G182: 222159 | H182: 0.084 | I182: 990 | J182: 172548 | K182: 0.417 | L182: 19 | M182: 92968 | O182: 222685 | P182: 205334 | Q182: 0.231 | R182: 0.2 | S182: 0.451 | T182: 0.398 | U182: 14916 | V182: 0.031 | W182: 3636 | X182: 0.058 | Y182: =(O182-P182)/O182 -> 0.077917237 | Z182: =P182/M182 -> 2.2086524
A183: 2025.06.10 - Raízes I e II - Investimento -.pdf | B183: Raízes I e II (Savana) | C183: 09/06/2025 | D183: Book de Investimento | E183: Aprovacao | F183: 520 | G183: 225538 | H183: 0.105 | I183: 369 | J183: 53037 | K183: 0.462 | L183: 11 | M183: 101995 | O183: 220758 | P183: 199514 | Q183: 0.2 | R183: 0.2 | S183: 0.369 | T183: 0.297 | U183: 8949 | V183: 0.069 | W183: 3381 | X183: 0.408 | Y183: =(O183-P183)/O183 -> 0.096232073 | Z183: =P183/M183 -> 1.9561155
A184: 2025.01.27 - Reserva dos Colibris (Investimento).pdf | B184: Reserva dos Colibris | C184: 27/01/2025 | D184: Book de Investimento | E184: Aprovacao | F184: 464 | G184: 229763 | H184: 0.085 | I184: 937 | J184: 46844 | K184: 0.446 | L184: 19 | M184: 100957 | O184: 202427 | P184: 202427 | Q184: 0.203 | R184: 0.2 | S184: 0.379 | T184: 0.297 | U184: 10676 | V184: 0.096 | W184: 3175 | X184: 0.5 | Y184: =(O184-P184)/O184 -> 0 | Z184: =P184/M184 -> 2.0050814
A185: 2026.03.09 - Reserva dos Colibris - Escritura e Lançamento V6.RESP.pdf | B185: Reserva dos Colibris | C185: 09/03/2026 | D185: Book de Escritura e Lançamento | E185: Aprovacao | F185: 464 | G185: 247349 | H185: 0.085 | I185: 1146 | J185: 52250 | K185: 0.433 | L185: 19 | M185: 112608 | N185: 0.001 | O185: 259882 | P185: 231955 | Q185: 0.2 | R185: 0.22 | S185: 0.395 | T185: 0.31 | U185: 12100 | V185: 0.101 | W185: 4052 | X185: 0.117 | Y185: =(O185-P185)/O185 -> 0.10746031 | Z185: =P185/M185 -> 2.0598448
A186: 2026.03.09 - Reserva dos Colibris - Escritura e Lançamento V6.RESP.pdf | B186: Reserva dos Colibris | C186: 09/03/2026 | D186: Book de Escritura e Lançamento | E186: Real | F186: 464 | G186: 247349 | H186: 0.085 | I186: 1146 | J186: 56238 | K186: 0.466 | L186: 25 | M186: 121203 | N186: 0.001 | O186: 259882 | P186: 231955 | Q186: 0.168 | R186: 0.22 | S186: 0.359 | T186: 0.269 | U186: 8582 | V186: 0.07 | W186: 4052 | X186: 0.117 | Y186: =(O186-P186)/O186 -> 0.10746031 | Z186: =P186/M186 -> 1.9137728
A187: 2025.10.20 - Mario Gatti - Investimento REV02.pdf | B187: Reservatto Amoreiras (Mario Gatti) | C187: 20/10/2025 | D187: Book de Investimento | E187: Aprovacao | F187: 200 | G187: 308124 | H187: 0.107 | I187: 3398 | J187: 23680 | K187: 0.407 | L187: 16 | M187: 118400 | O187: 291095 | P187: 270714 | Q187: 0.214 | R187: 0.2 | S187: 0.393 | T187: 0.343 | U187: 7008 | V187: 0.115 | W187: 5766 | X187: 0 | Y187: =(O187-P187)/O187 -> 0.070014944 | Z187: =P187/M187 -> 2.2864358
A188: 2025.06.30 Aurora (Santa Etelvina) Essencial.pdf | B188: Santa Etelvina – Lote B | C188: 30/06/2025 | D188: Book de Investimento - Comitê Essencial | E188: Aprovacao | F188: 383 | G188: 253222 | H188: 0.081 | I188: 949 | J188: 40920 | K188: 0.44 | L188: 19 | M188: 106841 | O188: 242558 | P188: 221079 | Q188: 0.18 | R188: 0.2 | S188: 0.372 | T188: 0.303 | U188: 11294 | V188: 0.113 | W188: 3874 | X188: 0.131 | Y188: =(O188-P188)/O188 -> 0.088552016 | Z188: =P188/M188 -> 2.0692337
A189: 2025.06.30 Aurora (Santa Etelvina) Essencial.pdf | B189: Santa Etelvina – Lote B | C189: 30/06/2025 | D189: Book de Investimento - Comitê Essencial | E189: Aprovacao | F189: 383 | G189: 253222 | H189: 0.081 | I189: 949 | J189: 40920 | K189: 0.44 | L189: 19 | M189: 106841 | O189: 242558 | P189: 221079 | Q189: 0.18 | R189: 0.2 | S189: 0.372 | T189: 0.303 | U189: 11294 | V189: 0.113 | W189: 3874 | X189: 0.131 | Y189: =(O189-P189)/O189 -> 0.088552016 | Z189: =P189/M189 -> 2.0692337
A190: 2025.06.26 - SANTA FÉ QD 83 - Investimento REV01.pdf | B190: Santa Fé Qd 83 | C190: 26/06/2025 | D190: Book de Investimento | E190: Aprovacao | F190: 318 | G190: 191918 | H190: 0.074 | I190: 565 | J190: 27462 | K190: 0.428 | L190: 14 | M190: 86360 | O190: 201845 | P190: 179301 | Q190: 0.219 | R190: 0.2 | S190: 0.414 | T190: 0.333 | U190: 8041 | V190: 0.115 | W190: 2606 | X190: 0.689 | Y190: =(O190-P190)/O190 -> 0.11168966 | Z190: =P190/M190 -> 2.0762043
A191: 2025.11.14 - Santorini Prime - Investimento - Respostas.pdf | B191: Santorini Prime | C191: 14/11/2025 | D191: Book de Investimento | E191: Aprovacao | F191: 925 | G191: 348351 | H191: 0.077 | I191: 1846 | J191: 105691 | K191: 0.323 | L191: 19 | M191: 114261 | O191: 353573 | P191: 333894 | Q191: 0.234 | R191: 0.2 | S191: 0.464 | T191: 0.428 | U191: 45316 | V191: 0.133 | W191: 7999 | X191: 0 | Y191: =(O191-P191)/O191 -> 0.05565753 | Z191: =P191/M191 -> 2.9222044
A192: 2025.11.14 - Santorini Prime - Investimento - Respostas.pdf | B192: Santorini Prime | C192: 14/11/2025 | D192: Book de Investimento | E192: Aprovacao | F192: 925 | G192: 348351 | H192: 0.077 | I192: 1846 | J192: 105691 | K192: 0.323 | L192: 19 | M192: 114261 | O192: 353573 | P192: 333894 | Q192: 0.234 | R192: 0.2 | S192: 0.464 | T192: 0.428 | U192: 45316 | V192: 0.133 | W192: 7999 | X192: 0 | Y192: =(O192-P192)/O192 -> 0.05565753 | Z192: =P192/M192 -> 2.9222044
A193: 2025.12.01 - Santos Silveiro - Investimento - E.E.pdf | B193: Santos Silveiro | C193: 01/12/2025 | D193: Book de Investimento | E193: Aprovacao | F193: 476 | G193: 227655 | H193: 0.085 | I193: 1552 | J193: 47634 | K193: 0.451 | L193: 19 | M193: 100071 | O193: 221666 | P193: 202921 | Q193: 0.206 | R193: 0.2 | S193: 0.373 | T193: 0.308 | U193: 11248 | V193: 0.102 | W193: 3302 | X193: 0.25 | Y193: =(O193-P193)/O193 -> 0.084564164 | Z193: =P193/M193 -> 2.0277703
A194: 24.11.2025 - São Joaquim - Investimento.pdf | B194: São Joaquim | C194: 24/11/2025 | D194: Book de Investimento | E194: Aprovacao | F194: 333 | G194: 210465 | H194: 0.043 | I194: 304 | J194: 29496 | K194: 0.425 | L194: 14 | M194: 88577 | O194: 208220 | P194: 190122 | Q194: 0.253 | R194: 0.2 | S194: 0.457 | T194: 0.4 | U194: 11647 | V194: 0.158 | W194: 2803 | X194: 0.551 | Y194: =(O194-P194)/O194 -> 0.086917683 | Z194: =P194/M194 -> 2.1464037
A195: 2025.11.14 - São Martinho - Investimento - Respostas.pdf | B195: São Martinho | C195: 14/11/2025 | E195: Real | F195: 350 | G195: 295961 | H195: 0.102 | I195: 1466 | J195: 42433 | K195: 0.42 | L195: 19 | M195: 121236 | O195: 288964 | P195: 268477 | Q195: 0.209 | R195: 0.2 | S195: 0.382 | T195: 0.334 | U195: 10947 | V195: 0.101 | W195: 5271 | X195: 0 | Y195: =(O195-P195)/O195 -> 0.070898105 | Z195: =P195/M195 -> 2.214499
A196: 2025.04.25 - Sena Parc Prime - Investimento_Respostas.pdf | B196: Sena Parc Prime (Terreno 587) | C196: 25/04/2025 | D196: Book de Investimento | E196: Aprovacao | F196: 214 | G196: 260139 | H196: 0.117 | I196: 2184 | J196: 22595 | K196: 0.406 | L196: 15 | M196: 105585 | O196: 259777 | P196: 238971 | Q196: 0.2 | R196: 0.2 | S196: 0.388 | T196: 0.329 | U196: 7269 | V196: 0.125 | W196: 4207 | X196: 0 | Y196: =(O196-P196)/O196 -> 0.080091771 | Z196: =P196/M196 -> 2.2633044
A197: 2025.10.27 - Sena Parc Prime - Investimento REV01.pdf | B197: Sena Parc Prime (Terreno 587) | C197: 27/10/2025 | D197: Book de Investimento | E197: Aprovacao | F197: 214 | G197: 267028 | H197: 0.117 | I197: 2194 | J197: 22610 | K197: 0.405 | L197: 15 | M197: 105655 | O197: 260967 | P197: 240270 | Q197: 0.2 | R197: 0.2 | S197: 0.388 | T197: 0.33 | U197: 7186 | V197: 0.124 | W197: 4256 | X197: 0 | Y197: =(O197-P197)/O197 -> 0.079308878 | Z197: =P197/M197 -> 2.2740997
A198: 2025.06.23 - 7 de Setembro - Essencial 1 ok.pdf | B198: Sete de Setembro | C198: 23/06/2025 | D198: Comitê Essencial | E198: Aprovacao | F198: 944 | G198: 248814 | H198: 0.056 | I198: 2101 | J198: 98225 | K198: 0.428 | L198: 21 | M198: 104051 | O198: 242978 | P198: 215722 | Q198: 0.201 | R198: 0.2 | S198: 0.41 | T198: 0.326 | U198: 17136 | V198: 0.067 | W198: 3551 | X198: 0.193 | Y198: =(O198-P198)/O198 -> 0.11217476 | Z198: =P198/M198 -> 2.0732333
A199: 2025.06.23 - Silva Vale - Investimento - Respostas.pdf | B199: Silva Vale – RZN3 | C199: 23/06/2025 | D199: Book de Investimento - Respostas | E199: Aprovacao | F199: 1946 | G199: 240000 | H199: 0.076 | I199: 1168 | J199: 192986 | K199: 0.432 | L199: 18 | M199: 99171 | O199: 229446 | P199: 204748 | Q199: 0.204 | R199: 0.2 | S199: 0.405 | T199: 0.325 | U199: 18966 | V199: 0.036 | W199: 3698 | X199: 0.25 | Y199: =(O199-P199)/O199 -> 0.10764189 | Z199: =P199/M199 -> 2.0645955
A200: 2025.06.30 - Sol de Camarás 2 F2 - Lançamento 1 - LM.pdf | B200: Sol de Camarás – Condomínio 2 – Fase 2 | C200: 30/06/25 | D200: Book de Lançamento | E200: Aprovacao | F200: 238 | G200: 190000 | H200: 0.056 | I200: 129 | J200: 19038 | K200: 0.418 | L200: 10 | M200: 79993 | O200: 191345 | P200: 167942 | Q200: 0.235 | R200: 0.286 | S200: 0.467 | T200: 0.387 | U200: 16324 | V200: 0.358 | W200: 2045 | X200: 1 | Y200: =(O200-P200)/O200 -> 0.12230787 | Z200: =P200/M200 -> 2.0994587
A201: 2025.06.30 - Sol de Camarás 2 F2 - Lançamento 1 - LM.pdf | B201: Sol de Camarás – Condomínio 2 – Fase 2 | C201: 30/06/25 | D201: Book de Lançamento | E201: Aprovacao | F201: 238 | G201: 190000 | H201: 0.054 | I201: 129 | J201: 19050 | K201: 0.404 | L201: 10 | M201: 80043 | O201: 185557 | P201: 185557 | Q201: 0.277 | R201: 0.286 | S201: 0.484 | T201: 0.446 | U201: 15414 | V201: 0.327 | W201: 2150 | X201: 1 | Y201: =(O201-P201)/O201 -> 0 | Z201: =P201/M201 -> 2.3182165
A202: 2025.02.17 - Book Sol do Mediterrâneo - Respostas 6.pdf | B202: Sol do Mediterrâneo - F2 | C202: 24/02/2025 | D202: Book de Lançamento | E202: Aprovacao | F202: 208 | G202: 184176 | H202: 0.068 | I202: 108 | J202: 18297 | K202: 0.444 | L202: 10 | M202: 87968 | O202: 204470 | P202: 182253 | Q202: 0.275 | R202: 0.2 | S202: 0.425 | T202: 0.351 | U202: 3351 | V202: 0.078 | W202: 2019 | X202: 0.75 | Y202: =(O202-P202)/O202 -> 0.10865653 | Z202: =P202/M202 -> 2.0718102
A203: 2025.02.17 - Book Sol do Mediterrâneo - Respostas 6.pdf | B203: Sol do Mediterrâneo - F2 | C203: 24/02/2025 | D203: Book de Lançamento | E203: Aprovacao | F203: 208 | G203: 184176 | H203: 0.069 | I203: 105 | J203: 18297 | K203: 0.444 | L203: 10 | M203: 87968 | O203: 198005 | P203: 175787 | Q203: 0.239 | R203: 0.2 | S203: 0.415 | T203: 0.341 | U203: 7492 | V203: 0.181 | W203: 2019 | X203: 0.75 | Y203: =(O203-P203)/O203 -> 0.11220929 | Z203: =P203/M203 -> 1.9983062
A204: 2025.04.28 - Solar do Bosque - Escritura_Final.pdf | B204: Solar do Bosque | C204: 28/04/2025 | D204: Book de Escritura | E204: Aprovacao | F204: 690 | G204: 218942 | H204: 0.08 | I204: 581 | J204: 65010 | K204: 0.469 | L204: 15 | M204: 94218 | O204: 200701 | P204: 179501 | Q204: 0.224 | R204: 0.2 | S204: 0.389 | T204: 0.311 | U204: 9468 | V204: 0.066 | W204: 2494 | X204: 0.687 | Y204: =(O204-P204)/O204 -> 0.10562977 | Z204: =P204/M204 -> 1.9051667
A205: 2025.06.30 - Solar do Bosque - Lançamento_respostas comite presencial.pdf | B205: Solar do Bosque | C205: 30/06/2025 | D205: Book de Lançamento | E205: Real | F205: 690 | G205: 201649 | H205: 0.08 | I205: 552 | J205: 65694 | K205: 0.499 | L205: 18 | M205: 95208 | O205: 190646 | P205: 171068 | Q205: 0.2 | R205: 0.2 | S205: 0.355 | T205: 0.273 | U205: 10669 | V205: 0.081 | W205: 2494 | X205: 0.929 | Y205: =(O205-P205)/O205 -> 0.10269295 | Z205: =P205/M205 -> 1.7967818
A206: 2025.11.17 - Solar dos Ventos Prime - Escritura e Lançamento EE REV03.pdf | B206: Solar dos Ventos Prime | C206: 17/11/2025 | D206: Book de Escritura e Lançamento | E206: Aprovacao | F206: 465 | G206: 284435 | H206: 0.108 | I206: 1797 | J206: 46074 | K206: 0.396 | L206: 19 | M206: 99083 | O206: 249897 | P206: 223879 | Q206: 0.214 | R206: 0.2 | S206: 0.401 | T206: 0.323 | U206: 10921 | V206: 0.095 | W206: 3727 | X206: 0.229 | Y206: =(O206-P206)/O206 -> 0.1041149 | Z206: =P206/M206 -> 2.2595097
A207: 2025.11.17 - Solar dos Ventos Prime - Escritura e Lançamento EE REV03.pdf | B207: Solar dos Ventos Prime | C207: 17/11/2025 | D207: Book de Escritura e Lançamento | E207: Real | F207: 465 | G207: 284435 | H207: 0.108 | I207: 1758 | J207: 46074 | K207: 0.405 | L207: 19 | M207: 99083 | O207: 244464 | P207: 219012 | Q207: 0.216 | R207: 0.2 | S207: 0.404 | T207: 0.326 | U207: 9964 | V207: 0.088 | W207: 3727 | X207: 0.229 | Y207: =(O207-P207)/O207 -> 0.10411349 | Z207: =P207/M207 -> 2.2103893
... A216: 2025.07.28 - Torres de Pirajá - Investimento.pdf | B216: Torres de Pirajá | C216: 28/07/2025 | D216: Book de Investimento | E216: Aprovacao | F216: 858 | G216: 239815 | H216: 0.072 | I216: 1226 | J216: 83527 | K216: 0.401 | L216: 20 | M216: 97350 | O216: 243026 | P216: 223666 | Q216: 0.208 | R216: 0.2 | S216: 0.434 | T216: 0.378 | U216: 25315 | V216: 0.114 | W216: 4166 | X216: 0 | Y216: =(O216-P216)/O216 -> 0.079662258 | Z216: =P216/M216 -> 2.2975449
A217: 2026.03.09 - Torres Marina - ESC + LÇTO - R04.pdf | B217: Torres Marina | C217: 09/03/2026 | D217: Book de Escritura + Lançamento | E217: Aprovacao | F217: 530 | G217: 223728 | H217: 0.04 | I217: 654 | J217: 55446 | K217: 0.476 | L217: 20 | M217: 104616 | N217: -0.004 | O217: 219741 | P217: 198645 | Q217: 0.188 | R217: 0.22 | S217: 0.381 | T217: 0.304 | U217: 18137 | V217: 0.156 | W217: 2506 | X217: 0.762 | Y217: =(O217-P217)/O217 -> 0.096003932 | Z217: =P217/M217 -> 1.8988013
A218: 2026.03.09 - Torres Marina - ESC + LÇTO - R04.pdf | B218: Torres Marina | C218: 09/03/2026 | D218: Book de Escritura + Lançamento | E218: Real | F218: 530 | G218: 223728 | H218: 0.038 | I218: 654 | J218: 56211 | K218: 0.454 | L218: 20 | M218: 106058 | N218: -0.003 | O218: 233435 | P218: 211026 | Q218: 0.22 | R218: 0.22 | S218: 0.411 | T218: 0.339 | U218: 17313 | V218: 0.14 | W218: 2506 | X218: 0.652 | Y218: =(O218-P218)/O218 -> 0.095996744 | Z218: =P218/M218 -> 1.9897226
A219: 2025.08.08 - Tucumã - Escrit + Lanç - Book comite - resposta.pdf | B219: Tucumã | C219: 08/08/2025 | D219: Book de Escritura e Lançamento | E219: Real | F219: 530 | G219: 241000 | H219: 0.066 | I219: 1533 | J219: 55992 | K219: 0.455 | L219: 23 | M219: 105646 | O219: 231994 | P219: 215015 | Q219: 0.201 | R219: 0.2 | S219: 0.371 | T219: 0.314 | U219: 10106 | V219: 0.083 | W219: 3409 | X219: 0.25 | Y219: =(O219-P219)/O219 -> 0.073187238 | Z219: =P219/M219 -> 2.0352403
A220: 02.06.2025 - Una Sonata - Investimento REV02_Respostas.pdf | B220: Una Sonata (Terreno 104) | C220: 02/06/2025 | D220: Book de Investimento | E220: Aprovacao | F220: 345 | G220: 213945 | H220: 0.088 | I220: 623 | J220: 32167 | K220: 0.434 | L220: 12 | M220: 93239 | O220: 214703 | P220: 190950 | Q220: 0.215 | R220: 0.2 | S220: 0.405 | T220: 0.325 | U220: 12387 | V220: 0.157 | W220: 3368 | X220: 0.359 | Y220: =(O220-P220)/O220 -> 0.1106319 | Z220: =P220/M220 -> 2.0479628
A221: 2025.09.01 Vale das Tulipas - Escritura e Lançamento REV02_Respostas.pdf | B221: Vale das Tulipas | C221: 01/09/2025 | D221: Book de Escritura e Lançamento | E221: Real | F221: 819 | G221: 233594 | H221: 0.08 | I221: 1082 | J221: 78305 | K221: 0.406 | L221: 23 | M221: 95610 | O221: 235663 | P221: 215834 | Q221: 0.24 | R221: 0.2 | S221: 0.421 | T221: 0.36 | U221: 15432 | V221: 0.081 | W221: 3248 | X221: 0.387 | Y221: =(O221-P221)/O221 -> 0.084141337 | Z221: =P221/M221 -> 2.2574417
A222: 2025.09.01 Vale das Tulipas - Escritura e Lançamento REV02_Respostas.pdf | B222: Vale das Tulipas | C222: 01/09/2025 | D222: Book de Escritura e Lançamento | E222: Aprovacao | F222: 819 | G222: 233594 | H222: 0.08 | I222: 1716 | J222: 78305 | K222: 0.411 | L222: 23 | M222: 95610 | O222: 232817 | P222: 212989 | Q222: 0.236 | R222: 0.2 | S222: 0.421 | T222: 0.359 | U222: 15432 | V222: 0.081 | W222: 3248 | X222: 0.387 | Y222: =(O222-P222)/O222 -> 0.085165602 | Z222: =P222/M222 -> 2.2276854
A223: 2025.02.28 - Vale dos Lírios F2 - Lançamento - Resp 1.pdf | B223: Vale dos Lírios - F2 | C223: 24/02/2025 | D223: Book de Lançamento | E223: Aprovacao | F223: 316 | G223: 224993 | H223: 0.08 | I223: 467 | J223: 29690 | K223: 0.394 | L223: 16 | M223: 93957 | O223: 238501 | P223: 211939 | Q223: 0.237 | R223: 0.2 | S223: 0.44 | T223: 0.362 | U223: 9159 | V223: 0.122 | W223: 3357 | X223: 0.18 | Y223: =(O223-P223)/O223 -> 0.1113706 | Z223: =P223/M223 -> 2.2557021
A224: 2025.02.28 - Vale dos Lírios F2 - Lançamento - Resp 1.pdf | B224: Vale dos Lírios - F2 | C224: 24/02/2025 | D224: Book de Lançamento | E224: Real | F224: 316 | G224: 224993 | H224: 0.08 | I224: 436 | J224: 29690 | K224: 0.422 | L224: 14 | M224: 93957 | O224: 222567 | P224: 197433 | Q224: 0.242 | R224: 0.2 | S224: 0.423 | T224: 0.343 | U224: 8709 | V224: 0.123 | W224: 3357 | X224: 0.399 | Y224: =(O224-P224)/O224 -> 0.11292779 | Z224: =P224/M224 -> 2.1013123
A225: 2025.08.25 - Veneza Prime - Escritura e Lançamento REV02 Resposta.pdf | B225: Veneza Prime | C225: 25/08/2025 | D225: Book de Escritura e Lançamento | E225: Aprovacao | F225: 1675 | G225: 257696 | H225: 0.071 | I225: 1067 | J225: 168632 | K225: 0.391 | L225: 21 | M225: 100676 | O225: 257307 | P225: 233422 | Q225: 0.217 | R225: 0.2 | S225: 0.456 | T225: 0.393 | U225: 26555 | V225: 0.056 | W225: 4495 | X225: 0 | Y225: =(O225-P225)/O225 -> 0.092826857 | Z225: =P225/M225 -> 2.3185466
A226: 2025.08.25 - Veneza Prime - Escritura e Lançamento REV02 Resposta.pdf | B226: Veneza Prime | C226: 25/08/2025 | D226: Book de Escritura e Lançamento | E226: Real | F226: 1675 | G226: 257696 | H226: 0.071 | I226: 1067 | J226: 168632 | K226: 0.39 | L226: 20 | M226: 100676 | O226: 258093 | P226: 233620 | Q226: 0.218 | R226: 0.2 | S226: 0.457 | T226: 0.393 | U226: 25772 | V226: 0.054 | W226: 4495 | X226: 0 | Y226: =(O226-P226)/O226 -> 0.094822409 | Z226: =P226/M226 -> 2.3205133
A227: 26.05.2025 - Videira - Investimento REV00_Respostas.pdf | B227: Videira | C227: 26/05/2025 | D227: Book de Investimento | E227: Aprovacao | F227: 294 | G227: 209765 | H227: 0.056 | I227: 202 | J227: 27108 | K227: 0.431 | L227: 12 | M227: 92205 | O227: 213984 | P227: 185778 | Q227: 0.214 | R227: 0.2 | S227: 0.422 | T227: 0.327 | U227: 12142 | V227: 0.178 | W227: 2424 | X227: 0.675 | Y227: =(O227-P227)/O227 -> 0.13181359 | Z227: =P227/M227 -> 2.0148365
A228: 2025.12.12 - Vila Butanta - Rev +Escr + Lçto - Respostas.pdf | B228: Vila Butantã (Joaquim Guimarães) | C228: 12/12/2025 | D228: Book de Escritura + Lançamento | E228: Aprovacao | F228: 796 | G228: 268088 | H228: 0.079 | I228: 3621 | J228: 85911 | K228: 0.45 | L228: 27 | M228: 107929 | O228: 239881 | P228: 219296 | Q228: 0.2 | R228: 0.2 | S228: 0.371 | T228: 0.303 | U228: 11753 | V228: 0.062 | W228: 3700 | X228: 0.203 | Y228: =(O228-P228)/O228 -> 0.085813382 | Z228: =P228/M228 -> 2.0318543
A229: 2025.12.12 - Vila Butanta - Rev +Escr + Lçto - Respostas.pdf | B229: Vila Butantã (Joaquim Guimarães) | C229: 12/12/2025 | D229: Book de Escritura + Lançamento | E229: Real | F229: 796 | G229: 268088 | H229: 0.079 | I229: 3597 | J229: 85911 | K229: 0.453 | L229: 27 | M229: 107929 | O229: 238310 | P229: 217414 | Q229: 0.197 | R229: 0.2 | S229: 0.371 | T229: 0.302 | U229: 14207 | V229: 0.075 | W229: 3700 | X229: 0.203 | Y229: =(O229-P229)/O229 -> 0.087684109 | Z229: =P229/M229 -> 2.0144169
A230: 2025.02.17 - Vila Laura Prime - Escritura e Lançamento 4.pdf | B230: Vila Laura Prime | C230: 17/02/2025 | D230: Book de Escritura e Lançamento | E230: Aprovacao | F230: 538 | G230: 264796 | H230: 0.11 | I230: 1941 | J230: 50446 | K230: 0.369 | L230: 20 | M230: 93766 | O230: 254371 | P230: 236077 | Q230: 0.213 | R230: 0.2 | S230: 0.413 | T230: 0.362 | U230: 12773 | V230: 0.095 | W230: 4290 | X230: 0 | Y230: =(O230-P230)/O230 -> 0.071918576 | Z230: =P230/M230 -> 2.517725
... A249: 2025.11.17 - Forte São Marcelo - Lançamento - Aprovação V3.pdf | B249: Viver Salvador – Forte São Marcelo | C249: 17/11/25 | D249: Book de Lançamento | E249: Real | F249: 476 | G249: 204705 | H249: 0.022 | I249: 359 | J249: 47382 | K249: 0.493 | L249: 15 | M249: 99541 | O249: 201765 | P249: 181256 | Q249: -0.058 | R249: 0.2 | S249: 0.388 | T249: 0.314 | U249: 17295 | V249: 0.179 | W249: 2546 | X249: 0.666 | Y249: =(O249-P249)/O249 -> 0.10164796 | Z249: =P249/M249 -> 1.820918

Sheet dados_filtrado
A1: nome_arquivo | B1: nome_projeto | C1: data_comite | D1: tipo_comite | E1: cenario | F1: unidades | G1: avaliacao_unit | H1: fracao_terreno_pct | I1: valor_rs_m2 | J1: custo_construcao_rs | K1: custo_construcao_pct_vgv | L1: prazo_obra_meses | M1: custo_total_unit | N1: custo_adc_selling | O1: preco_nominal_unit | P1: preco_raso_unit | Q1: li_pct | R1: li_regua_pct | S1: margem_bruta_economica_pct | T1: margem_rasa_economica_pct | U1: exposicao_rs_mil | V1: exposicao_pct_vgv | W1: renda | X1: pct_ret1 | Y1: pct_tcd | Z1: raso_sobre_custo | AA1: MÊS | AB1: FAIXA | AC1: FLAG | AD1: TRI | AE1: Range LI | AF1: Range MR | AG1: Range MB
A2: 2025.01.13 - Jaguaribe Prime - Investimento 1.1.pdf | B2: Jaguaribe Prime | C2: 45670 | D2: Book de Investimento | E2: Aprovacao | F2: 1143 | G2: 292021 | H2: 0.138 | I2: 2293 | J2: 107842 | K2: 0.347 | L2: 19 | M2: 94350 | O2: 271870 | P2: 244467 | Q2: 0.206 | R2: 0.2 | S2: 0.428 | T2: 0.356 | U2: 24694 | V2: 0.072 | W2: 4682 | X2: 0 | Y2: =(O2-P2)/O2 -> 0.1007945 | Z2: =P2/M2 -> 2.5910652 | AA2: =DATE(YEAR(C2),MONTH(C2),1) -> 45658 | AB2: =IF(X2>=0.5,"Faixa 1",IF(X2=0,"Faixa 3","Faixa 2")) -> Faixa 3 | AC2: 1 | AD2: =YEAR(AA2)&"-"&IF(MONTH(AA2)<4,1,IF(MONTH(AA2)<7,2,IF(MONTH(AA2)<10,3,4)))&"T" -> 2025-1T | AE2: =IF((Q2-R2)<0.005,"Até +0,5%",IF((Q2-R2)<0.01,"Ate +1%","Acima de +1%")) -> Ate +1% | AF2: =IF($T2<=0.32,"Ate 32%",IF($T2<=0.34,"Ate 34%","Acima de 34%")) -> Acima de 34% | AG2: =IF($S2<=0.39,"Ate 39%",IF($S2<=0.41,"Ate 41%","Acima de 41%")) -> Acima de 41%
A3: 2025.01.20 - Acqua Danubio -Lançamento.pdf | B3: Acqua Danúbio | C3: 45677 | D3: Book de Lançamento | E3: Aprovacao | F3: 388 | G3: 203835 | H3: 0.033 | I3: 398 | J3: 40555 | K3: 0.487 | L3: 18 | M3: 104524 | O3: 214464 | P3: 190902 | Q3: 0.203 | R3: 0.2 | S3: 0.401 | T3: 0.245 | U3: 16047 | V3: 0.12 | W3: 2521 | X3: 0.5 | Y3: =(O3-P3)/O3 -> 0.10986459 | Z3: =P3/M3 -> 1.8263939 | AA3: =DATE(YEAR(C3),MONTH(C3),1) -> 45658 | AB3: =IF(X3>=0.5,"Faixa 1",IF(X3=0,"Faixa 3","Faixa 2")) -> Faixa 1 | AC3: 1 | AD3: =YEAR(AA3)&"-"&IF(MONTH(AA3)<4,1,IF(MONTH(AA3)<7,2,IF(MONTH(AA3)<10,3,4)))&"T" -> 2025-1T | AE3: =IF((Q3-R3)<0.005,"Até +0,5%",IF((Q3-R3)<0.01,"Ate +1%","Acima de +1%")) -> Até +0,5% | AF3: =IF($T3<=0.32,"Ate 32%",IF($T3<=0.34,"Ate 34%","Acima de 34%")) -> Ate 32% | AG3: =IF($S3<=0.39,"Ate 39%",IF($S3<=0.41,"Ate 41%","Acima de 41%")) -> Ate 41%
A4: 2025.01.27 - Reserva dos Colibris (Investimento).pdf | B4: Reserva dos Colibris | C4: 45684 | D4: Book de Investimento | E4: Aprovacao | F4: 464 | G4: 229763 | H4: 0.085 | I4: 937 | J4: 46844 | K4: 0.446 | L4: 19 | M4: 100957 | O4: 202427 | P4: 202427 | Q4: 0.203 | R4: 0.2 | S4: 0.379 | T4: 0.297 | U4: 10676 | V4: 0.096 | W4: 3175 | X4: 0.5 | Y4: =(O4-P4)/O4 -> 0 | Z4: =P4/M4 -> 2.0050814 | AA4: =DATE(YEAR(C4),MONTH(C4),1) -> 45658 | AB4: =IF(X4>=0.5,"Faixa 1",IF(X4=0,"Faixa 3","Faixa 2")) -> Faixa 1 | AC4: 1 | AD4: =YEAR(AA4)&"-"&IF(MONTH(AA4)<4,1,IF(MONTH(AA4)<7,2,IF(MONTH(AA4)<10,3,4)))&"T" -> 2025-1T | AE4: =IF((Q4-R4)<0.005,"Até +0,5%",IF((Q4-R4)<0.01,"Ate +1%","Acima de +1%")) -> Até +0,5% | AF4: =IF($T4<=0.32,"Ate 32%",IF($T4<=0.34,"Ate 34%","Acima de 34%")) -> Ate 32% | AG4: =IF($S4<=0.39,"Ate 39%",IF($S4<=0.41,"Ate 41%","Acima de 41%")) -> Ate 39%
A5: 2025.02.14 - Altiplano Sunset - Investimento.pdf | B5: Altiplano Sunset | C5: 45698 | D5: Book de Investimento | E5: Aprovacao | F5: 712 | G5: 239775 | H5: 0.093 | I5: 1035 | J5: 69445 | K5: 0.435 | L5: 17 | M5: 97536 | O5: 224103 | P5: 201035 | Q5: 0.2 | R5: 0.2 | S5: 0.385 | T5: 0.306 | U5: 11267 | V5: 0.064 | W5: 3204 | X5: 0.381 | Y5: =(O5-P5)/O5 -> 0.10293481 | Z5: =P5/M5 -> 2.0611364 | AA5: =DATE(YEAR(C5),MONTH(C5),1) -> 45689 | AB5: =IF(X5>=0.5,"Faixa 1",IF(X5=0,"Faixa 3","Faixa 2")) -> Faixa 2 | AC5: 1 | AD5: =YEAR(AA5)&"-"&IF(MONTH(AA5)<4,1,IF(MONTH(AA5)<7,2,IF(MONTH(AA5)<10,3,4)))&"T" -> 2025-1T | AE5: =IF((Q5-R5)<0.005,"Até +0,5%",IF((Q5-R5)<0.01,"Ate +1%","Acima de +1%")) -> Até +0,5% | AF5: =IF($T5<=0.32,"Ate 32%",IF($T5<=0.34,"Ate 34%","Acima de 34%")) -> Ate 32% | AG5: =IF($S5<=0.39,"Ate 39%",IF($S5<=0.41,"Ate 41%","Acima de 41%")) -> Ate 39%
A6: 2025.02.10- Melodia Jaçanã - Comitê Escritura +Lançamento - Respostas.pdf | B6: Melodia Jaçanã | C6: 45698 | D6: Book de Escritura e Lançamento | E6: Aprovacao | F6: 768 | G6: 253188 | H6: 0.102 | I6: 3263 | J6: 74484 | K6: 0.401 | L6: 24 | M6: 96984 | O6: 217773 | P6: 217773 | Q6: 0.2 | R6: 0.2 | S6: 0.376 | T6: 0.298 | U6: 14761 | V6: 0.079 | W6: 3893 | X6: 0.15 | Y6: =(O6-P6)/O6 -> 0 | Z6: =P6/M6 -> 2.2454529 | AA6: =DATE(YEAR(C6),MONTH(C6),1) -> 45689 | AB6: =IF(X6>=0.5,"Faixa 1",IF(X6=0,"Faixa 3","Faixa 2")) -> Faixa 2 | AC6: 1 | AD6: =YEAR(AA6)&"-"&IF(MONTH(AA6)<4,1,IF(MONTH(AA6)<7,2,IF(MONTH(AA6)<10,3,4)))&"T" -> 2025-1T | AE6: =IF((Q6-R6)<0.005,"Até +0,5%",IF((Q6-R6)<0.01,"Ate +1%","Acima de +1%")) -> Até +0,5% | AF6: =IF($T6<=0.32,"Ate 32%",IF($T6<=0.34,"Ate 34%","Acima de 34%")) -> Ate 32% | AG6: =IF($S6<=0.39,"Ate 39%",IF($S6<=0.41,"Ate 41%","Acima de 41%")) -> Ate 39%
A7: 17.02.2025 - Estância Dourados I - Lançamento 1.pdf | B7: Estância Dourados I | C7: 45705 | D7: Book de Lançamento | E7: Aprovacao | F7: 376 | G7: 197323 | H7: 0.0767 | I7: 405 | J7: 34007 | K7: 0.435 | L7: 12 | M7: 89992 | O7: 208033 | P7: 179700 | Q7: 0.226 | R7: 0.2 | S7: 0.383 | T7: 0.325 | U7: 9595 | V7: 0.122 | W7: 2347 | X7: 0.75 | Y7: =(O7-P7)/O7 -> 0.13619474 | Z7: =P7/M7 -> 1.9968442 | AA7: =DATE(YEAR(C7),MONTH(C7),1) -> 45689 | AB7: =IF(X7>=0.5,"Faixa 1",IF(X7=0,"Faixa 3","Faixa 2")) -> Faixa 1 | AC7: 1 | AD7: =YEAR(AA7)&"-"&IF(MONTH(AA7)<4,1,IF(MONTH(AA7)<7,2,IF(MONTH(AA7)<10,3,4)))&"T" -> 2025-1T | AE7: =IF((Q7-R7)<0.005,"Até +0,5%",IF((Q7-R7)<0.01,"Ate +1%","Acima de +1%")) -> Acima de +1% | AF7: =IF($T7<=0.32,"Ate 32%",IF($T7<=0.34,"Ate 34%","Acima de 34%")) -> Ate 34% | AG7: =IF($S7<=0.39,"Ate 39%",IF($S7<=0.41,"Ate 41%","Acima de 41%")) -> Ate 39%
A8: 2025.02.17 - Vila Laura Prime - Escritura e Lançamento 4.pdf | B8: Vila Laura Prime | C8: 45705 | D8: Book de Escritura e Lançamento | E8: Aprovacao | F8: 538 | G8: 264796 | H8: 0.11 | I8: 1941 | J8: 50446 | K8: 0.369 | L8: 20 | M8: 93766 | O8: 254371 | P8: 236077 | Q8: 0.213 | R8: 0.2 | S8: 0.413 | T8: 0.362 | U8: 12773 | V8: 0.095 | W8: 4290 | X8: 0 | Y8: =(O8-P8)/O8 -> 0.071918576 | Z8: =P8/M8 -> 2.517725 | AA8: =DATE(YEAR(C8),MONTH(C8),1) -> 45689 | AB8: =IF(X8>=0.5,"Faixa 1",IF(X8=0,"Faixa 3","Faixa 2")) -> Faixa 3 | AC8: 1 | AD8: =YEAR(AA8)&"-"&IF(MONTH(AA8)<4,1,IF(MONTH(AA8)<7,2,IF(MONTH(AA8)<10,3,4)))&"T" -> 2025-1T | AE8: =IF((Q8-R8)<0.005,"Até +0,5%",IF((Q8-R8)<0.01,"Ate +1%","Acima de +1%")) -> Acima de +1% | AF8: =IF($T8<=0.32,"Ate 32%",IF($T8<=0.34,"Ate 34%","Acima de 34%")) -> Acima de 34% | AG8: =IF($S8<=0.39,"Ate 39%",IF($S8<=0.41,"Ate 41%","Acima de 41%")) -> Acima de 41%
A9: 2025.02.28 - Farol do Mucuripe - Comitê Lançamento - EE resp. (1) - LM.pdf | B9: Farol do Mucuripe | C9: 45712 | D9: Book de Lançamento | E9: Aprovacao | F9: 286 | G9: 244714 | H9: 0.09 | I9: 1237 | J9: 27873 | K9: 0.415 | L9: 17 | M9: 97457 | O9: 235028 | P9: 213469 | Q9: 0.2 | R9: 0.2 | S9: 0.404 | T9: 0.337 | U9: 9498 | V9: 0.142 | W9: 3513 | X9: 0.201 | Y9: =(O9-P9)/O9 -> 0.091729496 | Z9: =P9/M9 -> 2.1903917 | AA9: =DATE(YEAR(C9),MONTH(C9),1) -> 45689 | AB9: =IF(X9>=0.5,"Faixa 1",IF(X9=0,"Faixa 3","Faixa 2")) -> Faixa 2 | AC9: 1 | AD9: =YEAR(AA9)&"-"&IF(MONTH(AA9)<4,1,IF(MONTH(AA9)<7,2,IF(MONTH(AA9)<10,3,4)))&"T" -> 2025-1T | AE9: =IF((Q9-R9)<0.005,"Até +0,5%",IF((Q9-R9)<0.01,"Ate +1%","Acima de +1%")) -> Até +0,5% | AF9: =IF($T9<=0.32,"Ate 32%",IF($T9<=0.34,"Ate 34%","Acima de 34%")) -> Ate 34% | AG9: =IF($S9<=0.39,"Ate 39%",IF($S9<=0.41,"Ate 41%","Acima de 41%")) -> Ate 41%
A10: 2025.02.17 - Book Sol do Mediterrâneo - Respostas 6.pdf | B10: Sol do Mediterrâneo - F2 | C10: 45712 | D10: Book de Lançamento | E10: Aprovacao | F10: 208 | G10: 184176 | H10: 0.068 | I10: 108 | J10: 18297 | K10: 0.444 | L10: 10 | M10: 87968 | O10: 204470 | P10: 182253 | Q10: 0.275 | R10: 0.2 | S10: 0.425 | T10: 0.351 | U10: 3351 | V10: 0.078 | W10: 2019 | X10: 0.75 | Y10: =(O10-P10)/O10 -> 0.10865653 | Z10: =P10/M10 -> 2.0718102 | AA10: =DATE(YEAR(C10),MONTH(C10),1) -> 45689 | AB10: =IF(X10>=0.5,"Faixa 1",IF(X10=0,"Faixa 3","Faixa 2")) -> Faixa 1 | AC10: 1 | AD10: =YEAR(AA10)&"-"&IF(MONTH(AA10)<4,1,IF(MONTH(AA10)<7,2,IF(MONTH(AA10)<10,3,4)))&"T" -> 2025-1T | AE10: =IF((Q10-R10)<0.005,"Até +0,5%",IF((Q10-R10)<0.01,"Ate +1%","Acima de +1%")) -> Acima de +1% | AF10: =IF($T10<=0.32,"Ate 32%",IF($T10<=0.34,"Ate 34%","Acima de 34%")) -> Acima de 34% | AG10: =IF($S10<=0.39,"Ate 39%",IF($S10<=0.41,"Ate 41%","Acima de 41%")) -> Acima de 41%
A11: 2025.02.28 - Vale dos Lírios F2 - Lançamento - Resp 1.pdf | B11: Vale dos Lírios - F2 | C11: 45712 | D11: Book de Lançamento | E11: Aprovacao | F11: 316 | G11: 224993 | H11: 0.08 | I11: 467 | J11: 29690 | K11: 0.394 | L11: 16 | M11: 93957 | O11: 238501 | P11: 211939 | Q11: 0.237 | R11: 0.2 | S11: 0.44 | T11: 0.362 | U11: 9159 | V11: 0.122 | W11: 3357 | X11: 0.18 | Y11: =(O11-P11)/O11 -> 0.1113706 | Z11: =P11/M11 -> 2.2557021 | AA11: =DATE(YEAR(C11),MONTH(C11),1) -> 45689 | AB11: =IF(X11>=0.5,"Faixa 1",IF(X11=0,"Faixa 3","Faixa 2")) -> Faixa 2 | AC11: 1 | AD11: =YEAR(AA11)&"-"&IF(MONTH(AA11)<4,1,IF(MONTH(AA11)<7,2,IF(MONTH(AA11)<10,3,4)))&"T" -> 2025-1T | AE11: =IF((Q11-R11)<0.005,"Até +0,5%",IF((Q11-R11)<0.01,"Ate +1%","Acima de +1%")) -> Acima de +1% | AF11: =IF($T11<=0.32,"Ate 32%",IF($T11<=0.34,"Ate 34%","Acima de 34%")) -> Acima de 34% | AG11: =IF($S11<=0.39,"Ate 39%",IF($S11<=0.41,"Ate 41%","Acima de 41%")) -> Acima de 41%
A12: 2025.02.28 - Pq Ventura III - Escritura_Respostas_Final.pdf | B12: Parque Ventura III | C12: 45716 | D12: Book de Escritura | E12: Aprovacao | F12: 946 | G12: 213717 | H12: 0.023 | I12: 377 | J12: 92461 | K12: 0.46 | L12: 19 | M12: 97739 | O12: 212253 | P12: 187303 | Q12: 0.23 | R12: 0.2 | S12: 0.439 | T12: 0.356 | U12: 15373 | V12: 0.071 | W12: 2847 | X12: 0.48 | Y12: =(O12-P12)/O12 -> 0.1175484 | Z12: =P12/M12 -> 1.9163589 | AA12: =DATE(YEAR(C12),MONTH(C12),1) -> 45689 | AB12: =IF(X12>=0.5,"Faixa 1",IF(X12=0,"Faixa 3","Faixa 2")) -> Faixa 2 | AC12: 1 | AD12: =YEAR(AA12)&"-"&IF(MONTH(AA12)<4,1,IF(MONTH(AA12)<7,2,IF(MONTH(AA12)<10,3,4)))&"T" -> 2025-1T | AE12: =IF((Q12-R12)<0.005,"Até +0,5%",IF((Q12-R12)<0.01,"Ate +1%","Acima de +1%")) -> Acima de +1% | AF12: =IF($T12<=0.32,"Ate 32%",IF($T12<=0.34,"Ate 34%","Acima de 34%")) -> Acima de 34% | AG12: =IF($S12<=0.39,"Ate 39%",IF($S12<=0.41,"Ate 41%","Acima de 41%")) -> Acima de 41%
A13: 2025.03.17 - Frutas - Investimento.pdf | B13: FRUTAS | C13: 45733 | D13: Book de Investimento | E13: Aprovacao | F13: 320 | G13: 193641 | H13: 0.069 | I13: 532 | J13: 26722 | K13: 0.411 | L13: 13 | M13: 83505 | O13: 203268 | P13: 175186 | Q13: 0.253 | R13: 0.2 | S13: 0.453 | T13: 0.357 | U13: 8862 | V13: 0.124 | W13: 2171 | X13: 0.75 | Y13: =(O13-P13)/O13 -> 0.13815259 | Z13: =P13/M13 -> 2.0979103 | AA13: =DATE(YEAR(C13),MONTH(C13),1) -> 45717 | AB13: =IF(X13>=0.5,"Faixa 1",IF(X13=0,"Faixa 3","Faixa 2")) -> Faixa 1 | AC13: 1 | AD13: =YEAR(AA13)&"-"&IF(MONTH(AA13)<4,1,IF(MONTH(AA13)<7,2,IF(MONTH(AA13)<10,3,4)))&"T" -> 2025-1T | AE13: =IF((Q13-R13)<0.005,"Até +0,5%",IF((Q13-R13)<0.01,"Ate +1%","Acima de +1%")) -> Acima de +1% | AF13: =IF($T13<=0.32,"Ate 32%",IF($T13<=0.34,"Ate 34%","Acima de 34%")) -> Acima de 34% | AG13: =IF($S13<=0.39,"Ate 39%",IF($S13<=0.41,"Ate 41%","Acima de 41%")) -> Acima de 41%
... A115: 2025.11.14 - Santorini Prime - Investimento - Respostas.pdf | B115: Santorini Prime | C115: 45975 | D115: Book de Investimento | E115: Aprovacao | F115: 925 | G115: 348351 | H115: 0.077 | I115: 1846 | J115: 105691 | K115: 0.323 | L115: 19 | M115: 114261 | O115: 353573 | P115: 333894 | Q115: 0.234 | R115: 0.2 | S115: 0.464 | T115: 0.428 | U115: 45316 | V115: 0.133 | W115: 7999 | X115: 0 | Y115: =(O115-P115)/O115 -> 0.05565753 | Z115: =P115/M115 -> 2.9222044 | AA115: =DATE(YEAR(C115),MONTH(C115),1) -> 45962 | AB115: =IF(X115>=0.5,"Faixa 1",IF(X115=0,"Faixa 3","Faixa 2")) -> Faixa 3 | AC115: 1 | AD115: =YEAR(AA115)&"-"&IF(MONTH(AA115)<4,1,IF(MONTH(AA115)<7,2,IF(MONTH(AA115)<10,3,4)))&"T" -> 2025-4T | AE115: =IF((Q115-R115)<0.005,"Até +0,5%",IF((Q115-R115)<0.01,"Ate +1%","Acima de +1%")) -> Acima de +1% | AF115: =IF($T115<=0.32,"Ate 32%",IF($T115<=0.34,"Ate 34%","Acima de 34%")) -> Acima de 34% | AG115: =IF($S115<=0.39,"Ate 39%",IF($S115<=0.41,"Ate 41%","Acima de 41%")) -> Acima de 41%
A116: 2025.11.14 - São Martinho - Investimento - Respostas.pdf | B116: São Martinho | C116: 45975 | E116: Real | F116: 350 | G116: 295961 | H116: 0.102 | I116: 1466 | J116: 42433 | K116: 0.42 | L116: 19 | M116: 121236 | O116: 288964 | P116: 268477 | Q116: 0.209 | R116: 0.2 | S116: 0.382 | T116: 0.334 | U116: 10947 | V116: 0.101 | W116: 5271 | X116: 0 | Y116: =(O116-P116)/O116 -> 0.070898105 | Z116: =P116/M116 -> 2.214499 | AA116: =DATE(YEAR(C116),MONTH(C116),1) -> 45962 | AB116: =IF(X116>=0.5,"Faixa 1",IF(X116=0,"Faixa 3","Faixa 2")) -> Faixa 3 | AC116: 1 | AD116: =YEAR(AA116)&"-"&IF(MONTH(AA116)<4,1,IF(MONTH(AA116)<7,2,IF(MONTH(AA116)<10,3,4)))&"T" -> 2025-4T | AE116: =IF((Q116-R116)<0.005,"Até +0,5%",IF((Q116-R116)<0.01,"Ate +1%","Acima de +1%")) -> Ate +1% | AF116: =IF($T116<=0.32,"Ate 32%",IF($T116<=0.34,"Ate 34%","Acima de 34%")) -> Ate 34% | AG116: =IF($S116<=0.39,"Ate 39%",IF($S116<=0.41,"Ate 41%","Acima de 41%")) -> Ate 39%
A117: 17.11.2025 - Idealle Prime - Investimento REV02.pdf | B117: Idealle Prime (Terreno 289) | C117: 45978 | D117: Book de Investimento | E117: Aprovacao | F117: 753 | G117: 281992 | H117: 0.14 | I117: 2509 | J117: 74018 | K117: 0.371 | L117: 18 | M117: 98297 | O117: 264652 | P117: 239556 | Q117: 0.205 | R117: 0.2 | S117: 0.394 | T117: 0.324 | U117: 14685 | V117: 0.068 | W117: 4346 | X117: 0 | Y117: =(O117-P117)/O117 -> 0.094826414 | Z117: =P117/M117 -> 2.4370632 | AA117: =DATE(YEAR(C117),MONTH(C117),1) -> 45962 | AB117: =IF(X117>=0.5,"Faixa 1",IF(X117=0,"Faixa 3","Faixa 2")) -> Faixa 3 | AC117: 1 | AD117: =YEAR(AA117)&"-"&IF(MONTH(AA117)<4,1,IF(MONTH(AA117)<7,2,IF(MONTH(AA117)<10,3,4)))&"T" -> 2025-4T | AE117: =IF((Q117-R117)<0.005,"Até +0,5%",IF((Q117-R117)<0.01,"Ate +1%","Acima de +1%")) -> Até +0,5% | AF117: =IF($T117<=0.32,"Ate 32%",IF($T117<=0.34,"Ate 34%","Acima de 34%")) -> Ate 34% | AG117: =IF($S117<=0.39,"Ate 39%",IF($S117<=0.41,"Ate 41%","Acima de 41%")) -> Ate 41%
A118: 2025.11.17 - Leonel Martiniano - Essencial_v1.pdf | B118: Leonel Martiniano | C118: 45978 | D118: Book Essencial de Investimento | E118: Aprovacao | F118: 1794 | G118: 225000 | H118: 0.079 | I118: 3192 | J118: 183183 | K118: 0.461 | L118: 25 | M118: 102109 | O118: 221585 | P118: 199510 | Q118: 0.206 | R118: 0.2 | S118: 0.371 | T118: 0.291 | U118: 20086 | V118: 0.044 | W118: 2591 | X118: 0.75 | Y118: =(O118-P118)/O118 -> 0.099623169 | Z118: =P118/M118 -> 1.9538924 | AA118: =DATE(YEAR(C118),MONTH(C118),1) -> 45962 | AB118: =IF(X118>=0.5,"Faixa 1",IF(X118=0,"Faixa 3","Faixa 2")) -> Faixa 1 | AC118: 1 | AD118: =YEAR(AA118)&"-"&IF(MONTH(AA118)<4,1,IF(MONTH(AA118)<7,2,IF(MONTH(AA118)<10,3,4)))&"T" -> 2025-4T | AE118: =IF((Q118-R118)<0.005,"Até +0,5%",IF((Q118-R118)<0.01,"Ate +1%","Acima de +1%")) -> Ate +1% | AF118: =IF($T118<=0.32,"Ate 32%",IF($T118<=0.34,"Ate 34%","Acima de 34%")) -> Ate 32% | AG118: =IF($S118<=0.39,"Ate 39%",IF($S118<=0.41,"Ate 41%","Acima de 41%")) -> Ate 39%
A119: 2025.11.17 - Portal de Salvador - Reversão cReneg. 2.pdf | B119: Portal de Salvador | C119: 45978 | D119: Book de Reversão c/ Reneg. | E119: Aprovacao | F119: 1378 | G119: 239731 | H119: 0.086 | I119: 641 | J119: 134632 | K119: 0.402 | L119: 20 | M119: 97701 | O119: 242979 | P119: 223367 | Q119: 0.2 | R119: 0.2 | S119: 0.435 | T119: 0.38 | U119: 17996 | V119: 0.049 | W119: 3454 | X119: 0.144 | Y119: =(O119-P119)/O119 -> 0.080714794 | Z119: =P119/M119 -> 2.2862304 | AA119: =DATE(YEAR(C119),MONTH(C119),1) -> 45962 | AB119: =IF(X119>=0.5,"Faixa 1",IF(X119=0,"Faixa 3","Faixa 2")) -> Faixa 2 | AC119: 1 | AD119: =YEAR(AA119)&"-"&IF(MONTH(AA119)<4,1,IF(MONTH(AA119)<7,2,IF(MONTH(AA119)<10,3,4)))&"T" -> 2025-4T | AE119: =IF((Q119-R119)<0.005,"Até +0,5%",IF((Q119-R119)<0.01,"Ate +1%","Acima de +1%")) -> Até +0,5% | AF119: =IF($T119<=0.32,"Ate 32%",IF($T119<=0.34,"Ate 34%","Acima de 34%")) -> Acima de 34% | AG119: =IF($S119<=0.39,"Ate 39%",IF($S119<=0.41,"Ate 41%","Acima de 41%")) -> Acima de 41%
A120: 2025.11.17 - Solar dos Ventos Prime - Escritura e Lançamento EE REV03.pdf | B120: Solar dos Ventos Prime | C120: 45978 | D120: Book de Escritura e Lançamento | E120: Aprovacao | F120: 465 | G120: 284435 | H120: 0.108 | I120: 1797 | J120: 46074 | K120: 0.396 | L120: 19 | M120: 99083 | O120: 249897 | P120: 223879 | Q120: 0.214 | R120: 0.2 | S120: 0.401 | T120: 0.323 | U120: 10921 | V120: 0.095 | W120: 3727 | X120: 0.229 | Y120: =(O120-P120)/O120 -> 0.1041149 | Z120: =P120/M120 -> 2.2595097 | AA120: =DATE(YEAR(C120),MONTH(C120),1) -> 45962 | AB120: =IF(X120>=0.5,"Faixa 1",IF(X120=0,"Faixa 3","Faixa 2")) -> Faixa 2 | AC120: 1 | AD120: =YEAR(AA120)&"-"&IF(MONTH(AA120)<4,1,IF(MONTH(AA120)<7,2,IF(MONTH(AA120)<10,3,4)))&"T" -> 2025-4T | AE120: =IF((Q120-R120)<0.005,"Até +0,5%",IF((Q120-R120)<0.01,"Ate +1%","Acima de +1%")) -> Acima de +1% | AF120: =IF($T120<=0.32,"Ate 32%",IF($T120<=0.34,"Ate 34%","Acima de 34%")) -> Ate 34% | AG120: =IF($S120<=0.39,"Ate 39%",IF($S120<=0.41,"Ate 41%","Acima de 41%")) -> Ate 41%
A121: 2025.11.17 - Forte São Marcelo - Lançamento - Aprovação V3.pdf | B121: Viver Salvador – Forte São Marcelo | C121: 45978 | D121: Book de Lançamento | E121: Aprovacao | F121: 476 | G121: 204705 | H121: 0.036 | I121: 622 | J121: 47382 | K121: 0.478 | L121: 15 | M121: 99541 | O121: 208185 | P121: 187323 | Q121: 0.221 | R121: 0.2 | S121: 0.405 | T121: 0.333 | U121: 12892 | V121: 0.13 | W121: 2546 | X121: 0.666 | Y121: =(O121-P121)/O121 -> 0.10020895 | Z121: =P121/M121 -> 1.8818678 | AA121: =DATE(YEAR(C121),MONTH(C121),1) -> 45962 | AB121: =IF(X121>=0.5,"Faixa 1",IF(X121=0,"Faixa 3","Faixa 2")) -> Faixa 1 | AC121: 1 | AD121: =YEAR(AA121)&"-"&IF(MONTH(AA121)<4,1,IF(MONTH(AA121)<7,2,IF(MONTH(AA121)<10,3,4)))&"T" -> 2025-4T | AE121: =IF((Q121-R121)<0.005,"Até +0,5%",IF((Q121-R121)<0.01,"Ate +1%","Acima de +1%")) -> Acima de +1% | AF121: =IF($T121<=0.32,"Ate 32%",IF($T121<=0.34,"Ate 34%","Acima de 34%")) -> Ate 34% | AG121: =IF($S121<=0.39,"Ate 39%",IF($S121<=0.41,"Ate 41%","Acima de 41%")) -> Ate 41%
A122: 24.11.2025 - São Joaquim - Investimento.pdf | B122: São Joaquim | C122: 45985 | D122: Book de Investimento | E122: Aprovacao | F122: 333 | G122: 210465 | H122: 0.043 | I122: 304 | J122: 29496 | K122: 0.425 | L122: 14 | M122: 88577 | O122: 208220 | P122: 190122 | Q122: 0.253 | R122: 0.2 | S122: 0.457 | T122: 0.4 | U122: 11647 | V122: 0.158 | W122: 2803 | X122: 0.551 | Y122: =(O122-P122)/O122 -> 0.086917683 | Z122: =P122/M122 -> 2.1464037 | AA122: =DATE(YEAR(C122),MONTH(C122),1) -> 45962 | AB122: =IF(X122>=0.5,"Faixa 1",IF(X122=0,"Faixa 3","Faixa 2")) -> Faixa 1 | AC122: 1 | AD122: =YEAR(AA122)&"-"&IF(MONTH(AA122)<4,1,IF(MONTH(AA122)<7,2,IF(MONTH(AA122)<10,3,4)))&"T" -> 2025-4T | AE122: =IF((Q122-R122)<0.005,"Até +0,5%",IF((Q122-R122)<0.01,"Ate +1%","Acima de +1%")) -> Acima de +1% | AF122: =IF($T122<=0.32,"Ate 32%",IF($T122<=0.34,"Ate 34%","Acima de 34%")) -> Acima de 34% | AG122: =IF($S122<=0.39,"Ate 39%",IF($S122<=0.41,"Ate 41%","Acima de 41%")) -> Acima de 41%
A123: 28.11.2025 - Atilio 1407 - Escritura + Lançamento - Respostas.pdf | B123: Atílio 1407 | C123: 45989 | D123: Book de Escritura + Lançamento | E123: Aprovacao | F123: 874 | G123: 229573 | H123: 0.061 | I123: 999 | J123: 93824 | K123: 0.473 | L123: 20 | M123: 107350 | O123: 226816 | P123: 207123 | Q123: 0.179 | R123: 0.2 | S123: 0.38 | T123: 0.315 | U123: 13634 | V123: 0.067 | W123: 3189 | X123: 0.287 | Y123: =(O123-P123)/O123 -> 0.086823681 | Z123: =P123/M123 -> 1.9294178 | AA123: =DATE(YEAR(C123),MONTH(C123),1) -> 45962 | AB123: =IF(X123>=0.5,"Faixa 1",IF(X123=0,"Faixa 3","Faixa 2")) -> Faixa 2 | AC123: 1 | AD123: =YEAR(AA123)&"-"&IF(MONTH(AA123)<4,1,IF(MONTH(AA123)<7,2,IF(MONTH(AA123)<10,3,4)))&"T" -> 2025-4T | AE123: =IF((Q123-R123)<0.005,"Até +0,5%",IF((Q123-R123)<0.01,"Ate +1%","Acima de +1%")) -> Até +0,5% | AF123: =IF($T123<=0.32,"Ate 32%",IF($T123<=0.34,"Ate 34%","Acima de 34%")) -> Ate 32% | AG123: =IF($S123<=0.39,"Ate 39%",IF($S123<=0.41,"Ate 41%","Acima de 41%")) -> Ate 39%
A124: 2025.11.28 - Elevato Ramos - Escritura - Respostas_REV1.pdf | B124: Elevato Ramos – RZN2 | C124: 45989 | D124: Book de Escritura | E124: Aprovacao | F124: 494 | G124: 243279 | H124: 0.086 | I124: 2078 | J124: 50671 | K124: 0.43 | L124: 19 | M124: 102573 | O124: 238783 | P124: 217628 | Q124: 0.186 | R124: 0.2 | S124: 0.388 | T124: 0.322 | U124: 15664 | V124: 0.133 | W124: 4135 | X124: 0 | Y124: =(O124-P124)/O124 -> 0.088595084 | Z124: =P124/M124 -> 2.1216889 | AA124: =DATE(YEAR(C124),MONTH(C124),1) -> 45962 | AB124: =IF(X124>=0.5,"Faixa 1",IF(X124=0,"Faixa 3","Faixa 2")) -> Faixa 3 | AC124: 1 | AD124: =YEAR(AA124)&"-"&IF(MONTH(AA124)<4,1,IF(MONTH(AA124)<7,2,IF(MONTH(AA124)<10,3,4)))&"T" -> 2025-4T | AE124: =IF((Q124-R124)<0.005,"Até +0,5%",IF((Q124-R124)<0.01,"Ate +1%","Acima de +1%")) -> Até +0,5% | AF124: =IF($T124<=0.32,"Ate 32%",IF($T124<=0.34,"Ate 34%","Acima de 34%")) -> Ate 34% | AG124: =IF($S124<=0.39,"Ate 39%",IF($S124<=0.41,"Ate 41%","Acima de 41%")) -> Ate 39%
A125: 28.11.2025 - Essence Caucaia - Investimento - Respostas.pdf | B125: Essence Caucaia I, II e III (Terreno 710) | C125: 45989 | D125: Book de Investimento | E125: Aprovacao | F125: 1500 | G125: 207147 | H125: 0.085 | I125: 420 | J125: 137990 | K125: 0.462 | L125: 14 | M125: 91993 | O125: 199237 | P125: 181500 | Q125: 0.213 | R125: 0.2 | S125: 0.385 | T125: 0.319 | U125: 17242 | V125: 0.052 | W125: 2733 | X125: 0.756 | Y125: =(O125-P125)/O125 -> 0.089024629 | Z125: =P125/M125 -> 1.9729762 | AA125: =DATE(YEAR(C125),MONTH(C125),1) -> 45962 | AB125: =IF(X125>=0.5,"Faixa 1",IF(X125=0,"Faixa 3","Faixa 2")) -> Faixa 1 | AC125: 1 | AD125: =YEAR(AA125)&"-"&IF(MONTH(AA125)<4,1,IF(MONTH(AA125)<7,2,IF(MONTH(AA125)<10,3,4)))&"T" -> 2025-4T | AE125: =IF((Q125-R125)<0.005,"Até +0,5%",IF((Q125-R125)<0.01,"Ate +1%","Acima de +1%")) -> Acima de +1% | AF125: =IF($T125<=0.32,"Ate 32%",IF($T125<=0.34,"Ate 34%","Acima de 34%")) -> Ate 32% | AG125: =IF($S125<=0.39,"Ate 39%",IF($S125<=0.41,"Ate 41%","Acima de 41%")) -> Ate 39%
A126: 28.11.2025 - Estação das Fontes III - Escritura+Lançamento - Respostas.pdf | B126: Estação das Fontes III | C126: 45989 | D126: Book de Escritura + Lançamento | E126: Aprovacao | F126: 520 | G126: 190835 | H126: 0.073 | I126: 516 | J126: 45122 | K126: 0.435 | L126: 14 | M126: 86773 | O126: 199568 | P126: 175120 | Q126: 0.216 | R126: 0.2 | S126: 0.433 | T126: 0.346 | U126: 14098 | V126: 0.136 | W126: 2516 | X126: 0.75 | Y126: =(O126-P126)/O126 -> 0.12250461 | Z126: =P126/M126 -> 2.0181393 | AA126: =DATE(YEAR(C126),MONTH(C126),1) -> 45962 | AB126: =IF(X126>=0.5,"Faixa 1",IF(X126=0,"Faixa 3","Faixa 2")) -> Faixa 1 | AC126: 1 | AD126: =YEAR(AA126)&"-"&IF(MONTH(AA126)<4,1,IF(MONTH(AA126)<7,2,IF(MONTH(AA126)<10,3,4)))&"T" -> 2025-4T | AE126: =IF((Q126-R126)<0.005,"Até +0,5%",IF((Q126-R126)<0.01,"Ate +1%","Acima de +1%")) -> Acima de +1% | AF126: =IF($T126<=0.32,"Ate 32%",IF($T126<=0.34,"Ate 34%","Acima de 34%")) -> Acima de 34% | AG126: =IF($S126<=0.39,"Ate 39%",IF($S126<=0.41,"Ate 41%","Acima de 41%")) -> Acima de 41%
A127: 2025.11.28 - Morada Real - Lançamento - Atualizado.pdf | B127: Morada Real | C127: 45989 | D127: Book de Lançamento | E127: Aprovacao | F127: 443 | G127: 248192 | H127: 0.067 | I127: 1165 | J127: 46037 | K127: 0.425 | L127: 20 | M127: 103922 | O127: 244442 | P127: 227661 | Q127: 0.209 | R127: 0.209 | S127: 0.413 | T127: 0.364 | U127: 14195 | V127: 0.134 | W127: 3827 | X127: 0.393 | Y127: =(O127-P127)/O127 -> 0.068650232 | Z127: =P127/M127 -> 2.1906911 | AA127: =DATE(YEAR(C127),MONTH(C127),1) -> 45962 | AB127: =IF(X127>=0.5,"Faixa 1",IF(X127=0,"Faixa 3","Faixa 2")) -> Faixa 2 | AC127: 1 | AD127: =YEAR(AA127)&"-"&IF(MONTH(AA127)<4,1,IF(MONTH(AA127)<7,2,IF(MONTH(AA127)<10,3,4)))&"T" -> 2025-4T | AE127: =IF((Q127-R127)<0.005,"Até +0,5%",IF((Q127-R127)<0.01,"Ate +1%","Acima de +1%")) -> Até +0,5% | AF127: =IF($T127<=0.32,"Ate 32%",IF($T127<=0.34,"Ate 34%","Acima de 34%")) -> Acima de 34% | AG127: =IF($S127<=0.39,"Ate 39%",IF($S127<=0.41,"Ate 41%","Acima de 41%")) -> Acima de 41%
A128: 2025.12.01 - Aurora Iguaçu - Lançamento_R00 1.pdf | B128: Aurora Iguaçu (antigo Vale das águas II) – RBX | C128: 45992 | D128: Book de Lançamento | E128: Aprovacao | F128: 730 | G128: 199353 | H128: 0.053 | I128: 318 | J128: 68307 | K128: 0.472 | L128: 15 | M128: 93571 | O128: 198111 | P128: 180055 | Q128: 0.209 | R128: 0.2 | S128: 0.398 | T128: 0.332 | U128: 13271 | V128: 0.09 | W128: 2376 | X128: 0.717 | Y128: =(O128-P128)/O128 -> 0.091140825 | Z128: =P128/M128 -> 1.9242607 | AA128: =DATE(YEAR(C128),MONTH(C128),1) -> 45992 | AB128: =IF(X128>=0.5,"Faixa 1",IF(X128=0,"Faixa 3","Faixa 2")) -> Faixa 1 | AC128: 1 | AD128: =YEAR(AA128)&"-"&IF(MONTH(AA128)<4,1,IF(MONTH(AA128)<7,2,IF(MONTH(AA128)<10,3,4)))&"T" -> 2025-4T | AE128: =IF((Q128-R128)<0.005,"Até +0,5%",IF((Q128-R128)<0.01,"Ate +1%","Acima de +1%")) -> Ate +1% | AF128: =IF($T128<=0.32,"Ate 32%",IF($T128<=0.34,"Ate 34%","Acima de 34%")) -> Ate 34% | AG128: =IF($S128<=0.39,"Ate 39%",IF($S128<=0.41,"Ate 41%","Acima de 41%")) -> Ate 41%
... A133: 2025.12.01 - Viva Casa Amarela 2 - Investimento _Final.pdf | B133: Viva Casa Amarela 2 | C133: 45992 | D133: Book de Investimento | E133: Aprovacao | F133: 213 | G133: 257981 | H133: 0.077 | I133: 2114 | J133: 24039 | K133: 0.438 | L133: 16 | M133: 112860 | O133: 257543 | P133: 237036 | Q133: 0.202 | R133: 0.2 | S133: 0.38 | T133: 0.32 | U133: 6586 | V133: 0.115 | W133: 3738 | X133: 0.3 | Y133: =(O133-P133)/O133 -> 0.079625538 | Z133: =P133/M133 -> 2.1002658 | AA133: =DATE(YEAR(C133),MONTH(C133),1) -> 45992 | AB133: =IF(X133>=0.5,"Faixa 1",IF(X133=0,"Faixa 3","Faixa 2")) -> Faixa 2 | AC133: 1 | AD133: =YEAR(AA133)&"-"&IF(MONTH(AA133)<4,1,IF(MONTH(AA133)<7,2,IF(MONTH(AA133)<10,3,4)))&"T" -> 2025-4T | AE133: =IF((Q133-R133)<0.005,"Até +0,5%",IF((Q133-R133)<0.01,"Ate +1%","Acima de +1%")) -> Até +0,5% | AF133: =IF($T133<=0.32,"Ate 32%",IF($T133<=0.34,"Ate 34%","Acima de 34%")) -> Ate 32% | AG133: =IF($S133<=0.39,"Ate 39%",IF($S133<=0.41,"Ate 41%","Acima de 41%")) -> Ate 39%
A134: 2025.12.01 - Pirajussara - Essencial de Investimento.pdf | B134: Pirajussara | C134: 45993 | E134: Aprovacao | F134: 1103 | G134: 299691 | H134: 0.17 | I134: 4474 | J134: 111238 | K134: 0.364 | L134: 22 | M134: 100851 | O134: 276768 | P134: 260917 | Q134: 0.2 | R134: 0.2 | S134: 0.378 | T134: 0.335 | U134: 13544 | V134: 0.038 | W134: 5311 | X134: 0.009 | Y134: =(O134-P134)/O134 -> 0.057271794 | Z134: =P134/M134 -> 2.5871533 | AA134: =DATE(YEAR(C134),MONTH(C134),1) -> 45992 | AB134: =IF(X134>=0.5,"Faixa 1",IF(X134=0,"Faixa 3","Faixa 2")) -> Faixa 2 | AC134: 1 | AD134: =YEAR(AA134)&"-"&IF(MONTH(AA134)<4,1,IF(MONTH(AA134)<7,2,IF(MONTH(AA134)<10,3,4)))&"T" -> 2025-4T | AE134: =IF((Q134-R134)<0.005,"Até +0,5%",IF((Q134-R134)<0.01,"Ate +1%","Acima de +1%")) -> Até +0,5% | AF134: =IF($T134<=0.32,"Ate 32%",IF($T134<=0.34,"Ate 34%","Acima de 34%")) -> Ate 34% | AG134: =IF($S134<=0.39,"Ate 39%",IF($S134<=0.41,"Ate 41%","Acima de 41%")) -> Ate 39%
A135: 2025.12.08 - Brumatti Santos - Investimento Ampliado.pdf | B135: Brumatti Santos | C135: 45999 | D135: Book de Investimento - Comitê Ampliado | E135: Aprovacao | F135: 1092 | G135: 254759 | H135: 0.073 | I135: 1063 | J135: 119090 | K135: 0.443 | L135: 22 | M135: 109057 | O135: 246303 | P135: 226264 | Q135: 0.2 | R135: 0.2 | S135: 0.386 | T135: 0.325 | U135: 25678 | V135: 0.088 | W135: 3811 | X135: 0.277 | Y135: =(O135-P135)/O135 -> 0.081359139 | Z135: =P135/M135 -> 2.0747316 | AA135: =DATE(YEAR(C135),MONTH(C135),1) -> 45992 | AB135: =IF(X135>=0.5,"Faixa 1",IF(X135=0,"Faixa 3","Faixa 2")) -> Faixa 2 | AC135: 1 | AD135: =YEAR(AA135)&"-"&IF(MONTH(AA135)<4,1,IF(MONTH(AA135)<7,2,IF(MONTH(AA135)<10,3,4)))&"T" -> 2025-4T | AE135: =IF((Q135-R135)<0.005,"Até +0,5%",IF((Q135-R135)<0.01,"Ate +1%","Acima de +1%")) -> Até +0,5% | AF135: =IF($T135<=0.32,"Ate 32%",IF($T135<=0.34,"Ate 34%","Acima de 34%")) -> Ate 34% | AG135: =IF($S135<=0.39,"Ate 39%",IF($S135<=0.41,"Ate 41%","Acima de 41%")) -> Ate 39%
A136: 2025.12.08 - Cuiabinho - Reversão Essencial.pdf | B136: Cuiabinho | C136: 45999 | D136: Comitê Essencial de Reversão s/ Reneg | E136: Aprovacao | F136: 1140 | G136: 249113 | H136: 0.016 | I136: 360 | J136: 119109 | K136: 0.466 | L136: 23 | M136: 104482 | O136: 224338 | P136: 205299 | Q136: 0.237 | R136: 0.2 | S136: 0.421 | T136: 0.36 | U136: 19604 | V136: 0.07 | W136: 2924 | X136: 0.441 | Y136: =(O136-P136)/O136 -> 0.084867477 | Z136: =P136/M136 -> 1.9649222 | AA136: =DATE(YEAR(C136),MONTH(C136),1) -> 45992 | AB136: =IF(X136>=0.5,"Faixa 1",IF(X136=0,"Faixa 3","Faixa 2")) -> Faixa 2 | AC136: 1 | AD136: =YEAR(AA136)&"-"&IF(MONTH(AA136)<4,1,IF(MONTH(AA136)<7,2,IF(MONTH(AA136)<10,3,4)))&"T" -> 2025-4T | AE136: =IF((Q136-R136)<0.005,"Até +0,5%",IF((Q136-R136)<0.01,"Ate +1%","Acima de +1%")) -> Acima de +1% | AF136: =IF($T136<=0.32,"Ate 32%",IF($T136<=0.34,"Ate 34%","Acima de 34%")) -> Acima de 34% | AG136: =IF($S136<=0.39,"Ate 39%",IF($S136<=0.41,"Ate 41%","Acima de 41%")) -> Acima de 41%
A137: 2025.12.08 - Ferrovila - Investimento REV01.pdf | B137: Ferrovila | C137: 45999 | D137: Comite Ampliado de Investimento | E137: Aprovacao | F137: 783 | G137: 264157 | H137: 0.093 | I137: 1281 | J137: 80412 | K137: 0.395 | L137: 20 | M137: 102698 | O137: 260008 | P137: 237427 | Q137: 0.2 | R137: 0.2 | S137: 0.41 | T137: 0.349 | U137: 18851 | V137: 0.085 | W137: 4298 | X137: 0 | Y137: =(O137-P137)/O137 -> 0.086847328 | Z137: =P137/M137 -> 2.3118951 | AA137: =DATE(YEAR(C137),MONTH(C137),1) -> 45992 | AB137: =IF(X137>=0.5,"Faixa 1",IF(X137=0,"Faixa 3","Faixa 2")) -> Faixa 3 | AC137: 1 | AD137: =YEAR(AA137)&"-"&IF(MONTH(AA137)<4,1,IF(MONTH(AA137)<7,2,IF(MONTH(AA137)<10,3,4)))&"T" -> 2025-4T | AE137: =IF((Q137-R137)<0.005,"Até +0,5%",IF((Q137-R137)<0.01,"Ate +1%","Acima de +1%")) -> Até +0,5% | AF137: =IF($T137<=0.32,"Ate 32%",IF($T137<=0.34,"Ate 34%","Acima de 34%")) -> Acima de 34% | AG137: =IF($S137<=0.39,"Ate 39%",IF($S137<=0.41,"Ate 41%","Acima de 41%")) -> Ate 41%
A138: 2025.12.08 - Laguna Ville - Escritura e Lançamento REV02.1.pdf | B138: Laguna Ville | C138: 45999 | D138: Book de Escritura e Lançamento | E138: Aprovacao | F138: 532 | G138: 219601 | H138: 0.099 | I138: 697 | J138: 49407 | K138: 0.436 | L138: 16 | M138: 92871 | O138: 213044 | P138: 193042 | Q138: 0.202 | R138: 0.2 | S138: 0.384 | T138: 0.314 | U138: 15619 | V138: 0.138 | W138: 2769 | X138: 0.608 | Y138: =(O138-P138)/O138 -> 0.093886709 | Z138: =P138/M138 -> 2.0786037 | AA138: =DATE(YEAR(C138),MONTH(C138),1) -> 45992 | AB138: =IF(X138>=0.5,"Faixa 1",IF(X138=0,"Faixa 3","Faixa 2")) -> Faixa 1 | AC138: 1 | AD138: =YEAR(AA138)&"-"&IF(MONTH(AA138)<4,1,IF(MONTH(AA138)<7,2,IF(MONTH(AA138)<10,3,4)))&"T" -> 2025-4T | AE138: =IF((Q138-R138)<0.005,"Até +0,5%",IF((Q138-R138)<0.01,"Ate +1%","Acima de +1%")) -> Até +0,5% | AF138: =IF($T138<=0.32,"Ate 32%",IF($T138<=0.34,"Ate 34%","Acima de 34%")) -> Ate 32% | AG138: =IF($S138<=0.39,"Ate 39%",IF($S138<=0.41,"Ate 41%","Acima de 41%")) -> Ate 39%
A139: 2025.12.09 - Protendit - Essencial_v1 2.pdf | B139: Pedro de Castilho (PROTENDIT) | C139: 45999 | E139: Aprovacao | F139: 952 | G139: 230000 | H139: 0.099 | I139: 2086 | J139: 93190 | K139: 0.447 | L139: 25 | M139: 97888 | O139: 219216 | P139: 197616 | Q139: 0.201 | R139: 0.2 | S139: 0.36 | T139: 0.28 | U139: 15303 | V139: 0.067 | W139: 2573 | X139: 0.75 | Y139: =(O139-P139)/O139 -> 0.098532954 | Z139: =P139/M139 -> 2.018797 | AA139: =DATE(YEAR(C139),MONTH(C139),1) -> 45992 | AB139: =IF(X139>=0.5,"Faixa 1",IF(X139=0,"Faixa 3","Faixa 2")) -> Faixa 1 | AC139: 1 | AD139: =YEAR(AA139)&"-"&IF(MONTH(AA139)<4,1,IF(MONTH(AA139)<7,2,IF(MONTH(AA139)<10,3,4)))&"T" -> 2025-4T | AE139: =IF((Q139-R139)<0.005,"Até +0,5%",IF((Q139-R139)<0.01,"Ate +1%","Acima de +1%")) -> Até +0,5% | AF139: =IF($T139<=0.32,"Ate 32%",IF($T139<=0.34,"Ate 34%","Acima de 34%")) -> Ate 32% | AG139: =IF($S139<=0.39,"Ate 39%",IF($S139<=0.41,"Ate 41%","Acima de 41%")) -> Ate 39%
A140: 2025.12.08 - Vista Paraná - Ampliado de Investimento R00.pdf | B140: Vista Paraná– RZN3 | C140: 45999 | D140: Book de Investimento | E140: Aprovacao | F140: 285 | G140: 250807 | H140: 0.044 | I140: 992 | J140: 32482 | K140: 0.464 | L140: 16 | M140: 113972 | O140: 245737 | P140: 225489 | Q140: 0.201 | R140: 0.2 | S140: 0.401 | T140: 0.342 | U140: 11516 | V140: 0.156 | W140: 4100 | X140: 0 | Y140: =(O140-P140)/O140 -> 0.082397034 | Z140: =P140/M140 -> 1.9784596 | AA140: =DATE(YEAR(C140),MONTH(C140),1) -> 45992 | AB140: =IF(X140>=0.5,"Faixa 1",IF(X140=0,"Faixa 3","Faixa 2")) -> Faixa 3 | AC140: 1 | AD140: =YEAR(AA140)&"-"&IF(MONTH(AA140)<4,1,IF(MONTH(AA140)<7,2,IF(MONTH(AA140)<10,3,4)))&"T" -> 2025-4T | AE140: =IF((Q140-R140)<0.005,"Até +0,5%",IF((Q140-R140)<0.01,"Ate +1%","Acima de +1%")) -> Até +0,5% | AF140: =IF($T140<=0.32,"Ate 32%",IF($T140<=0.34,"Ate 34%","Acima de 34%")) -> Acima de 34% | AG140: =IF($S140<=0.39,"Ate 39%",IF($S140<=0.41,"Ate 41%","Acima de 41%")) -> Ate 41%
A141: 2025.12.12 - Bandeirante -Escrit + Lançamento_Respostas.pdf | B141: Bandeirante | C141: 46003 | D141: Book de Escritura + Lançamento | E141: Aprovacao | F141: 444 | G141: 209432 | H141: 0.061 | I141: 595 | J141: 44228 | K141: 0.457 | L141: 19 | M141: 99613 | O141: 217978 | P141: 197100 | Q141: 0.19 | R141: 0.2 | S141: 0.396 | T141: 0.325 | U141: 16218 | V141: 0.169 | W141: 2966 | X141: 0.493 | Y141: =(O141-P141)/O141 -> 0.095780308 | Z141: =P141/M141 -> 1.9786574 | AA141: =DATE(YEAR(C141),MONTH(C141),1) -> 45992 | AB141: =IF(X141>=0.5,"Faixa 1",IF(X141=0,"Faixa 3","Faixa 2")) -> Faixa 2 | AC141: 1 | AD141: =YEAR(AA141)&"-"&IF(MONTH(AA141)<4,1,IF(MONTH(AA141)<7,2,IF(MONTH(AA141)<10,3,4)))&"T" -> 2025-4T | AE141: =IF((Q141-R141)<0.005,"Até +0,5%",IF((Q141-R141)<0.01,"Ate +1%","Acima de +1%")) -> Até +0,5% | AF141: =IF($T141<=0.32,"Ate 32%",IF($T141<=0.34,"Ate 34%","Acima de 34%")) -> Ate 34% | AG141: =IF($S141<=0.39,"Ate 39%",IF($S141<=0.41,"Ate 41%","Acima de 41%")) -> Ate 41%
A142: 2025.12.12 - Elevato Inhaúma - Ampliado de Investimento_Respostas R01.pdf | B142: Elevato Inhaúma – RZN2 | C142: 46003 | D142: Book de Investimento | E142: Aprovacao | F142: 496 | G142: 240000 | H142: 0.07 | I142: 1561 | J142: 49492 | K142: 0.437 | L142: 18 | M142: 99782 | O142: 228529 | P142: 204827 | Q142: 0.2 | R142: 0.2 | S142: 0.402 | T142: 0.325 | U142: 15876 | V142: 0.131 | W142: 3563 | X142: 0.25 | Y142: =(O142-P142)/O142 -> 0.1037155 | Z142: =P142/M142 -> 2.052745 | AA142: =DATE(YEAR(C142),MONTH(C142),1) -> 45992 | AB142: =IF(X142>=0.5,"Faixa 1",IF(X142=0,"Faixa 3","Faixa 2")) -> Faixa 2 | AC142: 1 | AD142: =YEAR(AA142)&"-"&IF(MONTH(AA142)<4,1,IF(MONTH(AA142)<7,2,IF(MONTH(AA142)<10,3,4)))&"T" -> 2025-4T | AE142: =IF((Q142-R142)<0.005,"Até +0,5%",IF((Q142-R142)<0.01,"Ate +1%","Acima de +1%")) -> Até +0,5% | AF142: =IF($T142<=0.32,"Ate 32%",IF($T142<=0.34,"Ate 34%","Acima de 34%")) -> Ate 34% | AG142: =IF($S142<=0.39,"Ate 39%",IF($S142<=0.41,"Ate 41%","Acima de 41%")) -> Ate 41%
A143: 2025.12.12 - Pituba Prime - Investimento REV03_Resposta.pdf | B143: Pituba Prime | C143: 46003 | D143: Book de Investimento | E143: Aprovacao | F143: 428 | G143: 297220 | H143: 0.105 | I143: 2902 | J143: 48140 | K143: 0.388 | L143: 20 | M143: 112476 | O143: 289733 | P143: 266959 | Q143: 0.224 | R143: 0.2 | S143: 0.419 | T143: 0.363 | U143: 10380 | V143: 0.081 | W143: 5876 | X143: 0 | Y143: =(O143-P143)/O143 -> 0.078603404 | Z143: =P143/M143 -> 2.3734752 | AA143: =DATE(YEAR(C143),MONTH(C143),1) -> 45992 | AB143: =IF(X143>=0.5,"Faixa 1",IF(X143=0,"Faixa 3","Faixa 2")) -> Faixa 3 | AC143: 1 | AD143: =YEAR(AA143)&"-"&IF(MONTH(AA143)<4,1,IF(MONTH(AA143)<7,2,IF(MONTH(AA143)<10,3,4)))&"T" -> 2025-4T | AE143: =IF((Q143-R143)<0.005,"Até +0,5%",IF((Q143-R143)<0.01,"Ate +1%","Acima de +1%")) -> Acima de +1% | AF143: =IF($T143<=0.32,"Ate 32%",IF($T143<=0.34,"Ate 34%","Acima de 34%")) -> Acima de 34% | AG143: =IF($S143<=0.39,"Ate 39%",IF($S143<=0.41,"Ate 41%","Acima de 41%")) -> Acima de 41%
A144: 2025.12.12 - Vila Butanta - Rev +Escr + Lçto - Respostas.pdf | B144: Vila Butantã (Joaquim Guimarães) | C144: 46003 | D144: Book de Escritura + Lançamento | E144: Aprovacao | F144: 796 | G144: 268088 | H144: 0.079 | I144: 3621 | J144: 85911 | K144: 0.45 | L144: 27 | M144: 107929 | O144: 239881 | P144: 219296 | Q144: 0.2 | R144: 0.2 | S144: 0.371 | T144: 0.303 | U144: 11753 | V144: 0.062 | W144: 3700 | X144: 0.203 | Y144: =(O144-P144)/O144 -> 0.085813382 | Z144: =P144/M144 -> 2.0318543 | AA144: =DATE(YEAR(C144),MONTH(C144),1) -> 45992 | AB144: =IF(X144>=0.5,"Faixa 1",IF(X144=0,"Faixa 3","Faixa 2")) -> Faixa 2 | AC144: 1 | AD144: =YEAR(AA144)&"-"&IF(MONTH(AA144)<4,1,IF(MONTH(AA144)<7,2,IF(MONTH(AA144)<10,3,4)))&"T" -> 2025-4T | AE144: =IF((Q144-R144)<0.005,"Até +0,5%",IF((Q144-R144)<0.01,"Ate +1%","Acima de +1%")) -> Até +0,5% | AF144: =IF($T144<=0.32,"Ate 32%",IF($T144<=0.34,"Ate 34%","Acima de 34%")) -> Ate 32% | AG144: =IF($S144<=0.39,"Ate 39%",IF($S144<=0.41,"Ate 41%","Acima de 41%")) -> Ate 39%
A145: 2025.12.15 - Laranjal - Book Essencial EE.pdf | B145: Laranjal | C145: 46006 | D145: Comitê Essencial | E145: Aprovacao | F145: 568 | G145: 236900 | H145: 0.031 | I145: 400 | J145: 61773 | K145: 0.475 | L145: 21 | M145: 108756 | O145: 228739 | P145: 209271 | Q145: 0.218 | R145: 0.2 | S145: 0.402 | T145: 0.339 | U145: 16017 | V145: 0.112 | W145: 2964 | X145: 0.411 | Y145: =(O145-P145)/O145 -> 0.085110104 | Z145: =P145/M145 -> 1.9242249 | AA145: =DATE(YEAR(C145),MONTH(C145),1) -> 45992 | AB145: =IF(X145>=0.5,"Faixa 1",IF(X145=0,"Faixa 3","Faixa 2")) -> Faixa 2 | AC145: 1 | AD145: =YEAR(AA145)&"-"&IF(MONTH(AA145)<4,1,IF(MONTH(AA145)<7,2,IF(MONTH(AA145)<10,3,4)))&"T" -> 2025-4T | AE145: =IF((Q145-R145)<0.005,"Até +0,5%",IF((Q145-R145)<0.01,"Ate +1%","Acima de +1%")) -> Acima de +1% | AF145: =IF($T145<=0.32,"Ate 32%",IF($T145<=0.34,"Ate 34%","Acima de 34%")) -> Ate 34% | AG145: =IF($S145<=0.39,"Ate 39%",IF($S145<=0.41,"Ate 41%","Acima de 41%")) -> Ate 41%
A146: 2025.12.19 - Elevato Ramos - Lançamento REV03_Respostas.pdf | B146: Elevato Ramos – RZN2 | C146: 46010 | D146: Book de Lançamento - Respostas | E146: Aprovacao | F146: 494 | G146: 243006 | H146: 0.088 | I146: 2398 | J146: 49509 | K146: 0.42 | L146: 19 | M146: 100220 | O146: 238783 | P146: 217628 | Q146: 0.197 | R146: 0.2 | S146: 0.399 | T146: 0.334 | U146: 15273 | V146: 0.131 | W146: 4135 | X146: 0 | Y146: =(O146-P146)/O146 -> 0.088595084 | Z146: =P146/M146 -> 2.1715027 | AA146: =DATE(YEAR(C146),MONTH(C146),1) -> 45992 | AB146: =IF(X146>=0.5,"Faixa 1",IF(X146=0,"Faixa 3","Faixa 2")) -> Faixa 3 | AC146: 1 | AD146: =YEAR(AA146)&"-"&IF(MONTH(AA146)<4,1,IF(MONTH(AA146)<7,2,IF(MONTH(AA146)<10,3,4)))&"T" -> 2025-4T | AE146: =IF((Q146-R146)<0.005,"Até +0,5%",IF((Q146-R146)<0.01,"Ate +1%","Acima de +1%")) -> Até +0,5% | AF146: =IF($T146<=0.32,"Ate 32%",IF($T146<=0.34,"Ate 34%","Acima de 34%")) -> Ate 34% | AG146: =IF($S146<=0.39,"Ate 39%",IF($S146<=0.41,"Ate 41%","Acima de 41%")) -> Ate 41%
A147: 2025.12.19 - Guaranys - Ampliado de Investimento_R03_Respostas.pdf | B147: Guaranys – ZO7 | C147: 46010 | D147: Book de Investimento | E147: Aprovacao | F147: 354 | G147: 231751 | H147: 0.093 | I147: 829 | J147: 34938 | K147: 0.444 | L147: 12 | M147: 98695 | O147: 222366 | P147: 201782 | Q147: 0.2 | R147: 0.2 | S147: 0.388 | T147: 0.32 | U147: 11729 | V147: 0.142 | W147: 3867 | X147: 0.145 | Y147: =(O147-P147)/O147 -> 0.092568108 | Z147: =P147/M147 -> 2.0445007 | AA147: =DATE(YEAR(C147),MONTH(C147),1) -> 45992 | AB147: =IF(X147>=0.5,"Faixa 1",IF(X147=0,"Faixa 3","Faixa 2")) -> Faixa 2 | AC147: 1 | AD147: =YEAR(AA147)&"-"&IF(MONTH(AA147)<4,1,IF(MONTH(AA147)<7,2,IF(MONTH(AA147)<10,3,4)))&"T" -> 2025-4T | AE147: =IF((Q147-R147)<0.005,"Até +0,5%",IF((Q147-R147)<0.01,"Ate +1%","Acima de +1%")) -> Até +0,5% | AF147: =IF($T147<=0.32,"Ate 32%",IF($T147<=0.34,"Ate 34%","Acima de 34%")) -> Ate 32% | AG147: =IF($S147<=0.39,"Ate 39%",IF($S147<=0.41,"Ate 41%","Acima de 41%")) -> Ate 39%
A148: 2025.12.19 - Novos Ares Luar - Comitê Reversão c Reneg. - Resposta.pdf | B148: Novos Ares Luar | C148: 46010 | D148: Book de Reversão c/ Renegociação | E148: Aprovacao | F148: 530 | G148: 205179 | H148: 0.066 | I148: 345 | J148: 46365 | K148: 0.407 | L148: 12 | M148: 87481 | O148: 214814 | P148: 190830 | Q148: 0.22 | R148: 0.2 | S148: 0.441 | T148: 0.365 | U148: 16246 | V148: 0.136 | W148: 2707 | X148: 0.641 | Y148: =(O148-P148)/O148 -> 0.11165008 | Z148: =P148/M148 -> 2.181388 | AA148: =DATE(YEAR(C148),MONTH(C148),1) -> 45992 | AB148: =IF(X148>=0.5,"Faixa 1",IF(X148=0,"Faixa 3","Faixa 2")) -> Faixa 1 | AC148: 1 | AD148: =YEAR(AA148)&"-"&IF(MONTH(AA148)<4,1,IF(MONTH(AA148)<7,2,IF(MONTH(AA148)<10,3,4)))&"T" -> 2025-4T | AE148: =IF((Q148-R148)<0.005,"Até +0,5%",IF((Q148-R148)<0.01,"Ate +1%","Acima de +1%")) -> Acima de +1% | AF148: =IF($T148<=0.32,"Ate 32%",IF($T148<=0.34,"Ate 34%","Acima de 34%")) -> Acima de 34% | AG148: =IF($S148<=0.39,"Ate 39%",IF($S148<=0.41,"Ate 41%","Acima de 41%")) -> Acima de 41%
A149: 12.01.26 - Novos Ares Aurora - Escritura + Lançamento R01 (1).pdf | B149: Novos Ares Aurora - Atualização | C149: 46034 | D149: Book de Escritura + Lançamento | E149: Aprovacao | F149: 267 | G149: 202670 | H149: 0.097 | I149: 472 | J149: 23759 | K149: 0.431 | L149: 11 | M149: 88986 | O149: 206466 | P149: 183907 | Q149: 0.201 | R149: 0.2 | S149: 0.397 | T149: 0.325 | U149: 9727 | V149: 0.178 | W149: 2784 | X149: 0.621 | Y149: =(O149-P149)/O149 -> 0.10926254 | Z149: =P149/M149 -> 2.0666959 | AA149: =DATE(YEAR(C149),MONTH(C149),1) -> 46023 | AB149: =IF(X149>=0.5,"Faixa 1",IF(X149=0,"Faixa 3","Faixa 2")) -> Faixa 1 | AC149: 1 | AD149: =YEAR(AA149)&"-"&IF(MONTH(AA149)<4,1,IF(MONTH(AA149)<7,2,IF(MONTH(AA149)<10,3,4)))&"T" -> 2026-1T | AE149: =IF((Q149-R149)<0.005,"Até +0,5%",IF((Q149-R149)<0.01,"Ate +1%","Acima de +1%")) -> Até +0,5% | AF149: =IF($T149<=0.32,"Ate 32%",IF($T149<=0.34,"Ate 34%","Acima de 34%")) -> Ate 34% | AG149: =IF($S149<=0.39,"Ate 39%",IF($S149<=0.41,"Ate 41%","Acima de 41%")) -> Ate 41%
A150: 2026.01.19 - LAGUNA - Investimento - Respostas.pdf | B150: Laguna | C150: 46041 | D150: Book de Investimento | E150: Aprovacao | F150: 512 | G150: 241418 | H150: 0.105 | I150: 1827 | J150: 48855 | K150: 0.391 | L150: 19 | M150: 95419 | O150: 243984 | P150: 221407 | Q150: 0.2 | R150: 0.2 | S150: 0.411 | T150: 0.344 | U150: 16767 | V150: 0.127 | W150: 3723 | X150: 0.178 | Y150: =(O150-P150)/O150 -> 0.092534756 | Z150: =P150/M150 -> 2.320366 | AA150: =DATE(YEAR(C150),MONTH(C150),1) -> 46023 | AB150: =IF(X150>=0.5,"Faixa 1",IF(X150=0,"Faixa 3","Faixa 2")) -> Faixa 2 | AC150: 1 | AD150: =YEAR(AA150)&"-"&IF(MONTH(AA150)<4,1,IF(MONTH(AA150)<7,2,IF(MONTH(AA150)<10,3,4)))&"T" -> 2026-1T | AE150: =IF((Q150-R150)<0.005,"Até +0,5%",IF((Q150-R150)<0.01,"Ate +1%","Acima de +1%")) -> Até +0,5% | AF150: =IF($T150<=0.32,"Ate 32%",IF($T150<=0.34,"Ate 34%","Acima de 34%")) -> Acima de 34% | AG150: =IF($S150<=0.39,"Ate 39%",IF($S150<=0.41,"Ate 41%","Acima de 41%")) -> Acima de 41%
A151: 2026.01.19 - Vista da Mangueira - Escritura e Lançamento - Resposta.pdf | B151: Vista da Mangueira | C151: 46041 | D151: Book de Escritura + Lançamento | E151: Aprovacao | F151: 416 | G151: 203209 | H151: 0.023 | I151: 130 | J151: 41788 | K151: 0.486 | L151: 14 | M151: 100452 | O151: 206656 | P151: 189868 | Q151: 0.22 | R151: 0.2 | S151: 0.392 | T151: 0.333 | U151: 14156 | V151: 0.166 | W151: 2682 | X151: 0.619 | Y151: =(O151-P151)/O151 -> 0.081236451 | Z151: =P151/M151 -> 1.8901366 | AA151: =DATE(YEAR(C151),MONTH(C151),1) -> 46023 | AB151: =IF(X151>=0.5,"Faixa 1",IF(X151=0,"Faixa 3","Faixa 2")) -> Faixa 1 | AC151: 1 | AD151: =YEAR(AA151)&"-"&IF(MONTH(AA151)<4,1,IF(MONTH(AA151)<7,2,IF(MONTH(AA151)<10,3,4)))&"T" -> 2026-1T | AE151: =IF((Q151-R151)<0.005,"Até +0,5%",IF((Q151-R151)<0.01,"Ate +1%","Acima de +1%")) -> Acima de +1% | AF151: =IF($T151<=0.32,"Ate 32%",IF($T151<=0.34,"Ate 34%","Acima de 34%")) -> Ate 34% | AG151: =IF($S151<=0.39,"Ate 39%",IF($S151<=0.41,"Ate 41%","Acima de 41%")) -> Ate 41%
... A165: 2026.03.06 - Mirante Messejana - Escritura e Lançamento REV02_Respostas.pdf | B165: Mirante Messejana | C165: 46087 | D165: Book de Escritura e Lançamento | E165: Aprovacao | F165: 536 | G165: 268033 | H165: 0.106 | I165: 2114 | J165: 57247 | K165: 0.391 | L165: 20 | M165: 106805 | O165: 272861 | P165: 239562 | Q165: 0.221 | R165: 0.22 | S165: 0.417 | T165: 0.328 | U165: 14126 | V165: 0.096 | W165: 4521 | X165: 0 | Y165: =(O165-P165)/O165 -> 0.12203649 | Z165: =P165/M165 -> 2.2429849 | AA165: =DATE(YEAR(C165),MONTH(C165),1) -> 46082 | AB165: =IF(X165>=0.5,"Faixa 1",IF(X165=0,"Faixa 3","Faixa 2")) -> Faixa 3 | AC165: 1 | AD165: =YEAR(AA165)&"-"&IF(MONTH(AA165)<4,1,IF(MONTH(AA165)<7,2,IF(MONTH(AA165)<10,3,4)))&"T" -> 2026-1T | AE165: =IF((Q165-R165)<0.005,"Até +0,5%",IF((Q165-R165)<0.01,"Ate +1%","Acima de +1%")) -> Até +0,5% | AF165: =IF($T165<=0.32,"Ate 32%",IF($T165<=0.34,"Ate 34%","Acima de 34%")) -> Ate 34% | AG165: =IF($S165<=0.39,"Ate 39%",IF($S165<=0.41,"Ate 41%","Acima de 41%")) -> Acima de 41%
A166: 2026.03.09 - Reserva dos Colibris - Escritura e Lançamento V6.RESP.pdf | B166: Reserva dos Colibris | C166: 46090 | D166: Book de Escritura e Lançamento | E166: Aprovacao | F166: 464 | G166: 247349 | H166: 0.085 | I166: 1146 | J166: 52250 | K166: 0.433 | L166: 19 | M166: 112608 | N166: 0.001 | O166: 259882 | P166: 231955 | Q166: 0.2 | R166: 0.22 | S166: 0.395 | T166: 0.31 | U166: 12100 | V166: 0.101 | W166: 4052 | X166: 0.117 | Y166: =(O166-P166)/O166 -> 0.10746031 | Z166: =P166/M166 -> 2.0598448 | AA166: =DATE(YEAR(C166),MONTH(C166),1) -> 46082 | AB166: =IF(X166>=0.5,"Faixa 1",IF(X166=0,"Faixa 3","Faixa 2")) -> Faixa 2 | AC166: 1 | AD166: =YEAR(AA166)&"-"&IF(MONTH(AA166)<4,1,IF(MONTH(AA166)<7,2,IF(MONTH(AA166)<10,3,4)))&"T" -> 2026-1T | AE166: =IF((Q166-R166)<0.005,"Até +0,5%",IF((Q166-R166)<0.01,"Ate +1%","Acima de +1%")) -> Até +0,5% | AF166: =IF($T166<=0.32,"Ate 32%",IF($T166<=0.34,"Ate 34%","Acima de 34%")) -> Ate 32% | AG166: =IF($S166<=0.39,"Ate 39%",IF($S166<=0.41,"Ate 41%","Acima de 41%")) -> Ate 41%
A167: 2026.03.09 - Torres Marina - ESC + LÇTO - R04.pdf | B167: Torres Marina | C167: 46090 | D167: Book de Escritura + Lançamento | E167: Aprovacao | F167: 530 | G167: 223728 | H167: 0.04 | I167: 654 | J167: 55446 | K167: 0.476 | L167: 20 | M167: 104616 | N167: -0.004 | O167: 219741 | P167: 198645 | Q167: 0.188 | R167: 0.22 | S167: 0.381 | T167: 0.304 | U167: 18137 | V167: 0.156 | W167: 2506 | X167: 0.762 | Y167: =(O167-P167)/O167 -> 0.096003932 | Z167: =P167/M167 -> 1.8988013 | AA167: =DATE(YEAR(C167),MONTH(C167),1) -> 46082 | AB167: =IF(X167>=0.5,"Faixa 1",IF(X167=0,"Faixa 3","Faixa 2")) -> Faixa 1 | AC167: 1 | AD167: =YEAR(AA167)&"-"&IF(MONTH(AA167)<4,1,IF(MONTH(AA167)<7,2,IF(MONTH(AA167)<10,3,4)))&"T" -> 2026-1T | AE167: =IF((Q167-R167)<0.005,"Até +0,5%",IF((Q167-R167)<0.01,"Ate +1%","Acima de +1%")) -> Até +0,5% | AF167: =IF($T167<=0.32,"Ate 32%",IF($T167<=0.34,"Ate 34%","Acima de 34%")) -> Ate 32% | AG167: =IF($S167<=0.39,"Ate 39%",IF($S167<=0.41,"Ate 41%","Acima de 41%")) -> Ate 39%
A168: 2026.03.16 - Estrada das Lágrimas - Investimento Essencial v4.2_Respostas.pdf | B168: Estrada das Lágrimas | C168: 46097 | D168: Comitê de Investimentos - Essencial | E168: Aprovacao | F168: 565 | G168: 293504 | H168: 0.099 | I168: 4569 | J168: 59970 | K168: 0.377 | L168: 20 | M168: 106141 | O168: 281421 | P168: 248278 | Q168: 0.204 | R168: 0.22 | S168: 0.435 | T168: 0.347 | U168: 26756 | V168: 0.153 | W168: 4837 | X168: 0 | Y168: =(O168-P168)/O168 -> 0.11777017 | Z168: =P168/M168 -> 2.3391338 | AA168: =DATE(YEAR(C168),MONTH(C168),1) -> 46082 | AB168: =IF(X168>=0.5,"Faixa 1",IF(X168=0,"Faixa 3","Faixa 2")) -> Faixa 3 | AC168: 1 | AD168: =YEAR(AA168)&"-"&IF(MONTH(AA168)<4,1,IF(MONTH(AA168)<7,2,IF(MONTH(AA168)<10,3,4)))&"T" -> 2026-1T | AE168: =IF((Q168-R168)<0.005,"Até +0,5%",IF((Q168-R168)<0.01,"Ate +1%","Acima de +1%")) -> Até +0,5% | AF168: =IF($T168<=0.32,"Ate 32%",IF($T168<=0.34,"Ate 34%","Acima de 34%")) -> Acima de 34% | AG168: =IF($S168<=0.39,"Ate 39%",IF($S168<=0.41,"Ate 41%","Acima de 41%")) -> Acima de 41%
A169: 16.03.26 - Porto Lima - Lançamento EE.1.pdf | B169: Porto Lima & Porto Seleta | C169: 46097 | D169: Book de Lançamento | E169: Aprovacao | F169: 907 | G169: 206720 | H169: 0.044 | I169: 371 | J169: 88708 | K169: 0.464 | L169: 12 | M169: 97804 | N169: -0.004 | O169: 210643 | P169: 185785 | Q169: 0.23 | R169: 0.22 | S169: 0.412 | T169: 0.324 | U169: 19649 | V169: 0.1 | W169: 2535 | X169: 0.721 | Y169: =(O169-P169)/O169 -> 0.11801009 | Z169: =P169/M169 -> 1.8995644 | AA169: =DATE(YEAR(C169),MONTH(C169),1) -> 46082 | AB169: =IF(X169>=0.5,"Faixa 1",IF(X169=0,"Faixa 3","Faixa 2")) -> Faixa 1 | AC169: 1 | AD169: =YEAR(AA169)&"-"&IF(MONTH(AA169)<4,1,IF(MONTH(AA169)<7,2,IF(MONTH(AA169)<10,3,4)))&"T" -> 2026-1T | AE169: =IF((Q169-R169)<0.005,"Até +0,5%",IF((Q169-R169)<0.01,"Ate +1%","Acima de +1%")) -> Acima de +1% | AF169: =IF($T169<=0.32,"Ate 32%",IF($T169<=0.34,"Ate 34%","Acima de 34%")) -> Ate 34% | AG169: =IF($S169<=0.39,"Ate 39%",IF($S169<=0.41,"Ate 41%","Acima de 41%")) -> Acima de 41%
A170: 2026.03.20 - Elevato Ramos - Lançamento EE.1_Respostas.pdf | B170: Elevato Ramos – RZN2 | C170: 46101 | D170: Book de Lançamento | E170: Aprovacao | F170: 494 | G170: 243006 | H170: 0.087 | I170: 2451 | J170: 50111 | K170: 0.413 | L170: 19 | M170: 101439 | N170: 0.001 | O170: 245505 | P170: 216533 | Q170: 0.221 | R170: 0.22 | S170: 0.42 | T170: 0.33 | U170: 14440 | V170: 0.119 | W170: 4135 | X170: 0.182 | Y170: =(O170-P170)/O170 -> 0.11800982 | Z170: =P170/M170 -> 2.1346129 | AA170: =DATE(YEAR(C170),MONTH(C170),1) -> 46082 | AB170: =IF(X170>=0.5,"Faixa 1",IF(X170=0,"Faixa 3","Faixa 2")) -> Faixa 2 | AC170: 1 | AD170: =YEAR(AA170)&"-"&IF(MONTH(AA170)<4,1,IF(MONTH(AA170)<7,2,IF(MONTH(AA170)<10,3,4)))&"T" -> 2026-1T | AE170: =IF((Q170-R170)<0.005,"Até +0,5%",IF((Q170-R170)<0.01,"Ate +1%","Acima de +1%")) -> Até +0,5% | AF170: =IF($T170<=0.32,"Ate 32%",IF($T170<=0.34,"Ate 34%","Acima de 34%")) -> Ate 34% | AG170: =IF($S170<=0.39,"Ate 39%",IF($S170<=0.41,"Ate 41%","Acima de 41%")) -> Acima de 41%
A171: 2025.11.24 - Porto Valência F2 - Lançamento_Respostas (1) 1.pdf | B171: Porto Valência F2 | C171: 45989 | D171: Book de Lançamento | E171: Aprovacao | F171: 140 | G171: 203600 | H171: 0.034 | I171: 100 | J171: 12632 | K171: 0.424 | L171: 8 | M171: 90225 | O171: 212877 | P171: 191657 | Q171: 0.213 | R171: 0.301 | S171: 0.46 | T171: 0.396 | U171: 5135 | V171: 0.182 | W171: 2907 | X171: 0.2 | Y171: =(O171-P171)/O171 -> 0.099681976 | Z171: =P171/M171 -> 2.1242117 | AA171: =DATE(YEAR(C171),MONTH(C171),1) -> 45962 | AB171: =IF(X171>=0.5,"Faixa 1",IF(X171=0,"Faixa 3","Faixa 2")) -> Faixa 2 | AC171: 1 | AD171: =YEAR(AA171)&"-"&IF(MONTH(AA171)<4,1,IF(MONTH(AA171)<7,2,IF(MONTH(AA171)<10,3,4)))&"T" -> 2025-4T | AE171: =IF((Q171-R171)<0.005,"Até +0,5%",IF((Q171-R171)<0.01,"Ate +1%","Acima de +1%")) -> Até +0,5% | AF171: =IF($T171<=0.32,"Ate 32%",IF($T171<=0.34,"Ate 34%","Acima de 34%")) -> Acima de 34% | AG171: =IF($S171<=0.39,"Ate 39%",IF($S171<=0.41,"Ate 41%","Acima de 41%")) -> Acima de 41%

Sheet Planilha2
B4: QTD PROJETOS COMITÊ
B5: TRI | C5: FAIXA 1 | D5: FAIXA 2 | E5: FAIXA 3 | F5: TOTAL
B6: 2025-1T | C6: =COUNTIFS(dados_filtrado!$AB:$AB,Planilha2!C$5,dados_filtrado!$AD:$AD,Planilha2!$B6) -> 5 | D6: =COUNTIFS(dados_filtrado!$AB:$AB,Planilha2!D$5,dados_filtrado!$AD:$AD,Planilha2!$B6) -> 7 | E6: =COUNTIFS(dados_filtrado!$AB:$AB,Planilha2!E$5,dados_filtrado!$AD:$AD,Planilha2!$B6) -> 3 | F6: =SUM(C6:E6) -> 15
B7: 2025-2T | C7: =COUNTIFS(dados_filtrado!$AB:$AB,Planilha2!C$5,dados_filtrado!$AD:$AD,Planilha2!$B7) -> 15 | D7: =COUNTIFS(dados_filtrado!$AB:$AB,Planilha2!D$5,dados_filtrado!$AD:$AD,Planilha2!$B7) -> 27 | E7: =COUNTIFS(dados_filtrado!$AB:$AB,Planilha2!E$5,dados_filtrado!$AD:$AD,Planilha2!$B7) -> 7 | F7: =SUM(C7:E7) -> 49
B8: 2025-3T | C8: =COUNTIFS(dados_filtrado!$AB:$AB,Planilha2!C$5,dados_filtrado!$AD:$AD,Planilha2!$B8) -> 4 | D8: =COUNTIFS(dados_filtrado!$AB:$AB,Planilha2!D$5,dados_filtrado!$AD:$AD,Planilha2!$B8) -> 20 | E8: =COUNTIFS(dados_filtrado!$AB:$AB,Planilha2!E$5,dados_filtrado!$AD:$AD,Planilha2!$B8) -> 10 | F8: =SUM(C8:E8) -> 34
B9: 2025-4T | C9: =COUNTIFS(dados_filtrado!$AB:$AB,Planilha2!C$5,dados_filtrado!$AD:$AD,Planilha2!$B9) -> 12 | D9: =COUNTIFS(dados_filtrado!$AB:$AB,Planilha2!D$5,dados_filtrado!$AD:$AD,Planilha2!$B9) -> 24 | E9: =COUNTIFS(dados_filtrado!$AB:$AB,Planilha2!E$5,dados_filtrado!$AD:$AD,Planilha2!$B9) -> 14 | F9: =SUM(C9:E9) -> 50
B10: 2026-1T | C10: =COUNTIFS(dados_filtrado!$AB:$AB,Planilha2!C$5,dados_filtrado!$AD:$AD,Planilha2!$B10) -> 8 | D10: =COUNTIFS(dados_filtrado!$AB:$AB,Planilha2!D$5,dados_filtrado!$AD:$AD,Planilha2!$B10) -> 6 | E10: =COUNTIFS(dados_filtrado!$AB:$AB,Planilha2!E$5,dados_filtrado!$AD:$AD,Planilha2!$B10) -> 8 | F10: =SUM(C10:E10) -> 22
B12: PREÇO RASO / CUSTO
B13: TRI | C13: FAIXA 1 | D13: FAIXA 2 | E13: FAIXA 3 | F13: TOTAL
B14: 2025-1T | C14: =AVERAGEIFS(dados_filtrado!$Z:$Z,dados_filtrado!$AB:$AB,Planilha2!C$5,dados_filtrado!$AD:$AD,Planilha2!$B14) -> 1.999608 | D14: =AVERAGEIFS(dados_filtrado!$Z:$Z,dados_filtrado!$AB:$AB,Planilha2!D$5,dados_filtrado!$AD:$AD,Planilha2!$B14) -> 2.1464421 | E14: =AVERAGEIFS(dados_filtrado!$Z:$Z,dados_filtrado!$AB:$AB,Planilha2!E$5,dados_filtrado!$AD:$AD,Planilha2!$B14) -> 2.5027137 | F14: =AVERAGEIFS(dados_filtrado!$Z:$Z,dados_filtrado!$AD:$AD,Planilha2!$B14) -> 2.1687517
B15: 2025-2T | C15: =AVERAGEIFS(dados_filtrado!$Z:$Z,dados_filtrado!$AB:$AB,Planilha2!C$5,dados_filtrado!$AD:$AD,Planilha2!$B15) -> 2.0045121 | D15: =AVERAGEIFS(dados_filtrado!$Z:$Z,dados_filtrado!$AB:$AB,Planilha2!D$5,dados_filtrado!$AD:$AD,Planilha2!$B15) -> 2.1121961 | E15: =AVERAGEIFS(dados_filtrado!$Z:$Z,dados_filtrado!$AB:$AB,Planilha2!E$5,dados_filtrado!$AD:$AD,Planilha2!$B15) -> 2.3511835 | F15: =AVERAGEIFS(dados_filtrado!$Z:$Z,dados_filtrado!$AD:$AD,Planilha2!$B15) -> 2.1133727
B16: 2025-3T | C16: =AVERAGEIFS(dados_filtrado!$Z:$Z,dados_filtrado!$AB:$AB,Planilha2!C$5,dados_filtrado!$AD:$AD,Planilha2!$B16) -> 2.0961373 | D16: =AVERAGEIFS(dados_filtrado!$Z:$Z,dados_filtrado!$AB:$AB,Planilha2!D$5,dados_filtrado!$AD:$AD,Planilha2!$B16) -> 2.1419669 | E16: =AVERAGEIFS(dados_filtrado!$Z:$Z,dados_filtrado!$AB:$AB,Planilha2!E$5,dados_filtrado!$AD:$AD,Planilha2!$B16) -> 2.3355619 | F16: =AVERAGEIFS(dados_filtrado!$Z:$Z,dados_filtrado!$AD:$AD,Planilha2!$B16) -> 2.1935149
B17: 2025-4T | C17: =AVERAGEIFS(dados_filtrado!$Z:$Z,dados_filtrado!$AB:$AB,Planilha2!C$5,dados_filtrado!$AD:$AD,Planilha2!$B17) -> 2.0230218 | D17: =AVERAGEIFS(dados_filtrado!$Z:$Z,dados_filtrado!$AB:$AB,Planilha2!D$5,dados_filtrado!$AD:$AD,Planilha2!$B17) -> 2.1212831 | E17: =AVERAGEIFS(dados_filtrado!$Z:$Z,dados_filtrado!$AB:$AB,Planilha2!E$5,dados_filtrado!$AD:$AD,Planilha2!$B17) -> 2.3453068 | F17: =AVERAGEIFS(dados_filtrado!$Z:$Z,dados_filtrado!$AD:$AD,Planilha2!$B17) -> 2.160427
B18: 2026-1T | C18: =AVERAGEIFS(dados_filtrado!$Z:$Z,dados_filtrado!$AB:$AB,Planilha2!C$5,dados_filtrado!$AD:$AD,Planilha2!$B18) -> 1.942067 | D18: =AVERAGEIFS(dados_filtrado!$Z:$Z,dados_filtrado!$AB:$AB,Planilha2!D$5,dados_filtrado!$AD:$AD,Planilha2!$B18) -> 2.132478 | E18: =AVERAGEIFS(dados_filtrado!$Z:$Z,dados_filtrado!$AB:$AB,Planilha2!E$5,dados_filtrado!$AD:$AD,Planilha2!$B18) -> 2.4663687 | F18: =AVERAGEIFS(dados_filtrado!$Z:$Z,dados_filtrado!$AD:$AD,Planilha2!$B18) -> 2.1846524
I28: MARGEM RASA ECONÔMICA | P28: MARGEM BRUTA ECONÔMICA | W28: MARGEM RASA ECONÔMICA | AE28: MARGEM BRUTA ECONÔMICA
H29: Dif. LI régua | I29: TOTAL | J29: Ate 32% | K29: Ate 34% | L29: Acima de 34% | M29: Total | O29: Dif. LI régua | P29: TOTAL | Q29: Ate 39% | R29: Ate 41% | S29: Acima de 41% | T29: Total | V29: Dif. LI régua | W29: TOTAL | X29: Quantidade | Y29: Ate 32% | Z29: Ate 34% | AA29: Acima de 34% | AB29: Total | AD29: Dif. LI régua | AE29: TOTAL | AF29: Quantidade | AG29: Ate 39% | AH29: Ate 41% | AI29: Acima de 41% | AJ29: Total
I30: Até +0,5% | J30: =COUNTIFS(dados_filtrado!$AF:$AF,Planilha2!J$29,dados_filtrado!$AE:$AE,Planilha2!$I30) -> 37 | K30: =COUNTIFS(dados_filtrado!$AF:$AF,Planilha2!K$29,dados_filtrado!$AE:$AE,Planilha2!$I30) -> 39 | L30: =COUNTIFS(dados_filtrado!$AF:$AF,Planilha2!L$29,dados_filtrado!$AE:$AE,Planilha2!$I30) -> 26 | M30: =SUM(J30:L30) -> 102 | P30: Até +0,5% | Q30: =COUNTIFS(dados_filtrado!$AG:$AG,Planilha2!Q$29,dados_filtrado!$AE:$AE,Planilha2!$I30) -> 46 | R30: =COUNTIFS(dados_filtrado!$AG:$AG,Planilha2!R$29,dados_filtrado!$AE:$AE,Planilha2!$I30) -> 40 | S30: =COUNTIFS(dados_filtrado!$AG:$AG,Planilha2!S$29,dados_filtrado!$AE:$AE,Planilha2!$I30) -> 16 | T30: =SUM(Q30:S30) -> 102 | W30: Até +0,5% | X30: =T30 -> 102 | Y30: =J30/$X30 -> 0.3627451 | Z30: =K30/$X30 -> 0.38235294 | AA30: =L30/$X30 -> 0.25490196 | AB30: =M30/$X30 -> 1 | AE30: Até +0,5% | AF30: =X30 -> 102 | AG30: =Q30/$AF30 -> 0.45098039 | AH30: =R30/$AF30 -> 0.39215686 | AI30: =S30/$AF30 -> 0.15686275 | AJ30: =T30/$AF30 -> 1
I31: Ate +1% | J31: =COUNTIFS(dados_filtrado!$AF:$AF,Planilha2!J$29,dados_filtrado!$AE:$AE,Planilha2!$I31) -> 2 | K31: =COUNTIFS(dados_filtrado!$AF:$AF,Planilha2!K$29,dados_filtrado!$AE:$AE,Planilha2!$I31) -> 5 | L31: =COUNTIFS(dados_filtrado!$AF:$AF,Planilha2!L$29,dados_filtrado!$AE:$AE,Planilha2!$I31) -> 2 | M31: =SUM(J31:L31) -> 9 | P31: Ate +1% | Q31: =COUNTIFS(dados_filtrado!$AG:$AG,Planilha2!Q$29,dados_filtrado!$AE:$AE,Planilha2!$I31) -> 3 | R31: =COUNTIFS(dados_filtrado!$AG:$AG,Planilha2!R$29,dados_filtrado!$AE:$AE,Planilha2!$I31) -> 4 | S31: =COUNTIFS(dados_filtrado!$AG:$AG,Planilha2!S$29,dados_filtrado!$AE:$AE,Planilha2!$I31) -> 2 | T31: =SUM(Q31:S31) -> 9 | W31: Ate +1% | X31: =T31 -> 9 | Y31: =J31/$X31 -> 0.22222222 | Z31: =K31/$X31 -> 0.55555556 | AA31: =L31/$X31 -> 0.22222222 | AB31: =M31/$X31 -> 1 | AE31: Ate +1% | AF31: =X31 -> 9 | AG31: =Q31/$AF31 -> 0.33333333 | AH31: =R31/$AF31 -> 0.44444444 | AI31: =S31/$AF31 -> 0.22222222 | AJ31: =T31/$AF31 -> 1
I32: Acima de +1% | J32: =COUNTIFS(dados_filtrado!$AF:$AF,Planilha2!J$29,dados_filtrado!$AE:$AE,Planilha2!$I32) -> 4 | K32: =COUNTIFS(dados_filtrado!$AF:$AF,Planilha2!K$29,dados_filtrado!$AE:$AE,Planilha2!$I32) -> 13 | L32: =COUNTIFS(dados_filtrado!$AF:$AF,Planilha2!L$29,dados_filtrado!$AE:$AE,Planilha2!$I32) -> 42 | M32: =SUM(J32:L32) -> 59 | P32: Acima de +1% | Q32: =COUNTIFS(dados_filtrado!$AG:$AG,Planilha2!Q$29,dados_filtrado!$AE:$AE,Planilha2!$I32) -> 6 | R32: =COUNTIFS(dados_filtrado!$AG:$AG,Planilha2!R$29,dados_filtrado!$AE:$AE,Planilha2!$I32) -> 13 | S32: =COUNTIFS(dados_filtrado!$AG:$AG,Planilha2!S$29,dados_filtrado!$AE:$AE,Planilha2!$I32) -> 40 | T32: =SUM(Q32:S32) -> 59 | W32: Acima de +1% | X32: =T32 -> 59 | Y32: =J32/$X32 -> 0.06779661 | Z32: =K32/$X32 -> 0.22033898 | AA32: =L32/$X32 -> 0.71186441 | AB32: =M32/$X32 -> 1 | AE32: Acima de +1% | AF32: =X32 -> 59 | AG32: =Q32/$AF32 -> 0.10169492 | AH32: =R32/$AF32 -> 0.22033898 | AI32: =S32/$AF32 -> 0.6779661 | AJ32: =T32/$AF32 -> 1
I33: Total | J33: =SUM(J30:J32) -> 43 | K33: =SUM(K30:K32) -> 57 | L33: =SUM(L30:L32) -> 70 | M33: =SUM(J33:L33) -> 170 | P33: Total | Q33: =SUM(Q30:Q32) -> 55 | R33: =SUM(R30:R32) -> 57 | S33: =SUM(S30:S32) -> 58 | T33: =SUM(Q33:S33) -> 170 | W33: Total | X33: =T33 -> 170 | Y33: =J33/$X33 -> 0.25294118 | Z33: =K33/$X33 -> 0.33529412 | AA33: =L33/$X33 -> 0.41176471 | AB33: =M33/$X33 -> 1 | AE33: Total | AF33: =X33 -> 170 | AG33: =Q33/$AF33 -> 0.32352941 | AH33: =R33/$AF33 -> 0.33529412 | AI33: =S33/$AF33 -> 0.34117647 | AJ33: =T33/$AF33 -> 1
X34: =X33/X$33 -> 1 | AF34: =X34 -> 1
I35: MARGEM RASA ECONÔMICA | P35: MARGEM BRUTA ECONÔMICA | W35: MARGEM RASA ECONÔMICA | AE35: MARGEM BRUTA ECONÔMICA
H36: Dif. LI régua | I36: FAIXA 1 | J36: Ate 32% | K36: Ate 34% | L36: Acima de 34% | M36: Total | O36: Dif. LI régua | P36: FAIXA 1 | Q36: Ate 39% | R36: Ate 41% | S36: Acima de 41% | T36: Total | V36: Dif. LI régua | W36: FAIXA 1 | X36: Quantidade | Y36: Ate 32% | Z36: Ate 34% | AA36: Acima de 34% | AB36: Total | AD36: Dif. LI régua | AE36: FAIXA 1 | AF36: Quantidade | AG36: Ate 39% | AH36: Ate 41% | AI36: Acima de 41% | AJ36: Total
I37: Até +0,5% | J37: =COUNTIFS(dados_filtrado!$AF:$AF,Planilha2!J$29,dados_filtrado!$AE:$AE,Planilha2!$I37,dados_filtrado!$AB:$AB,Planilha2!I36) -> 11 | K37: =COUNTIFS(dados_filtrado!$AF:$AF,Planilha2!K$29,dados_filtrado!$AE:$AE,Planilha2!$I37,dados_filtrado!$AB:$AB,Planilha2!I36) -> 7 | L37: =COUNTIFS(dados_filtrado!$AF:$AF,Planilha2!L$29,dados_filtrado!$AE:$AE,Planilha2!$I37,dados_filtrado!$AB:$AB,Planilha2!I36) -> 1 | M37: =SUM(J37:L37) -> 19 | P37: Até +0,5% | Q37: =COUNTIFS(dados_filtrado!$AG:$AG,Planilha2!Q$29,dados_filtrado!$AE:$AE,Planilha2!$I37,dados_filtrado!$AB:$AB,Planilha2!P36) -> 8 | R37: =COUNTIFS(dados_filtrado!$AG:$AG,Planilha2!R$29,dados_filtrado!$AE:$AE,Planilha2!$I37,dados_filtrado!$AB:$AB,Planilha2!P36) -> 9 | S37: =COUNTIFS(dados_filtrado!$AG:$AG,Planilha2!S$29,dados_filtrado!$AE:$AE,Planilha2!$I37,dados_filtrado!$AB:$AB,Planilha2!P36) -> 2 | T37: =SUM(Q37:S37) -> 19 | W37: Até +0,5% | X37: =T37 -> 19 | Y37: =J37/$X37 -> 0.57894737 | Z37: =K37/$X37 -> 0.36842105 | AA37: =L37/$X37 -> 0.052631579 | AB37: =M37/$X37 -> 1 | AE37: Até +0,5% | AF37: =X37 -> 19 | AG37: =Q37/$AF37 -> 0.42105263 | AH37: =R37/$AF37 -> 0.47368421 | AI37: =S37/$AF37 -> 0.10526316 | AJ37: =T37/$AF37 -> 1
I38: Ate +1% | J38: =COUNTIFS(dados_filtrado!$AF:$AF,Planilha2!J$29,dados_filtrado!$AE:$AE,Planilha2!$I38,dados_filtrado!$AB:$AB,Planilha2!I36) -> 1 | K38: =COUNTIFS(dados_filtrado!$AF:$AF,Planilha2!K$29,dados_filtrado!$AE:$AE,Planilha2!$I38,dados_filtrado!$AB:$AB,Planilha2!I36) -> 2 | L38: =COUNTIFS(dados_filtrado!$AF:$AF,Planilha2!L$29,dados_filtrado!$AE:$AE,Planilha2!$I38,dados_filtrado!$AB:$AB,Planilha2!I36) -> 0 | M38: =SUM(J38:L38) -> 3 | P38: Ate +1% | Q38: =COUNTIFS(dados_filtrado!$AG:$AG,Planilha2!Q$29,dados_filtrado!$AE:$AE,Planilha2!$I38,dados_filtrado!$AB:$AB,Planilha2!P36) -> 1 | R38: =COUNTIFS(dados_filtrado!$AG:$AG,Planilha2!R$29,dados_filtrado!$AE:$AE,Planilha2!$I38,dados_filtrado!$AB:$AB,Planilha2!P36) -> 2 | S38: =COUNTIFS(dados_filtrado!$AG:$AG,Planilha2!S$29,dados_filtrado!$AE:$AE,Planilha2!$I38,dados_filtrado!$AB:$AB,Planilha2!P36) -> 0 | T38: =SUM(Q38:S38) -> 3 | W38: Ate +1% | X38: =T38 -> 3 | Y38: =J38/$X38 -> 0.33333333 | Z38: =K38/$X38 -> 0.66666667 | AA38: =L38/$X38 -> 0 | AB38: =M38/$X38 -> 1 | AE38: Ate +1% | AF38: =X38 -> 3 | AG38: =Q38/$AF38 -> 0.33333333 | AH38: =R38/$AF38 -> 0.66666667 | AI38: =S38/$AF38 -> 0 | AJ38: =T38/$AF38 -> 1
I39: Acima de +1% | J39: =COUNTIFS(dados_filtrado!$AF:$AF,Planilha2!J$29,dados_filtrado!$AE:$AE,Planilha2!$I39,dados_filtrado!$AB:$AB,Planilha2!I36) -> 2 | K39: =COUNTIFS(dados_filtrado!$AF:$AF,Planilha2!K$29,dados_filtrado!$AE:$AE,Planilha2!$I39,dados_filtrado!$AB:$AB,Planilha2!I36) -> 6 | L39: =COUNTIFS(dados_filtrado!$AF:$AF,Planilha2!L$29,dados_filtrado!$AE:$AE,Planilha2!$I39,dados_filtrado!$AB:$AB,Planilha2!I36) -> 14 | M39: =SUM(J39:L39) -> 22 | P39: Acima de +1% | Q39: =COUNTIFS(dados_filtrado!$AG:$AG,Planilha2!Q$29,dados_filtrado!$AE:$AE,Planilha2!$I39,dados_filtrado!$AB:$AB,Planilha2!P36) -> 3 | R39: =COUNTIFS(dados_filtrado!$AG:$AG,Planilha2!R$29,dados_filtrado!$AE:$AE,Planilha2!$I39,dados_filtrado!$AB:$AB,Planilha2!P36) -> 4 | S39: =COUNTIFS(dados_filtrado!$AG:$AG,Planilha2!S$29,dados_filtrado!$AE:$AE,Planilha2!$I39,dados_filtrado!$AB:$AB,Planilha2!P36) -> 15 | T39: =SUM(Q39:S39) -> 22 | W39: Acima de +1% | X39: =T39 -> 22 | Y39: =J39/$X39 -> 0.090909091 | Z39: =K39/$X39 -> 0.27272727 | AA39: =L39/$X39 -> 0.63636364 | AB39: =M39/$X39 -> 1 | AE39: Acima de +1% | AF39: =X39 -> 22 | AG39: =Q39/$AF39 -> 0.13636364 | AH39: =R39/$AF39 -> 0.18181818 | AI39: =S39/$AF39 -> 0.68181818 | AJ39: =T39/$AF39 -> 1
I40: Total | J40: =SUM(J37:J39) -> 14 | K40: =SUM(K37:K39) -> 15 | L40: =SUM(L37:L39) -> 15 | M40: =SUM(J40:L40) -> 44 | P40: Total | Q40: =SUM(Q37:Q39) -> 12 | R40: =SUM(R37:R39) -> 15 | S40: =SUM(S37:S39) -> 17 | T40: =SUM(Q40:S40) -> 44 | W40: Total | X40: =T40 -> 44 | Y40: =J40/$X40 -> 0.31818182 | Z40: =K40/$X40 -> 0.34090909 | AA40: =L40/$X40 -> 0.34090909 | AB40: =M40/$X40 -> 1 | AE40: Total | AF40: =X40 -> 44 | AG40: =Q40/$AF40 -> 0.27272727 | AH40: =R40/$AF40 -> 0.34090909 | AI40: =S40/$AF40 -> 0.38636364 | AJ40: =T40/$AF40 -> 1
X41: =X40/X$33 -> 0.25882353
I42: MARGEM RASA ECONÔMICA | P42: MARGEM BRUTA ECONÔMICA | W42: MARGEM RASA ECONÔMICA | AE42: MARGEM BRUTA ECONÔMICA
H43: Dif. LI régua | I43: FAIXA 2 | J43: Ate 32% | K43: Ate 34% | L43: Acima de 34% | M43: Total | O43: Dif. LI régua | P43: FAIXA 2 | Q43: Ate 39% | R43: Ate 41% | S43: Acima de 41% | T43: Total | V43: Dif. LI régua | W43: FAIXA 2 | X43: Quantidade | Y43: Ate 32% | Z43: Ate 34% | AA43: Acima de 34% | AB43: Total | AD43: Dif. LI régua | AE43: FAIXA 2 | AF43: Quantidade | AG43: Ate 39% | AH43: Ate 41% | AI43: Acima de 41% | AJ43: Total
I44: Até +0,5% | J44: =COUNTIFS(dados_filtrado!$AF:$AF,Planilha2!J$29,dados_filtrado!$AE:$AE,Planilha2!$I44,dados_filtrado!$AB:$AB,Planilha2!I43) -> 23 | K44: =COUNTIFS(dados_filtrado!$AF:$AF,Planilha2!K$29,dados_filtrado!$AE:$AE,Planilha2!$I44,dados_filtrado!$AB:$AB,Planilha2!I43) -> 20 | L44: =COUNTIFS(dados_filtrado!$AF:$AF,Planilha2!L$29,dados_filtrado!$AE:$AE,Planilha2!$I44,dados_filtrado!$AB:$AB,Planilha2!I43) -> 14 | M44: =SUM(J44:L44) -> 57 | P44: Até +0,5% | Q44: =COUNTIFS(dados_filtrado!$AG:$AG,Planilha2!Q$29,dados_filtrado!$AE:$AE,Planilha2!$I44,dados_filtrado!$AB:$AB,Planilha2!P43) -> 29 | R44: =COUNTIFS(dados_filtrado!$AG:$AG,Planilha2!R$29,dados_filtrado!$AE:$AE,Planilha2!$I44,dados_filtrado!$AB:$AB,Planilha2!P43) -> 19 | S44: =COUNTIFS(dados_filtrado!$AG:$AG,Planilha2!S$29,dados_filtrado!$AE:$AE,Planilha2!$I44,dados_filtrado!$AB:$AB,Planilha2!P43) -> 9 | T44: =SUM(Q44:S44) -> 57 | W44: Até +0,5% | X44: =T44 -> 57 | Y44: =J44/$X44 -> 0.40350877 | Z44: =K44/$X44 -> 0.35087719 | AA44: =L44/$X44 -> 0.24561404 | AB44: =M44/$X44 -> 1 | AE44: Até +0,5% | AF44: =X44 -> 57 | AG44: =Q44/$AF44 -> 0.50877193 | AH44: =R44/$AF44 -> 0.33333333 | AI44: =S44/$AF44 -> 0.15789474 | AJ44: =T44/$AF44 -> 1
I45: Ate +1% | J45: =COUNTIFS(dados_filtrado!$AF:$AF,Planilha2!J$29,dados_filtrado!$AE:$AE,Planilha2!$I45,dados_filtrado!$AB:$AB,Planilha2!I43) -> 1 | K45: =COUNTIFS(dados_filtrado!$AF:$AF,Planilha2!K$29,dados_filtrado!$AE:$AE,Planilha2!$I45,dados_filtrado!$AB:$AB,Planilha2!I43) -> 1 | L45: =COUNTIFS(dados_filtrado!$AF:$AF,Planilha2!L$29,dados_filtrado!$AE:$AE,Planilha2!$I45,dados_filtrado!$AB:$AB,Planilha2!I43) -> 0 | M45: =SUM(J45:L45) -> 2 | P45: Ate +1% | Q45: =COUNTIFS(dados_filtrado!$AG:$AG,Planilha2!Q$29,dados_filtrado!$AE:$AE,Planilha2!$I45,dados_filtrado!$AB:$AB,Planilha2!P43) -> 1 | R45: =COUNTIFS(dados_filtrado!$AG:$AG,Planilha2!R$29,dados_filtrado!$AE:$AE,Planilha2!$I45,dados_filtrado!$AB:$AB,Planilha2!P43) -> 1 | S45: =COUNTIFS(dados_filtrado!$AG:$AG,Planilha2!S$29,dados_filtrado!$AE:$AE,Planilha2!$I45,dados_filtrado!$AB:$AB,Planilha2!P43) -> 0 | T45: =SUM(Q45:S45) -> 2 | W45: Ate +1% | X45: =T45 -> 2 | Y45: =J45/$X45 -> 0.5 | Z45: =K45/$X45 -> 0.5 | AA45: =L45/$X45 -> 0 | AB45: =M45/$X45 -> 1 | AE45: Ate +1% | AF45: =X45 -> 2 | AG45: =Q45/$AF45 -> 0.5 | AH45: =R45/$AF45 -> 0.5 | AI45: =S45/$AF45 -> 0 | AJ45: =T45/$AF45 -> 1
I46: Acima de +1% | J46: =COUNTIFS(dados_filtrado!$AF:$AF,Planilha2!J$29,dados_filtrado!$AE:$AE,Planilha2!$I46,dados_filtrado!$AB:$AB,Planilha2!I43) -> 1 | K46: =COUNTIFS(dados_filtrado!$AF:$AF,Planilha2!K$29,dados_filtrado!$AE:$AE,Planilha2!$I46,dados_filtrado!$AB:$AB,Planilha2!I43) -> 7 | L46: =COUNTIFS(dados_filtrado!$AF:$AF,Planilha2!L$29,dados_filtrado!$AE:$AE,Planilha2!$I46,dados_filtrado!$AB:$AB,Planilha2!I43) -> 17 | M46: =SUM(J46:L46) -> 25 | P46: Acima de +1% | Q46: =COUNTIFS(dados_filtrado!$AG:$AG,Planilha2!Q$29,dados_filtrado!$AE:$AE,Planilha2!$I46,dados_filtrado!$AB:$AB,Planilha2!P43) -> 2 | R46: =COUNTIFS(dados_filtrado!$AG:$AG,Planilha2!R$29,dados_filtrado!$AE:$AE,Planilha2!$I46,dados_filtrado!$AB:$AB,Planilha2!P43) -> 7 | S46: =COUNTIFS(dados_filtrado!$AG:$AG,Planilha2!S$29,dados_filtrado!$AE:$AE,Planilha2!$I46,dados_filtrado!$AB:$AB,Planilha2!P43) -> 16 | T46: =SUM(Q46:S46) -> 25 | W46: Acima de +1% | X46: =T46 -> 25 | Y46: =J46/$X46 -> 0.04 | Z46: =K46/$X46 -> 0.28 | AA46: =L46/$X46 -> 0.68 | AB46: =M46/$X46 -> 1 | AE46: Acima de +1% | AF46: =X46 -> 25 | AG46: =Q46/$AF46 -> 0.08 | AH46: =R46/$AF46 -> 0.28 | AI46: =S46/$AF46 -> 0.64 | AJ46: =T46/$AF46 -> 1
I47: Total | J47: =SUM(J44:J46) -> 25 | K47: =SUM(K44:K46) -> 28 | L47: =SUM(L44:L46) -> 31 | M47: =SUM(J47:L47) -> 84 | P47: Total | Q47: =SUM(Q44:Q46) -> 32 | R47: =SUM(R44:R46) -> 27 | S47: =SUM(S44:S46) -> 25 | T47: =SUM(Q47:S47) -> 84 | W47: Total | X47: =T47 -> 84 | Y47: =J47/$X47 -> 0.29761905 | Z47: =K47/$X47 -> 0.33333333 | AA47: =L47/$X47 -> 0.36904762 | AB47: =M47/$X47 -> 1 | AE47: Total | AF47: =X47 -> 84 | AG47: =Q47/$AF47 -> 0.38095238 | AH47: =R47/$AF47 -> 0.32142857 | AI47: =S47/$AF47 -> 0.29761905 | AJ47: =T47/$AF47 -> 1
X48: =X47/X$33 -> 0.49411765
I49: MARGEM RASA ECONÔMICA | P49: MARGEM BRUTA ECONÔMICA | W49: MARGEM RASA ECONÔMICA | AE49: MARGEM BRUTA ECONÔMICA
H50: Dif. LI régua | I50: FAIXA 3 | J50: Ate 32% | K50: Ate 34% | L50: Acima de 34% | M50: Total | O50: Dif. LI régua | P50: FAIXA 3 | Q50: Ate 39% | R50: Ate 41% | S50: Acima de 41% | T50: Total | V50: Dif. LI régua | W50: FAIXA 3 | X50: Quantidade | Y50: Ate 32% | Z50: Ate 34% | AA50: Acima de 34% | AB50: Total | AD50: Dif. LI régua | AE50: FAIXA 3 | AF50: Quantidade | AG50: Ate 39% | AH50: Ate 41% | AI50: Acima de 41% | AJ50: Total
I51: Até +0,5% | J51: =COUNTIFS(dados_filtrado!$AF:$AF,Planilha2!J$29,dados_filtrado!$AE:$AE,Planilha2!$I51,dados_filtrado!$AB:$AB,Planilha2!I50) -> 3 | K51: =COUNTIFS(dados_filtrado!$AF:$AF,Planilha2!K$29,dados_filtrado!$AE:$AE,Planilha2!$I51,dados_filtrado!$AB:$AB,Planilha2!I50) -> 12 | L51: =COUNTIFS(dados_filtrado!$AF:$AF,Planilha2!L$29,dados_filtrado!$AE:$AE,Planilha2!$I51,dados_filtrado!$AB:$AB,Planilha2!I50) -> 11 | M51: =SUM(J51:L51) -> 26 | P51: Até +0,5% | Q51: =COUNTIFS(dados_filtrado!$AG:$AG,Planilha2!Q$29,dados_filtrado!$AE:$AE,Planilha2!$I51,dados_filtrado!$AB:$AB,Planilha2!P50) -> 9 | R51: =COUNTIFS(dados_filtrado!$AG:$AG,Planilha2!R$29,dados_filtrado!$AE:$AE,Planilha2!$I51,dados_filtrado!$AB:$AB,Planilha2!P50) -> 12 | S51: =COUNTIFS(dados_filtrado!$AG:$AG,Planilha2!S$29,dados_filtrado!$AE:$AE,Planilha2!$I51,dados_filtrado!$AB:$AB,Planilha2!P50) -> 5 | T51: =SUM(Q51:S51) -> 26 | W51: Até +0,5% | X51: =T51 -> 26 | Y51: =J51/$X51 -> 0.11538462 | Z51: =K51/$X51 -> 0.46153846 | AA51: =L51/$X51 -> 0.42307692 | AB51: =M51/$X51 -> 1 | AE51: Até +0,5% | AF51: =X51 -> 26 | AG51: =Q51/$AF51 -> 0.34615385 | AH51: =R51/$AF51 -> 0.46153846 | AI51: =S51/$AF51 -> 0.19230769 | AJ51: =T51/$AF51 -> 1
I52: Ate +1% | J52: =COUNTIFS(dados_filtrado!$AF:$AF,Planilha2!J$29,dados_filtrado!$AE:$AE,Planilha2!$I52,dados_filtrado!$AB:$AB,Planilha2!I50) -> 0 | K52: =COUNTIFS(dados_filtrado!$AF:$AF,Planilha2!K$29,dados_filtrado!$AE:$AE,Planilha2!$I52,dados_filtrado!$AB:$AB,Planilha2!I50) -> 2 | L52: =COUNTIFS(dados_filtrado!$AF:$AF,Planilha2!L$29,dados_filtrado!$AE:$AE,Planilha2!$I52,dados_filtrado!$AB:$AB,Planilha2!I50) -> 2 | M52: =SUM(J52:L52) -> 4 | P52: Ate +1% | Q52: =COUNTIFS(dados_filtrado!$AG:$AG,Planilha2!Q$29,dados_filtrado!$AE:$AE,Planilha2!$I52,dados_filtrado!$AB:$AB,Planilha2!P50) -> 1 | R52: =COUNTIFS(dados_filtrado!$AG:$AG,Planilha2!R$29,dados_filtrado!$AE:$AE,Planilha2!$I52,dados_filtrado!$AB:$AB,Planilha2!P50) -> 1 | S52: =COUNTIFS(dados_filtrado!$AG:$AG,Planilha2!S$29,dados_filtrado!$AE:$AE,Planilha2!$I52,dados_filtrado!$AB:$AB,Planilha2!P50) -> 2 | T52: =SUM(Q52:S52) -> 4 | W52: Ate +1% | X52: =T52 -> 4 | Y52: =J52/$X52 -> 0 | Z52: =K52/$X52 -> 0.5 | AA52: =L52/$X52 -> 0.5 | AB52: =M52/$X52 -> 1 | AE52: Ate +1% | AF52: =X52 -> 4 | AG52: =Q52/$AF52 -> 0.25 | AH52: =R52/$AF52 -> 0.25 | AI52: =S52/$AF52 -> 0.5 | AJ52: =T52/$AF52 -> 1
I53: Acima de +1% | J53: =COUNTIFS(dados_filtrado!$AF:$AF,Planilha2!J$29,dados_filtrado!$AE:$AE,Planilha2!$I53,dados_filtrado!$AB:$AB,Planilha2!I50) -> 1 | K53: =COUNTIFS(dados_filtrado!$AF:$AF,Planilha2!K$29,dados_filtrado!$AE:$AE,Planilha2!$I53,dados_filtrado!$AB:$AB,Planilha2!I50) -> 0 | L53: =COUNTIFS(dados_filtrado!$AF:$AF,Planilha2!L$29,dados_filtrado!$AE:$AE,Planilha2!$I53,dados_filtrado!$AB:$AB,Planilha2!I50) -> 11 | M53: =SUM(J53:L53) -> 12 | P53: Acima de +1% | Q53: =COUNTIFS(dados_filtrado!$AG:$AG,Planilha2!Q$29,dados_filtrado!$AE:$AE,Planilha2!$I53,dados_filtrado!$AB:$AB,Planilha2!P50) -> 1 | R53: =COUNTIFS(dados_filtrado!$AG:$AG,Planilha2!R$29,dados_filtrado!$AE:$AE,Planilha2!$I53,dados_filtrado!$AB:$AB,Planilha2!P50) -> 2 | S53: =COUNTIFS(dados_filtrado!$AG:$AG,Planilha2!S$29,dados_filtrado!$AE:$AE,Planilha2!$I53,dados_filtrado!$AB:$AB,Planilha2!P50) -> 9 | T53: =SUM(Q53:S53) -> 12 | W53: Acima de +1% | X53: =T53 -> 12 | Y53: =J53/$X53 -> 0.083333333 | Z53: =K53/$X53 -> 0 | AA53: =L53/$X53 -> 0.91666667 | AB53: =M53/$X53 -> 1 | AE53: Acima de +1% | AF53: =X53 -> 12 | AG53: =Q53/$AF53 -> 0.083333333 | AH53: =R53/$AF53 -> 0.16666667 | AI53: =S53/$AF53 -> 0.75 | AJ53: =T53/$AF53 -> 1
I54: Total | J54: =SUM(J51:J53) -> 4 | K54: =SUM(K51:K53) -> 14 | L54: =SUM(L51:L53) -> 24 | M54: =SUM(J54:L54) -> 42 | P54: Total | Q54: =SUM(Q51:Q53) -> 11 | R54: =SUM(R51:R53) -> 15 | S54: =SUM(S51:S53) -> 16 | T54: =SUM(Q54:S54) -> 42 | W54: Total | X54: =T54 -> 42 | Y54: =J54/$X54 -> 0.095238095 | Z54: =K54/$X54 -> 0.33333333 | AA54: =L54/$X54 -> 0.57142857 | AB54: =M54/$X54 -> 1 | AE54: Total | AF54: =X54 -> 42 | AG54: =Q54/$AF54 -> 0.26190476 | AH54: =R54/$AF54 -> 0.35714286 | AI54: =S54/$AF54 -> 0.38095238 | AJ54: =T54/$AF54 -> 1
X55: =X54/X$33 -> 0.24705882
